Workbook

Sheet Arrived Shipments
B1: Order Number | C1: Containers | D1: Bayan | E1: Shipment | F1: Supplier | G1: External Email | H1: Internal Email | I1: Transfer File sent? | J1: Transfer Qty Dispatched? | K1: Landing Cost | L1: Arrived | M1: Received | N1: Announcement Number | O1: PO | P1: Invoice | Q1: GRPO | R1: GRPO Date | S1: Days to be ready | T1: Sample Recieved ? | U1: Requested Date | V1: Recieved Date | W1: Prices updated in the system ? | X1: Remark | Y1: Shipment Status
A2: 1 | B2: =IFERROR(__xludf.DUMMYFUNCTION("INDEX(IMPORTRANGE(""https://docs.google.com/spreadsheets/d/1S7deMHO2waboU9dywpXeKIDfCmjiuAc0HUIsFpaXQq8/edit?gid=0#gid=0"", ""Tracking Shipments - PPTCO!o:o""), MATCH(D2, IMPORTRANGE(""https://docs.google.com/spreadsheets/d/1S7deMHO2waboU9dywpXeKIDfCmjiuA"&"c0HUIsFpaXQq8/edit?gid=0#gid=0"", ""Tracking Shipments - PPTCO!p:p""), 0))"),"PPT-73") -> PPT-73 | D2: 284599 | E2: JOSERA X9 | F2: Josera | G2: Before DSV | H2: Done | K2: Done | L2: Yes | M2: 45225 | N2: 0192023 | O2: 348 -> 358 | P2: 389 -> 399 | Q2: 348 -> 358 | R2: SMACC | S2: =IFERROR(IF(DATEDIF(M2,R2,"d")=0,"",DATEDIF(M2,R2,"d")),"") | T2: Not requested | W2: Done | Y2: Closed
A3: 2 | B3: =IFERROR(__xludf.DUMMYFUNCTION("INDEX(IMPORTRANGE(""https://docs.google.com/spreadsheets/d/1S7deMHO2waboU9dywpXeKIDfCmjiuAc0HUIsFpaXQq8/edit?gid=0#gid=0"", ""Tracking Shipments - PPTCO!o:o""), MATCH(D3, IMPORTRANGE(""https://docs.google.com/spreadsheets/d/1S7deMHO2waboU9dywpXeKIDfCmjiuA"&"c0HUIsFpaXQq8/edit?gid=0#gid=0"", ""Tracking Shipments - PPTCO!p:p""), 0))"),"PPT-29") -> PPT-29 | D3: 105972 | E3: KIT CAT - 400g | F3: Kit Cat | G3: Before DSV | H3: Done | K3: Done | L3: Yes | M3: 45236 | N3: 0192023 | O3: 361 | P3: 403 | Q3: 362 | R3: SMACC | S3: =IFERROR(IF(DATEDIF(M3,R3,"d")=0,"",DATEDIF(M3,R3,"d")),"") | T3: Received | W3: Done | Y3: Closed
A4: 3 | B4: =IFERROR(__xludf.DUMMYFUNCTION("INDEX(IMPORTRANGE(""https://docs.google.com/spreadsheets/d/1S7deMHO2waboU9dywpXeKIDfCmjiuAc0HUIsFpaXQq8/edit?gid=0#gid=0"", ""Tracking Shipments - PPTCO!o:o""), MATCH(D4, IMPORTRANGE(""https://docs.google.com/spreadsheets/d/1S7deMHO2waboU9dywpXeKIDfCmjiuA"&"c0HUIsFpaXQq8/edit?gid=0#gid=0"", ""Tracking Shipments - PPTCO!p:p""), 0))"),"PUUR ") -> PUUR | D4: 300854 | E4: LAROY - PUUR | F4: Laroy | G4: Before DSV | H4: Done | K4: Done | L4: Yes | M4: 45229 | N4: 212023 | O4: 359 | P4: 401 | Q4: 360 | R4: SMACC | S4: =IFERROR(IF(DATEDIF(M4,R4,"d")=0,"",DATEDIF(M4,R4,"d")),"") | W4: Done | Y4: Closed
A5: 4 | B5: =IFERROR(__xludf.DUMMYFUNCTION("INDEX(IMPORTRANGE(""https://docs.google.com/spreadsheets/d/1S7deMHO2waboU9dywpXeKIDfCmjiuAc0HUIsFpaXQq8/edit?gid=0#gid=0"", ""Tracking Shipments - PPTCO!o:o""), MATCH(D5, IMPORTRANGE(""https://docs.google.com/spreadsheets/d/1S7deMHO2waboU9dywpXeKIDfCmjiuA"&"c0HUIsFpaXQq8/edit?gid=0#gid=0"", ""Tracking Shipments - PPTCO!p:p""), 0))"),"PPT-39") -> PPT-39 | D5: 90377 | E5: KIT CAT - KCIT230042B/2-C | F5: Kit Cat | G5: Before DSV | H5: Done | K5: Done | L5: Yes | M5: 45200 | N5: 212023 | O5: 360 | P5: 400 | Q5: 361 | R5: SMACC | S5: =IFERROR(IF(DATEDIF(M5,R5,"d")=0,"",DATEDIF(M5,R5,"d")),"") | Y5: Closed
A6: 5 | B6: =IFERROR(__xludf.DUMMYFUNCTION("INDEX(IMPORTRANGE(""https://docs.google.com/spreadsheets/d/1S7deMHO2waboU9dywpXeKIDfCmjiuAc0HUIsFpaXQq8/edit?gid=0#gid=0"", ""Tracking Shipments - PPTCO!o:o""), MATCH(D6, IMPORTRANGE(""https://docs.google.com/spreadsheets/d/1S7deMHO2waboU9dywpXeKIDfCmjiuA"&"c0HUIsFpaXQq8/edit?gid=0#gid=0"", ""Tracking Shipments - PPTCO!p:p""), 0))"),"PPT-51") -> PPT-51 | D6: 101368 | E6: SCHESIR - 901104 | F6: Schesir | G6: Before DSV | H6: Done | K6: Done | L6: Yes | M6: 45225 | N6: 0192023 | O6: 347 | P6: 388 | Q6: 347 | R6: SMACC | S6: =IFERROR(IF(DATEDIF(M6,R6,"d")=0,"",DATEDIF(M6,R6,"d")),"") | Y6: Closed
A7: 6 | B7: =IFERROR(__xludf.DUMMYFUNCTION("INDEX(IMPORTRANGE(""https://docs.google.com/spreadsheets/d/1S7deMHO2waboU9dywpXeKIDfCmjiuAc0HUIsFpaXQq8/edit?gid=0#gid=0"", ""Tracking Shipments - PPTCO!o:o""), MATCH(D7, IMPORTRANGE(""https://docs.google.com/spreadsheets/d/1S7deMHO2waboU9dywpXeKIDfCmjiuA"&"c0HUIsFpaXQq8/edit?gid=0#gid=0"", ""Tracking Shipments - PPTCO!p:p""), 0))"),"PPT-51") -> PPT-51 | D7: 101362 | E7: SCHESIR - 901105 | F7: Schesir | G7: Before DSV | H7: Done | K7: Done | L7: Yes | M7: 45225 | N7: 0192023 | O7: 346 | P7: 387 | Q7: 359 | R7: SMACC | S7: =IFERROR(IF(DATEDIF(M7,R7,"d")=0,"",DATEDIF(M7,R7,"d")),"") | Y7: Closed
A8: 7 | B8: =IFERROR(__xludf.DUMMYFUNCTION("INDEX(IMPORTRANGE(""https://docs.google.com/spreadsheets/d/1S7deMHO2waboU9dywpXeKIDfCmjiuAc0HUIsFpaXQq8/edit?gid=0#gid=0"", ""Tracking Shipments - PPTCO!o:o""), MATCH(D8, IMPORTRANGE(""https://docs.google.com/spreadsheets/d/1S7deMHO2waboU9dywpXeKIDfCmjiuA"&"c0HUIsFpaXQq8/edit?gid=0#gid=0"", ""Tracking Shipments - PPTCO!p:p""), 0))"),"PUUR ") -> PUUR | D8: 306682 | E8: LAROY - PUUR | F8: Laroy | G8: Before DSV | H8: Done | K8: Done | L8: Yes | M8: 45241 | N8: 212023 | O8: 363->365 | P8: 408->410 | Q8: 364->366 | R8: SMACC | S8: =IFERROR(IF(DATEDIF(M8,R8,"d")=0,"",DATEDIF(M8,R8,"d")),"") | W8: Done | Y8: Closed
A9: 8 | B9: =IFERROR(__xludf.DUMMYFUNCTION("INDEX(IMPORTRANGE(""https://docs.google.com/spreadsheets/d/1S7deMHO2waboU9dywpXeKIDfCmjiuAc0HUIsFpaXQq8/edit?gid=0#gid=0"", ""Tracking Shipments - PPTCO!o:o""), MATCH(D9, IMPORTRANGE(""https://docs.google.com/spreadsheets/d/1S7deMHO2waboU9dywpXeKIDfCmjiuA"&"c0HUIsFpaXQq8/edit?gid=0#gid=0"", ""Tracking Shipments - PPTCO!p:p""), 0))"),"N/A") -> N/A | D9: 104096 | E9: INNER MONGOLIA | F9: Inner Mongolia | G9: Before DSV | H9: Done | K9: Done | L9: Yes | M9: 45238 | N9: 212023 | O9: 366-> 369 | P9: 411 > 412 | Q9: 367-> 370 | R9: SMACC | S9: =IFERROR(IF(DATEDIF(M9,R9,"d")=0,"",DATEDIF(M9,R9,"d")),"") | W9: Done | Y9: Closed
A10: 9 | B10: =IFERROR(__xludf.DUMMYFUNCTION("INDEX(IMPORTRANGE(""https://docs.google.com/spreadsheets/d/1S7deMHO2waboU9dywpXeKIDfCmjiuAc0HUIsFpaXQq8/edit?gid=0#gid=0"", ""Tracking Shipments - PPTCO!o:o""), MATCH(D10, IMPORTRANGE(""https://docs.google.com/spreadsheets/d/1S7deMHO2waboU9dywpXeKIDfCmjiu"&"Ac0HUIsFpaXQq8/edit?gid=0#gid=0"", ""Tracking Shipments - PPTCO!p:p""), 0))"),"PPT-58") -> PPT-58 | D10: 106546 | E10: KCIT230134 - Yogurt | F10: Kit Cat | G10: Before DSV | H10: Done | K10: Done | L10: Yes | M10: 45241 | N10: 212023 | O10: 362 | P10: 407 | Q10: 363 | R10: SMACC | S10: =IFERROR(IF(DATEDIF(M10,R10,"d")=0,"",DATEDIF(M10,R10,"d")),"") | W10: Done | Y10: Closed
A11: 10 | B11: =IFERROR(__xludf.DUMMYFUNCTION("INDEX(IMPORTRANGE(""https://docs.google.com/spreadsheets/d/1S7deMHO2waboU9dywpXeKIDfCmjiuAc0HUIsFpaXQq8/edit?gid=0#gid=0"", ""Tracking Shipments - PPTCO!o:o""), MATCH(D11, IMPORTRANGE(""https://docs.google.com/spreadsheets/d/1S7deMHO2waboU9dywpXeKIDfCmjiu"&"Ac0HUIsFpaXQq8/edit?gid=0#gid=0"", ""Tracking Shipments - PPTCO!p:p""), 0))"),"SA001-2023") -> SA001-2023 | D11: 115808 | E11: INABA | F11: INABA | G11: Before DSV | H11: Done | K11: Done | L11: Yes | M11: 45270 | N11: 232023 | O11: 374-375 | P11: 418-419 | Q11: 375-376 | R11: SMACC | S11: =IFERROR(IF(DATEDIF(M11,R11,"d")=0,"",DATEDIF(M11,R11,"d")),"") | W11: Done | Y11: Closed
A12: 11 | B12: =IFERROR(__xludf.DUMMYFUNCTION("INDEX(IMPORTRANGE(""https://docs.google.com/spreadsheets/d/1S7deMHO2waboU9dywpXeKIDfCmjiuAc0HUIsFpaXQq8/edit?gid=0#gid=0"", ""Tracking Shipments - PPTCO!o:o""), MATCH(D12, IMPORTRANGE(""https://docs.google.com/spreadsheets/d/1S7deMHO2waboU9dywpXeKIDfCmjiu"&"Ac0HUIsFpaXQq8/edit?gid=0#gid=0"", ""Tracking Shipments - PPTCO!p:p""), 0))"),"PPT-78") -> PPT-78 | D12: 115809 | E12: SANAL/NEDARMA | F12: Sanal | G12: Before DSV | H12: Done | K12: Done | L12: Yes | M12: 45265 | N12: 232023 | O12: 370 | P12: 417 | Q12: 371 | R12: SMACC | S12: =IFERROR(IF(DATEDIF(M12,R12,"d")=0,"",DATEDIF(M12,R12,"d")),"") | Y12: Closed
A13: 12 | B13: =IFERROR(__xludf.DUMMYFUNCTION("INDEX(IMPORTRANGE(""https://docs.google.com/spreadsheets/d/1S7deMHO2waboU9dywpXeKIDfCmjiuAc0HUIsFpaXQq8/edit?gid=0#gid=0"", ""Tracking Shipments - PPTCO!o:o""), MATCH(D13, IMPORTRANGE(""https://docs.google.com/spreadsheets/d/1S7deMHO2waboU9dywpXeKIDfCmjiu"&"Ac0HUIsFpaXQq8/edit?gid=0#gid=0"", ""Tracking Shipments - PPTCO!p:p""), 0))"),"PPT-75") -> PPT-75 | D13: 108588 | E13: Schesir -901280 | F13: Schesir | G13: Before DSV | H13: Done | K13: Done | L13: Yes | M13: 45248 | N13: 212023 | O13: 367 | P13: 414 | Q13: 368 | R13: SMACC | S13: =IFERROR(IF(DATEDIF(M13,R13,"d")=0,"",DATEDIF(M13,R13,"d")),"") | W13: Done | X13: Moayad Pricing | Y13: Closed
A14: 13 | B14: =IFERROR(__xludf.DUMMYFUNCTION("INDEX(IMPORTRANGE(""https://docs.google.com/spreadsheets/d/1S7deMHO2waboU9dywpXeKIDfCmjiuAc0HUIsFpaXQq8/edit?gid=0#gid=0"", ""Tracking Shipments - PPTCO!o:o""), MATCH(D14, IMPORTRANGE(""https://docs.google.com/spreadsheets/d/1S7deMHO2waboU9dywpXeKIDfCmjiu"&"Ac0HUIsFpaXQq8/edit?gid=0#gid=0"", ""Tracking Shipments - PPTCO!p:p""), 0))"),"N/A") -> N/A | D14: 108586 | E14: Schesir -901281 | F14: Schesir | G14: Before DSV | H14: Done | K14: Done | L14: Yes | M14: 44907 | N14: 212023 | O14: 368 | P14: 413 | Q14: 369 | R14: SMACC | S14: =IFERROR(IF(DATEDIF(M14,R14,"d")=0,"",DATEDIF(M14,R14,"d")),"") | W14: Done | X14: Moayad Pricing | Y14: Closed
A15: 14 | B15: =IFERROR(__xludf.DUMMYFUNCTION("INDEX(IMPORTRANGE(""https://docs.google.com/spreadsheets/d/1S7deMHO2waboU9dywpXeKIDfCmjiuAc0HUIsFpaXQq8/edit?gid=0#gid=0"", ""Tracking Shipments - PPTCO!o:o""), MATCH(D15, IMPORTRANGE(""https://docs.google.com/spreadsheets/d/1S7deMHO2waboU9dywpXeKIDfCmjiu"&"Ac0HUIsFpaXQq8/edit?gid=0#gid=0"", ""Tracking Shipments - PPTCO!p:p""), 0))"),"PPT-83") -> PPT-83 | D15: 341926 | E15: Witte Molen Expert | F15: Laroy | G15: Before DSV | H15: Done | K15: Done | L15: Yes | M15: 45270 | N15: 232023 | O15: 371 > 373 | P15: 420 > 422 | Q15: 372 > 374 | R15: SMACC | S15: =IFERROR(IF(DATEDIF(M15,R15,"d")=0,"",DATEDIF(M15,R15,"d")),"") | W15: Done | Y15: Closed
A16: 15 | B16: =IFERROR(__xludf.DUMMYFUNCTION("INDEX(IMPORTRANGE(""https://docs.google.com/spreadsheets/d/1S7deMHO2waboU9dywpXeKIDfCmjiuAc0HUIsFpaXQq8/edit?gid=0#gid=0"", ""Tracking Shipments - PPTCO!o:o""), MATCH(D16, IMPORTRANGE(""https://docs.google.com/spreadsheets/d/1S7deMHO2waboU9dywpXeKIDfCmjiu"&"Ac0HUIsFpaXQq8/edit?gid=0#gid=0"", ""Tracking Shipments - PPTCO!p:p""), 0))"),"N/A") -> N/A | D16: 117571 | E16: BUTCHERS | F16: Butchers | G16: Before DSV | H16: Done | K16: Done | L16: Yes | M16: 45273 | N16: 232023 | O16: 376-377 | P16: 423 - 424 | Q16: 377-378 | R16: SMACC | S16: =IFERROR(IF(DATEDIF(M16,R16,"d")=0,"",DATEDIF(M16,R16,"d")),"") | Y16: Closed
A17: 16 | B17: =IFERROR(__xludf.DUMMYFUNCTION("INDEX(IMPORTRANGE(""https://docs.google.com/spreadsheets/d/1S7deMHO2waboU9dywpXeKIDfCmjiuAc0HUIsFpaXQq8/edit?gid=0#gid=0"", ""Tracking Shipments - PPTCO!o:o""), MATCH(D17, IMPORTRANGE(""https://docs.google.com/spreadsheets/d/1S7deMHO2waboU9dywpXeKIDfCmjiu"&"Ac0HUIsFpaXQq8/edit?gid=0#gid=0"", ""Tracking Shipments - PPTCO!p:p""), 0))"),"PPT-39") -> PPT-39 | D17: 119664 | E17: KIT CAT -Deboned 42A | F17: Kit Cat | G17: Before DSV | H17: Done | K17: Done | L17: Yes | M17: 45281 | N17: 242023 | O17: 385 | P17: 431 | Q17: 386 | R17: SMACC | S17: =IFERROR(IF(DATEDIF(M17,R17,"d")=0,"",DATEDIF(M17,R17,"d")),"") | W17: Done | Y17: Closed
A18: 17 | B18: =IFERROR(__xludf.DUMMYFUNCTION("INDEX(IMPORTRANGE(""https://docs.google.com/spreadsheets/d/1S7deMHO2waboU9dywpXeKIDfCmjiuAc0HUIsFpaXQq8/edit?gid=0#gid=0"", ""Tracking Shipments - PPTCO!o:o""), MATCH(D18, IMPORTRANGE(""https://docs.google.com/spreadsheets/d/1S7deMHO2waboU9dywpXeKIDfCmjiu"&"Ac0HUIsFpaXQq8/edit?gid=0#gid=0"", ""Tracking Shipments - PPTCO!p:p""), 0))"),"PPT-34") -> PPT-34 | D18: 120610 | E18: KIT CAT - Deboned 45 | F18: Kit Cat | G18: Before DSV | H18: Done | K18: Done | L18: Yes | M18: 45280 | N18: 242023 | O18: 383 | P18: 426 | Q18: 384 | R18: SMACC | S18: =IFERROR(IF(DATEDIF(M18,R18,"d")=0,"",DATEDIF(M18,R18,"d")),"") | W18: Done | Y18: Closed
A19: 18 | B19: =IFERROR(__xludf.DUMMYFUNCTION("INDEX(IMPORTRANGE(""https://docs.google.com/spreadsheets/d/1S7deMHO2waboU9dywpXeKIDfCmjiuAc0HUIsFpaXQq8/edit?gid=0#gid=0"", ""Tracking Shipments - PPTCO!o:o""), MATCH(D19, IMPORTRANGE(""https://docs.google.com/spreadsheets/d/1S7deMHO2waboU9dywpXeKIDfCmjiu"&"Ac0HUIsFpaXQq8/edit?gid=0#gid=0"", ""Tracking Shipments - PPTCO!p:p""), 0))"),"N/A") -> N/A | D19: 117571 | E19: Butcher's FS/23/10/0001/EX, FS/23/10/0002/EX | F19: Butchers | G19: Before DSV | H19: Done | K19: Done | L19: Yes | M19: 45273 | N19: 242023 | O19: 386 - 387 | P19: 436 - 437 | Q19: 387 - 388 | R19: SMACC | S19: =IFERROR(IF(DATEDIF(M19,R19,"d")=0,"",DATEDIF(M19,R19,"d")),"") | W19: Done | Y19: Closed
A20: 19 | B20: =IFERROR(__xludf.DUMMYFUNCTION("INDEX(IMPORTRANGE(""https://docs.google.com/spreadsheets/d/1S7deMHO2waboU9dywpXeKIDfCmjiuAc0HUIsFpaXQq8/edit?gid=0#gid=0"", ""Tracking Shipments - PPTCO!o:o""), MATCH(D20, IMPORTRANGE(""https://docs.google.com/spreadsheets/d/1S7deMHO2waboU9dywpXeKIDfCmjiu"&"Ac0HUIsFpaXQq8/edit?gid=0#gid=0"", ""Tracking Shipments - PPTCO!p:p""), 0))"),"PPT-39") -> PPT-39 | D20: 124051 | E20: KIT CAT - Goat Milk | F20: Kit Cat | G20: Before DSV | H20: Done | K20: Done | L20: Yes | M20: 45293 | N20: 242023 | O20: 394 | P20: 439 | Q20: 395 | R20: SMACC | S20: =IFERROR(IF(DATEDIF(M20,R20,"d")=0,"",DATEDIF(M20,R20,"d")),"") | W20: Done | Y20: Closed
A21: 20 | B21: =IFERROR(__xludf.DUMMYFUNCTION("INDEX(IMPORTRANGE(""https://docs.google.com/spreadsheets/d/1S7deMHO2waboU9dywpXeKIDfCmjiuAc0HUIsFpaXQq8/edit?gid=0#gid=0"", ""Tracking Shipments - PPTCO!o:o""), MATCH(D21, IMPORTRANGE(""https://docs.google.com/spreadsheets/d/1S7deMHO2waboU9dywpXeKIDfCmjiu"&"Ac0HUIsFpaXQq8/edit?gid=0#gid=0"", ""Tracking Shipments - PPTCO!p:p""), 0))"),"PPT-35") -> PPT-35 | D21: 124042 | E21: KIT CAT - Gravy | F21: Kit Cat | G21: Before DSV | H21: Done | K21: Done | L21: Yes | M21: 45293 | N21: 242023 | O21: 395 | P21: 440 | Q21: 396 | R21: SMACC | S21: =IFERROR(IF(DATEDIF(M21,R21,"d")=0,"",DATEDIF(M21,R21,"d")),"") | W21: Done | Y21: Closed
A22: 21 | B22: =IFERROR(__xludf.DUMMYFUNCTION("INDEX(IMPORTRANGE(""https://docs.google.com/spreadsheets/d/1S7deMHO2waboU9dywpXeKIDfCmjiuAc0HUIsFpaXQq8/edit?gid=0#gid=0"", ""Tracking Shipments - PPTCO!o:o""), MATCH(D22, IMPORTRANGE(""https://docs.google.com/spreadsheets/d/1S7deMHO2waboU9dywpXeKIDfCmjiu"&"Ac0HUIsFpaXQq8/edit?gid=0#gid=0"", ""Tracking Shipments - PPTCO!p:p""), 0))"),"PPT-71") -> PPT-71 | D22: 349863 | E22: Applaws Cat Dry "4 Contenr | F22: Applaws | G22: Before DSV | H22: Done | K22: Done | L22: Yes | M22: 45278 | N22: 242023 | O22: 378 > 381 | P22: 427 > 430 | Q22: 379 > 382 | R22: SMACC | S22: =IFERROR(IF(DATEDIF(M22,R22,"d")=0,"",DATEDIF(M22,R22,"d")),"") | W22: Done | Y22: Closed
A23: 22 | B23: =IFERROR(__xludf.DUMMYFUNCTION("INDEX(IMPORTRANGE(""https://docs.google.com/spreadsheets/d/1S7deMHO2waboU9dywpXeKIDfCmjiuAc0HUIsFpaXQq8/edit?gid=0#gid=0"", ""Tracking Shipments - PPTCO!o:o""), MATCH(D23, IMPORTRANGE(""https://docs.google.com/spreadsheets/d/1S7deMHO2waboU9dywpXeKIDfCmjiu"&"Ac0HUIsFpaXQq8/edit?gid=0#gid=0"", ""Tracking Shipments - PPTCO!p:p""), 0))"),"PPT-71") -> PPT-71 | D23: 353778 | E23: Applaws Cat Dry "6 Contenr | F23: Applaws | G23: Before DSV | H23: Done | K23: Done | L23: Yes | M23: 45291 | N23: 242023 | O23: 388 < 393 | P23: 441 > 446 | Q23: 389 < 394 | R23: SMACC | S23: =IFERROR(IF(DATEDIF(M23,R23,"d")=0,"",DATEDIF(M23,R23,"d")),"") | W23: Done | Y23: Closed
A24: 23 | B24: =IFERROR(__xludf.DUMMYFUNCTION("INDEX(IMPORTRANGE(""https://docs.google.com/spreadsheets/d/1S7deMHO2waboU9dywpXeKIDfCmjiuAc0HUIsFpaXQq8/edit?gid=0#gid=0"", ""Tracking Shipments - PPTCO!o:o""), MATCH(D24, IMPORTRANGE(""https://docs.google.com/spreadsheets/d/1S7deMHO2waboU9dywpXeKIDfCmjiu"&"Ac0HUIsFpaXQq8/edit?gid=0#gid=0"", ""Tracking Shipments - PPTCO!p:p""), 0))"),"PPT-65") -> PPT-65 | D24: 657 | E24: CATIDEA | F24: CatIdea | G24: Before DSV | H24: Done | K24: Done | L24: Yes | M24: 45300 | N24: 242023 | O24: 4 | P24: 2 | Q24: 10 | R24: 45328 | S24: =IFERROR(IF(DATEDIF(M24,R24,"d")=0,"",DATEDIF(M24,R24,"d")),"") -> 28 | W24: Done | Y24: Closed
A25: 24 | B25: =IFERROR(__xludf.DUMMYFUNCTION("INDEX(IMPORTRANGE(""https://docs.google.com/spreadsheets/d/1S7deMHO2waboU9dywpXeKIDfCmjiuAc0HUIsFpaXQq8/edit?gid=0#gid=0"", ""Tracking Shipments - PPTCO!o:o""), MATCH(D25, IMPORTRANGE(""https://docs.google.com/spreadsheets/d/1S7deMHO2waboU9dywpXeKIDfCmjiu"&"Ac0HUIsFpaXQq8/edit?gid=0#gid=0"", ""Tracking Shipments - PPTCO!p:p""), 0))"),"#N/A") -> #N/A | D25: 236554 | E25: My Family 8406 | F25: MyFamily | G25: Before DSV | H25: Done | K25: Done | L25: Yes | M25: 45277 | O25: 384 | P25: 438 | Q25: 385 | R25: SMACC | S25: =IFERROR(IF(DATEDIF(M25,R25,"d")=0,"",DATEDIF(M25,R25,"d")),"") | W25: Done | Y25: Closed
A26: 25 | B26: =IFERROR(__xludf.DUMMYFUNCTION("INDEX(IMPORTRANGE(""https://docs.google.com/spreadsheets/d/1S7deMHO2waboU9dywpXeKIDfCmjiuAc0HUIsFpaXQq8/edit?gid=0#gid=0"", ""Tracking Shipments - PPTCO!o:o""), MATCH(D26, IMPORTRANGE(""https://docs.google.com/spreadsheets/d/1S7deMHO2waboU9dywpXeKIDfCmjiu"&"Ac0HUIsFpaXQq8/edit?gid=0#gid=0"", ""Tracking Shipments - PPTCO!p:p""), 0))"),"#N/A") -> #N/A | E26: LAYROY Expert 313+314+315 | F26: Laroy | G26: Before DSV | H26: Done | O26: 131-133 | P26: 498-500 | Q26: 127-129 | S26: =IFERROR(IF(DATEDIF(M26,R26,"d")=0,"",DATEDIF(M26,R26,"d")),"") | Y26: Closed
A27: 26 | B27: =IFERROR(__xludf.DUMMYFUNCTION("INDEX(IMPORTRANGE(""https://docs.google.com/spreadsheets/d/1S7deMHO2waboU9dywpXeKIDfCmjiuAc0HUIsFpaXQq8/edit?gid=0#gid=0"", ""Tracking Shipments - PPTCO!o:o""), MATCH(D27, IMPORTRANGE(""https://docs.google.com/spreadsheets/d/1S7deMHO2waboU9dywpXeKIDfCmjiu"&"Ac0HUIsFpaXQq8/edit?gid=0#gid=0"", ""Tracking Shipments - PPTCO!p:p""), 0))"),"#N/A") -> #N/A | D27: 2702 | E27: Kit Cat SoyaClump KCIT230322 | F27: Kit Cat | G27: Before DSV | H27: Done | K27: Done | L27: Yes | M27: 45302 | N27: 0012024 | O27: 16 | P27: 7 | Q27: 2 | R27: 45328 | S27: =IFERROR(IF(DATEDIF(M27,R27,"d")=0,"",DATEDIF(M27,R27,"d")),"") -> 26 | Y27: Closed
A28: 27 | B28: =IFERROR(__xludf.DUMMYFUNCTION("INDEX(IMPORTRANGE(""https://docs.google.com/spreadsheets/d/1S7deMHO2waboU9dywpXeKIDfCmjiuAc0HUIsFpaXQq8/edit?gid=0#gid=0"", ""Tracking Shipments - PPTCO!o:o""), MATCH(D28, IMPORTRANGE(""https://docs.google.com/spreadsheets/d/1S7deMHO2waboU9dywpXeKIDfCmjiu"&"Ac0HUIsFpaXQq8/edit?gid=0#gid=0"", ""Tracking Shipments - PPTCO!p:p""), 0))"),"PPT-67") -> PPT-67 | D28: 15674 | E28: VERSELE LAGA 2311826 | F28: Versele Laga | G28: Before DSV | H28: Done | K28: Done | L28: Yes | M28: 45325 | N28: 0012024 | O28: 22 | P28: 23 | Q28: 21 | R28: 45329 | S28: =IFERROR(IF(DATEDIF(M28,R28,"d")=0,"",DATEDIF(M28,R28,"d")),"") -> 4 | Y28: Closed
A29: 28 | B29: =IFERROR(__xludf.DUMMYFUNCTION("INDEX(IMPORTRANGE(""https://docs.google.com/spreadsheets/d/1S7deMHO2waboU9dywpXeKIDfCmjiuAc0HUIsFpaXQq8/edit?gid=0#gid=0"", ""Tracking Shipments - PPTCO!o:o""), MATCH(D29, IMPORTRANGE(""https://docs.google.com/spreadsheets/d/1S7deMHO2waboU9dywpXeKIDfCmjiu"&"Ac0HUIsFpaXQq8/edit?gid=0#gid=0"", ""Tracking Shipments - PPTCO!p:p""), 0))"),"PPT-67") -> PPT-67 | D29: 15129 | E29: VERSELE LAGA 2311821 , 2311822 | F29: Versele Laga | G29: Before DSV | H29: Done | K29: Done | L29: Yes | M29: 45325 | N29: 0012024 | O29: 20 , 21 | P29: 20 , 21 | Q29: 22 , 23 | R29: 45329 | S29: =IFERROR(IF(DATEDIF(M29,R29,"d")=0,"",DATEDIF(M29,R29,"d")),"") -> 4 | Y29: Closed
A30: 29 | B30: =IFERROR(__xludf.DUMMYFUNCTION("INDEX(IMPORTRANGE(""https://docs.google.com/spreadsheets/d/1S7deMHO2waboU9dywpXeKIDfCmjiuAc0HUIsFpaXQq8/edit?gid=0#gid=0"", ""Tracking Shipments - PPTCO!o:o""), MATCH(D30, IMPORTRANGE(""https://docs.google.com/spreadsheets/d/1S7deMHO2waboU9dywpXeKIDfCmjiu"&"Ac0HUIsFpaXQq8/edit?gid=0#gid=0"", ""Tracking Shipments - PPTCO!p:p""), 0))"),"PPT-80") -> PPT-80 | D30: 10114 | E30: LAVIOSA 2300000541 | F30: Laviosa | G30: Before DSV | H30: Done | K30: Done | L30: Yes | M30: 45309 | N30: 0012024 | O30: 3 | P30: 12 | Q30: 14 | R30: 45328 | S30: =IFERROR(IF(DATEDIF(M30,R30,"d")=0,"",DATEDIF(M30,R30,"d")),"") -> 19 | Y30: Closed
A31: 30 | B31: =IFERROR(__xludf.DUMMYFUNCTION("INDEX(IMPORTRANGE(""https://docs.google.com/spreadsheets/d/1S7deMHO2waboU9dywpXeKIDfCmjiuAc0HUIsFpaXQq8/edit?gid=0#gid=0"", ""Tracking Shipments - PPTCO!o:o""), MATCH(D31, IMPORTRANGE(""https://docs.google.com/spreadsheets/d/1S7deMHO2waboU9dywpXeKIDfCmjiu"&"Ac0HUIsFpaXQq8/edit?gid=0#gid=0"", ""Tracking Shipments - PPTCO!p:p""), 0))"),"PPT-83") -> PPT-83 | D31: 15125 | E31: LAYROY 513 +765+ 766 | F31: Laroy | G31: Before DSV | H31: Done | K31: Done | L31: Yes | M31: 45325 | N31: 0012024 | O31: 10 -> 12 | P31: 3 -> 5 | Q31: 5 -> 7 | R31: 45328 | S31: =IFERROR(IF(DATEDIF(M31,R31,"d")=0,"",DATEDIF(M31,R31,"d")),"") -> 3 | Y31: Closed
A32: 31 | B32: =IFERROR(__xludf.DUMMYFUNCTION("INDEX(IMPORTRANGE(""https://docs.google.com/spreadsheets/d/1S7deMHO2waboU9dywpXeKIDfCmjiuAc0HUIsFpaXQq8/edit?gid=0#gid=0"", ""Tracking Shipments - PPTCO!o:o""), MATCH(D32, IMPORTRANGE(""https://docs.google.com/spreadsheets/d/1S7deMHO2waboU9dywpXeKIDfCmjiu"&"Ac0HUIsFpaXQq8/edit?gid=0#gid=0"", ""Tracking Shipments - PPTCO!p:p""), 0))"),"PPT-80") -> PPT-80 | D32: 10121 | E32: LAVIOSA 2300000548 - 2300000563 | F32: Laviosa | G32: Before DSV | H32: Done | K32: Done | L32: Yes | M32: 45309 | N32: 0012024 | O32: 7 , 8 | P32: 13 , 14 | Q32: 11 , 12 | R32: 45328 | S32: =IFERROR(IF(DATEDIF(M32,R32,"d")=0,"",DATEDIF(M32,R32,"d")),"") -> 19 | Y32: Closed
A33: 32 | B33: =IFERROR(__xludf.DUMMYFUNCTION("INDEX(IMPORTRANGE(""https://docs.google.com/spreadsheets/d/1S7deMHO2waboU9dywpXeKIDfCmjiuAc0HUIsFpaXQq8/edit?gid=0#gid=0"", ""Tracking Shipments - PPTCO!o:o""), MATCH(D33, IMPORTRANGE(""https://docs.google.com/spreadsheets/d/1S7deMHO2waboU9dywpXeKIDfCmjiu"&"Ac0HUIsFpaXQq8/edit?gid=0#gid=0"", ""Tracking Shipments - PPTCO!p:p""), 0))"),"PPT-30") -> PPT-30 | D33: 2675 | E33: Kit Cat Litter KCIT230034B | F33: Kit Cat | G33: Before DSV | H33: Done | K33: Done | L33: Yes | M33: 45314 | N33: 0012024 | O33: 2 | P33: 1 | Q33: 1 | R33: 45325 | S33: =IFERROR(IF(DATEDIF(M33,R33,"d")=0,"",DATEDIF(M33,R33,"d")),"") -> 11 | Y33: Closed
A34: 33 | B34: =IFERROR(__xludf.DUMMYFUNCTION("INDEX(IMPORTRANGE(""https://docs.google.com/spreadsheets/d/1S7deMHO2waboU9dywpXeKIDfCmjiuAc0HUIsFpaXQq8/edit?gid=0#gid=0"", ""Tracking Shipments - PPTCO!o:o""), MATCH(D34, IMPORTRANGE(""https://docs.google.com/spreadsheets/d/1S7deMHO2waboU9dywpXeKIDfCmjiu"&"Ac0HUIsFpaXQq8/edit?gid=0#gid=0"", ""Tracking Shipments - PPTCO!p:p""), 0))"),"PPT-30") -> PPT-30 | D34: 2718 | E34: Kit Cat Litter KCIT230034A | F34: Kit Cat | G34: Before DSV | H34: Done | K34: Done | L34: Yes | M34: 45316 | N34: 0012024 | O34: 17 | P34: 9 | Q34: 4 | R34: 45328 | S34: =IFERROR(IF(DATEDIF(M34,R34,"d")=0,"",DATEDIF(M34,R34,"d")),"") -> 12 | Y34: Closed
A35: 34 | B35: =IFERROR(__xludf.DUMMYFUNCTION("INDEX(IMPORTRANGE(""https://docs.google.com/spreadsheets/d/1S7deMHO2waboU9dywpXeKIDfCmjiuAc0HUIsFpaXQq8/edit?gid=0#gid=0"", ""Tracking Shipments - PPTCO!o:o""), MATCH(D35, IMPORTRANGE(""https://docs.google.com/spreadsheets/d/1S7deMHO2waboU9dywpXeKIDfCmjiu"&"Ac0HUIsFpaXQq8/edit?gid=0#gid=0"", ""Tracking Shipments - PPTCO!p:p""), 0))"),"#N/A") -> #N/A | D35: 8092 | E35: KIt cat Gravy KCIT230310 | F35: Kit Cat | G35: Before DSV | H35: Done | K35: Done | L35: Yes | M35: 45316 | N35: 0012024 | O35: 23 | P35: 15 | Q35: 15 | R35: 45328 | S35: =IFERROR(IF(DATEDIF(M35,R35,"d")=0,"",DATEDIF(M35,R35,"d")),"") -> 12 | Y35: Closed
A36: 35 | B36: =IFERROR(__xludf.DUMMYFUNCTION("INDEX(IMPORTRANGE(""https://docs.google.com/spreadsheets/d/1S7deMHO2waboU9dywpXeKIDfCmjiuAc0HUIsFpaXQq8/edit?gid=0#gid=0"", ""Tracking Shipments - PPTCO!o:o""), MATCH(D36, IMPORTRANGE(""https://docs.google.com/spreadsheets/d/1S7deMHO2waboU9dywpXeKIDfCmjiu"&"Ac0HUIsFpaXQq8/edit?gid=0#gid=0"", ""Tracking Shipments - PPTCO!p:p""), 0))"),"PPT-89") -> PPT-89 | D36: 8076 | E36: Deboned&Gravy KCIT230314 | F36: Kit Cat | G36: Before DSV | H36: Done | K36: Done | L36: Yes | M36: 45319 | N36: 0012024 | O36: 18 | P36: 10 | Q36: 8 | R36: 45328 | S36: =IFERROR(IF(DATEDIF(M36,R36,"d")=0,"",DATEDIF(M36,R36,"d")),"") -> 9 | Y36: Closed
A37: 36 | B37: =IFERROR(__xludf.DUMMYFUNCTION("INDEX(IMPORTRANGE(""https://docs.google.com/spreadsheets/d/1S7deMHO2waboU9dywpXeKIDfCmjiuAc0HUIsFpaXQq8/edit?gid=0#gid=0"", ""Tracking Shipments - PPTCO!o:o""), MATCH(D37, IMPORTRANGE(""https://docs.google.com/spreadsheets/d/1S7deMHO2waboU9dywpXeKIDfCmjiu"&"Ac0HUIsFpaXQq8/edit?gid=0#gid=0"", ""Tracking Shipments - PPTCO!p:p""), 0))"),"#N/A") -> #N/A | D37: 8103 | E37: Deboned - KCIT230311 | F37: Kit Cat | G37: Before DSV | H37: Done | K37: Done | L37: Yes | M37: 45321 | N37: 0012024 | O37: 19 | P37: 11 | Q37: 9 | R37: 45328 | S37: =IFERROR(IF(DATEDIF(M37,R37,"d")=0,"",DATEDIF(M37,R37,"d")),"") -> 7 | Y37: Closed
A38: 37 | B38: =IFERROR(__xludf.DUMMYFUNCTION("INDEX(IMPORTRANGE(""https://docs.google.com/spreadsheets/d/1S7deMHO2waboU9dywpXeKIDfCmjiuAc0HUIsFpaXQq8/edit?gid=0#gid=0"", ""Tracking Shipments - PPTCO!o:o""), MATCH(D38, IMPORTRANGE(""https://docs.google.com/spreadsheets/d/1S7deMHO2waboU9dywpXeKIDfCmjiu"&"Ac0HUIsFpaXQq8/edit?gid=0#gid=0"", ""Tracking Shipments - PPTCO!p:p""), 0))"),"PPT-81") -> PPT-81 | D38: 8328 | E38: Schesir - 900006 | F38: Schesir | G38: Before DSV | H38: Done | K38: Done | L38: Yes | M38: 45321 | N38: 0012024 | O38: 6 | P38: 8 | Q38: 13 | R38: 45328 | S38: =IFERROR(IF(DATEDIF(M38,R38,"d")=0,"",DATEDIF(M38,R38,"d")),"") -> 7 | Y38: Closed
A39: 38 | B39: =IFERROR(__xludf.DUMMYFUNCTION("INDEX(IMPORTRANGE(""https://docs.google.com/spreadsheets/d/1S7deMHO2waboU9dywpXeKIDfCmjiuAc0HUIsFpaXQq8/edit?gid=0#gid=0"", ""Tracking Shipments - PPTCO!o:o""), MATCH(D39, IMPORTRANGE(""https://docs.google.com/spreadsheets/d/1S7deMHO2waboU9dywpXeKIDfCmjiu"&"Ac0HUIsFpaXQq8/edit?gid=0#gid=0"", ""Tracking Shipments - PPTCO!p:p""), 0))"),"#N/A") -> #N/A | D39: 9629 | E39: Laviosa LAT2023000001848 | F39: Laviosa | G39: Before DSV | H39: Done | K39: Done | L39: Yes | M39: 45324 | N39: 0012024 | O39: 9 | P39: 6 | Q39: 3 | R39: 45328 | S39: =IFERROR(IF(DATEDIF(M39,R39,"d")=0,"",DATEDIF(M39,R39,"d")),"") -> 4 | Y39: Closed
A40: 39 | B40: =IFERROR(__xludf.DUMMYFUNCTION("INDEX(IMPORTRANGE(""https://docs.google.com/spreadsheets/d/1S7deMHO2waboU9dywpXeKIDfCmjiuAc0HUIsFpaXQq8/edit?gid=0#gid=0"", ""Tracking Shipments - PPTCO!o:o""), MATCH(D40, IMPORTRANGE(""https://docs.google.com/spreadsheets/d/1S7deMHO2waboU9dywpXeKIDfCmjiu"&"Ac0HUIsFpaXQq8/edit?gid=0#gid=0"", ""Tracking Shipments - PPTCO!p:p""), 0))"),"PPT-41") -> PPT-41 | D40: 10947 | E40: Selim 287+288+298 | F40: Biosand | G40: Before DSV | H40: Done | K40: Done | L40: Yes | M40: 45311 | N40: 0012024 | O40: 13-14-15 | P40: 18-19-20 | Q40: 17-18-19 | R40: 45329 | S40: =IFERROR(IF(DATEDIF(M40,R40,"d")=0,"",DATEDIF(M40,R40,"d")),"") -> 18 | Y40: Closed
A41: 40 | B41: =IFERROR(__xludf.DUMMYFUNCTION("INDEX(IMPORTRANGE(""https://docs.google.com/spreadsheets/d/1S7deMHO2waboU9dywpXeKIDfCmjiuAc0HUIsFpaXQq8/edit?gid=0#gid=0"", ""Tracking Shipments - PPTCO!o:o""), MATCH(D41, IMPORTRANGE(""https://docs.google.com/spreadsheets/d/1S7deMHO2waboU9dywpXeKIDfCmjiu"&"Ac0HUIsFpaXQq8/edit?gid=0#gid=0"", ""Tracking Shipments - PPTCO!p:p""), 0))"),"PPT-81") -> PPT-81 | D41: 8378 | E41: Schesir - 900004 | F41: Schesir | G41: Before DSV | H41: Done | K41: Done | L41: Yes | M41: 45321 | N41: 0012024 | O41: 1 | P41: 16 | Q41: 16 | R41: 45329 | S41: =IFERROR(IF(DATEDIF(M41,R41,"d")=0,"",DATEDIF(M41,R41,"d")),"") -> 8 | Y41: Closed
A42: 41 | B42: =IFERROR(__xludf.DUMMYFUNCTION("INDEX(IMPORTRANGE(""https://docs.google.com/spreadsheets/d/1S7deMHO2waboU9dywpXeKIDfCmjiuAc0HUIsFpaXQq8/edit?gid=0#gid=0"", ""Tracking Shipments - PPTCO!o:o""), MATCH(D42, IMPORTRANGE(""https://docs.google.com/spreadsheets/d/1S7deMHO2waboU9dywpXeKIDfCmjiu"&"Ac0HUIsFpaXQq8/edit?gid=0#gid=0"", ""Tracking Shipments - PPTCO!p:p""), 0))"),"PPT-79") -> PPT-79 | D42: 7846 | E42: INABA INK202311030-004 | F42: INABA | G42: Before DSV | H42: Done | K42: Done | L42: Yes | M42: 45321 | N42: 0012024 | O42: 5 | P42: 24 | Q42: 20 | R42: 45329 | S42: =IFERROR(IF(DATEDIF(M42,R42,"d")=0,"",DATEDIF(M42,R42,"d")),"") -> 8 | Y42: Closed
A43: 42 | B43: =IFERROR(__xludf.DUMMYFUNCTION("INDEX(IMPORTRANGE(""https://docs.google.com/spreadsheets/d/1S7deMHO2waboU9dywpXeKIDfCmjiuAc0HUIsFpaXQq8/edit?gid=0#gid=0"", ""Tracking Shipments - PPTCO!o:o""), MATCH(D43, IMPORTRANGE(""https://docs.google.com/spreadsheets/d/1S7deMHO2waboU9dywpXeKIDfCmjiu"&"Ac0HUIsFpaXQq8/edit?gid=0#gid=0"", ""Tracking Shipments - PPTCO!p:p""), 0))"),"PPT-33") -> PPT-33 | D43: 9916 | E43: KCIT230037B | F43: Kit Cat | G43: Before DSV | H43: Done | K43: Done | L43: Yes | M43: 45330 | N43: 0012024 | O43: 25 | P43: 26 | Q43: 25 | R43: 45333 | S43: =IFERROR(IF(DATEDIF(M43,R43,"d")=0,"",DATEDIF(M43,R43,"d")),"") -> 3 | Y43: Closed
A44: 43 | B44: =IFERROR(__xludf.DUMMYFUNCTION("INDEX(IMPORTRANGE(""https://docs.google.com/spreadsheets/d/1S7deMHO2waboU9dywpXeKIDfCmjiuAc0HUIsFpaXQq8/edit?gid=0#gid=0"", ""Tracking Shipments - PPTCO!o:o""), MATCH(D44, IMPORTRANGE(""https://docs.google.com/spreadsheets/d/1S7deMHO2waboU9dywpXeKIDfCmjiu"&"Ac0HUIsFpaXQq8/edit?gid=0#gid=0"", ""Tracking Shipments - PPTCO!p:p""), 0))"),"PPT-33") -> PPT-33 | D44: 9920 | E44: KCIT230037A | F44: Kit Cat | G44: Before DSV | H44: Done | K44: Done | L44: Yes | M44: 45329 | N44: 0012024 | O44: 24 | P44: 25 | Q44: 24 | R44: 45333 | S44: =IFERROR(IF(DATEDIF(M44,R44,"d")=0,"",DATEDIF(M44,R44,"d")),"") -> 4 | Y44: Closed
A45: 44 | B45: =IFERROR(__xludf.DUMMYFUNCTION("INDEX(IMPORTRANGE(""https://docs.google.com/spreadsheets/d/1S7deMHO2waboU9dywpXeKIDfCmjiuAc0HUIsFpaXQq8/edit?gid=0#gid=0"", ""Tracking Shipments - PPTCO!o:o""), MATCH(D45, IMPORTRANGE(""https://docs.google.com/spreadsheets/d/1S7deMHO2waboU9dywpXeKIDfCmjiu"&"Ac0HUIsFpaXQq8/edit?gid=0#gid=0"", ""Tracking Shipments - PPTCO!p:p""), 0))"),"PPT-81") -> PPT-81 | D45: 13657 | E45: Schesir - 900007 | F45: Schesir | G45: Before DSV | H45: Done | K45: Done | L45: Yes | M45: 45335 | O45: 26 | P45: 70 | Q45: 29 | R45: 45336 | S45: =IFERROR(IF(DATEDIF(M45,R45,"d")=0,"",DATEDIF(M45,R45,"d")),"") -> 1 | Y45: Closed
A46: 45 | B46: =IFERROR(__xludf.DUMMYFUNCTION("INDEX(IMPORTRANGE(""https://docs.google.com/spreadsheets/d/1S7deMHO2waboU9dywpXeKIDfCmjiuAc0HUIsFpaXQq8/edit?gid=0#gid=0"", ""Tracking Shipments - PPTCO!o:o""), MATCH(D46, IMPORTRANGE(""https://docs.google.com/spreadsheets/d/1S7deMHO2waboU9dywpXeKIDfCmjiu"&"Ac0HUIsFpaXQq8/edit?gid=0#gid=0"", ""Tracking Shipments - PPTCO!p:p""), 0))"),"INNOVATION-CONTAINER#1") -> INNOVATION-CONTAINER#1 | D46: 5146 | E46: Schesir - 900002 | F46: Schesir | G46: Before DSV | H46: Done | L46: Yes | M46: 45307 | O46: 30 | P46: 36 | Q46: 47 | R46: 45361 | S46: =IFERROR(IF(DATEDIF(M46,R46,"d")=0,"",DATEDIF(M46,R46,"d")),"") -> 54 | Y46: Closed
A47: 46 | B47: =IFERROR(__xludf.DUMMYFUNCTION("INDEX(IMPORTRANGE(""https://docs.google.com/spreadsheets/d/1S7deMHO2waboU9dywpXeKIDfCmjiuAc0HUIsFpaXQq8/edit?gid=0#gid=0"", ""Tracking Shipments - PPTCO!o:o""), MATCH(D47, IMPORTRANGE(""https://docs.google.com/spreadsheets/d/1S7deMHO2waboU9dywpXeKIDfCmjiu"&"Ac0HUIsFpaXQq8/edit?gid=0#gid=0"", ""Tracking Shipments - PPTCO!p:p""), 0))"),"INNOVATION-CONTAINER#2") -> INNOVATION-CONTAINER#2 | D47: 5161 | E47: Schesir - 900003 | F47: Schesir | G47: Before DSV | H47: Done | L47: Yes | M47: 45308 | O47: 31 | P47: 37 | Q47: 46 | R47: 45360 | S47: =IFERROR(IF(DATEDIF(M47,R47,"d")=0,"",DATEDIF(M47,R47,"d")),"") -> 52 | Y47: Closed
A48: 47 | B48: =IFERROR(__xludf.DUMMYFUNCTION("INDEX(IMPORTRANGE(""https://docs.google.com/spreadsheets/d/1S7deMHO2waboU9dywpXeKIDfCmjiuAc0HUIsFpaXQq8/edit?gid=0#gid=0"", ""Tracking Shipments - PPTCO!o:o""), MATCH(D48, IMPORTRANGE(""https://docs.google.com/spreadsheets/d/1S7deMHO2waboU9dywpXeKIDfCmjiu"&"Ac0HUIsFpaXQq8/edit?gid=0#gid=0"", ""Tracking Shipments - PPTCO!p:p""), 0))"),"PPT-84 & PPT-96 & PPT-71") -> PPT-84 & PPT-96 & PPT-71 | D48: 39995 | E48: Applaws Cat Dry "12Contenr | F48: Applaws | G48: Before DSV | H48: Done | K48: Done | L48: Yes | M48: 45353 | N48: 222024 | O48: 32-43 | P48: 219-230 | Q48: 34-45 | R48: 45357 | S48: =IFERROR(IF(DATEDIF(M48,R48,"d")=0,"",DATEDIF(M48,R48,"d")),"") -> 4 | Y48: Closed
A49: 48 | B49: =IFERROR(__xludf.DUMMYFUNCTION("INDEX(IMPORTRANGE(""https://docs.google.com/spreadsheets/d/1S7deMHO2waboU9dywpXeKIDfCmjiuAc0HUIsFpaXQq8/edit?gid=0#gid=0"", ""Tracking Shipments - PPTCO!o:o""), MATCH(D49, IMPORTRANGE(""https://docs.google.com/spreadsheets/d/1S7deMHO2waboU9dywpXeKIDfCmjiu"&"Ac0HUIsFpaXQq8/edit?gid=0#gid=0"", ""Tracking Shipments - PPTCO!p:p""), 0))"),"PPT-82") -> PPT-82 | D49: 39905 | E49: SANAL / 5240123 | F49: Sanal | G49: Before DSV | H49: Done | K49: Done | L49: Yes | M49: 45353 | N49: 222024 | O49: 44 | P49: 238 | Q49: 48 | R49: 45361 | S49: =IFERROR(IF(DATEDIF(M49,R49,"d")=0,"",DATEDIF(M49,R49,"d")),"") -> 8 | Y49: Closed
A50: 49 | B50: =IFERROR(__xludf.DUMMYFUNCTION("INDEX(IMPORTRANGE(""https://docs.google.com/spreadsheets/d/1S7deMHO2waboU9dywpXeKIDfCmjiuAc0HUIsFpaXQq8/edit?gid=0#gid=0"", ""Tracking Shipments - PPTCO!o:o""), MATCH(D50, IMPORTRANGE(""https://docs.google.com/spreadsheets/d/1S7deMHO2waboU9dywpXeKIDfCmjiu"&"Ac0HUIsFpaXQq8/edit?gid=0#gid=0"", ""Tracking Shipments - PPTCO!p:p""), 0))"),"PPT-71 PPT-84 PPT-96") -> PPT-71 PPT-84 PPT-96 | D50: 47366 | E50: Applaws Cat Dry "6Contenr | F50: Applaws | G50: Before DSV | H50: Done | K50: Done | L50: Yes | M50: 45362 | O50: 48-53 | P50: 47->52 | Q50: 49->54 | R50: 45364 | S50: =IFERROR(IF(DATEDIF(M50,R50,"d")=0,"",DATEDIF(M50,R50,"d")),"") -> 2 | Y50: Closed
A51: 50 | B51: =IFERROR(__xludf.DUMMYFUNCTION("INDEX(IMPORTRANGE(""https://docs.google.com/spreadsheets/d/1S7deMHO2waboU9dywpXeKIDfCmjiuAc0HUIsFpaXQq8/edit?gid=0#gid=0"", ""Tracking Shipments - PPTCO!o:o""), MATCH(D51, IMPORTRANGE(""https://docs.google.com/spreadsheets/d/1S7deMHO2waboU9dywpXeKIDfCmjiu"&"Ac0HUIsFpaXQq8/edit?gid=0#gid=0"", ""Tracking Shipments - PPTCO!p:p""), 0))"),"#N/A") -> #N/A | D51: 47021 | E51: Princess litter166408-166409-166410 | F51: Princess | G51: no need | H51: Done | K51: Done | L51: Yes | M51: 45362 | O51: 59-60-61 | P51: 57-58-59 | Q51: 55-56-57 | R51: 45365 | S51: =IFERROR(IF(DATEDIF(M51,R51,"d")=0,"",DATEDIF(M51,R51,"d")),"") -> 3 | Y51: Closed
A52: 51 | B52: - | D52: 31259 | E52: Butcher's 003 / 004 | F52: Butchers | G52: done | H52: Done | K52: Done | L52: Yes | M52: 45378 | N52: 32024 | O52: 84-85 | P52: 51-52 | Q52: 67-68 | R52: 45397 | S52: =IFERROR(IF(DATEDIF(M52,R52,"d")=0,"",DATEDIF(M52,R52,"d")),"") -> 19 | Y52: Closed
A53: 52 | B53: =IFERROR(__xludf.DUMMYFUNCTION("INDEX(IMPORTRANGE(""https://docs.google.com/spreadsheets/d/1S7deMHO2waboU9dywpXeKIDfCmjiuAc0HUIsFpaXQq8/edit?gid=0#gid=0"", ""Tracking Shipments - PPTCO!o:o""), MATCH(D53, IMPORTRANGE(""https://docs.google.com/spreadsheets/d/1S7deMHO2waboU9dywpXeKIDfCmjiu"&"Ac0HUIsFpaXQq8/edit?gid=0#gid=0"", ""Tracking Shipments - PPTCO!p:p""), 0))"),"PPT-41") -> PPT-41 | D53: 63465 | E53: Biosand 33,32 | F53: Biosand | G53: no need | H53: Done | K53: Done | L53: Yes | M53: 45383 | O53: 71-72 | P53: 304-305 | Q53: 59-60 | R53: 45388 | S53: =IFERROR(IF(DATEDIF(M53,R53,"d")=0,"",DATEDIF(M53,R53,"d")),"") -> 5 | Y53: Closed
A54: 53 | B54: - | D54: 30059 | E54: Kit Cat 2nd chance | F54: Kit Cat | G54: no need | H54: Done | K54: Done | L54: Yes | M54: 45386 | O54: 102 | P54: 371 | Q54: 84 | R54: 45403 | S54: =IFERROR(IF(DATEDIF(M54,R54,"d")=0,"",DATEDIF(M54,R54,"d")),"") -> 17 | Y54: Closed
A55: 54 | B55: =IFERROR(__xludf.DUMMYFUNCTION("INDEX(IMPORTRANGE(""https://docs.google.com/spreadsheets/d/1S7deMHO2waboU9dywpXeKIDfCmjiuAc0HUIsFpaXQq8/edit?gid=0#gid=0"", ""Tracking Shipments - PPTCO!o:o""), MATCH(D55, IMPORTRANGE(""https://docs.google.com/spreadsheets/d/1S7deMHO2waboU9dywpXeKIDfCmjiu"&"Ac0HUIsFpaXQq8/edit?gid=0#gid=0"", ""Tracking Shipments - PPTCO!p:p""), 0))"),"#N/A") -> #N/A | D55: 53936 | E55: Josera Dry x7 | F55: Josera | G55: done | H55: Done | K55: Done | L55: Yes | M55: 45377 | N55: 32024 | O55: 106-108>113 | P55: 440->446 | Q55: 105->111 | R55: 45411 | S55: =IFERROR(IF(DATEDIF(M55,R55,"d")=0,"",DATEDIF(M55,R55,"d")),"") -> 34 | W55: Done | Y55: Closed
A56: 55 | B56: =IFERROR(__xludf.DUMMYFUNCTION("INDEX(IMPORTRANGE(""https://docs.google.com/spreadsheets/d/1S7deMHO2waboU9dywpXeKIDfCmjiuAc0HUIsFpaXQq8/edit?gid=0#gid=0"", ""Tracking Shipments - PPTCO!o:o""), MATCH(D56, IMPORTRANGE(""https://docs.google.com/spreadsheets/d/1S7deMHO2waboU9dywpXeKIDfCmjiu"&"Ac0HUIsFpaXQq8/edit?gid=0#gid=0"", ""Tracking Shipments - PPTCO!p:p""), 0))"),"PPT-80") -> PPT-80 | D56: 56524 | E56: Lindocat - 2300000065 | F56: Laviosa | G56: no need | H56: Done | K56: Done | L56: Yes | M56: 45377 | O56: 70 | P56: 82 | Q56: 58 | R56: 45378 | S56: =IFERROR(IF(DATEDIF(M56,R56,"d")=0,"",DATEDIF(M56,R56,"d")),"") -> 1 | Y56: Closed
A57: 56 | B57: =IFERROR(__xludf.DUMMYFUNCTION("INDEX(IMPORTRANGE(""https://docs.google.com/spreadsheets/d/1S7deMHO2waboU9dywpXeKIDfCmjiuAc0HUIsFpaXQq8/edit?gid=0#gid=0"", ""Tracking Shipments - PPTCO!o:o""), MATCH(D57, IMPORTRANGE(""https://docs.google.com/spreadsheets/d/1S7deMHO2waboU9dywpXeKIDfCmjiu"&"Ac0HUIsFpaXQq8/edit?gid=0#gid=0"", ""Tracking Shipments - PPTCO!p:p""), 0))"),"#N/A") -> #N/A | D57: 56600 | E57: Applaws Wet - 243693, 243694, 243695 | F57: Applaws | G57: done | H57: Done | K57: Done | L57: Yes | M57: 45378 | O57: 65-66-67 | P57: 93-94-95 | Q57: 71-72-73 | R57: 45399 | S57: =IFERROR(IF(DATEDIF(M57,R57,"d")=0,"",DATEDIF(M57,R57,"d")),"") -> 21 | Y57: Closed
A58: 57 | B58: =IFERROR(__xludf.DUMMYFUNCTION("INDEX(IMPORTRANGE(""https://docs.google.com/spreadsheets/d/1S7deMHO2waboU9dywpXeKIDfCmjiuAc0HUIsFpaXQq8/edit?gid=0#gid=0"", ""Tracking Shipments - PPTCO!o:o""), MATCH(D58, IMPORTRANGE(""https://docs.google.com/spreadsheets/d/1S7deMHO2waboU9dywpXeKIDfCmjiu"&"Ac0HUIsFpaXQq8/edit?gid=0#gid=0"", ""Tracking Shipments - PPTCO!p:p""), 0))"),"#N/A") -> #N/A | E58: Zolux Mats OC-3030 | F58: Zolux | O58: 28 | P58: N | Q58: N | S58: =IFERROR(IF(DATEDIF(M58,R58,"d")=0,"",DATEDIF(M58,R58,"d")),"") | X58: Arrived | Y58: closed
A59: 58 | B59: =IFERROR(__xludf.DUMMYFUNCTION("INDEX(IMPORTRANGE(""https://docs.google.com/spreadsheets/d/1S7deMHO2waboU9dywpXeKIDfCmjiuAc0HUIsFpaXQq8/edit?gid=0#gid=0"", ""Tracking Shipments - PPTCO!o:o""), MATCH(D59, IMPORTRANGE(""https://docs.google.com/spreadsheets/d/1S7deMHO2waboU9dywpXeKIDfCmjiu"&"Ac0HUIsFpaXQq8/edit?gid=0#gid=0"", ""Tracking Shipments - PPTCO!p:p""), 0))"),"#N/A") -> #N/A | E59: WM Expert x3 PPT-116 | F59: Laroy | O59: 62-63-64 | P59: N | Q59: N | S59: =IFERROR(IF(DATEDIF(M59,R59,"d")=0,"",DATEDIF(M59,R59,"d")),"") | X59: Not arrived yet, PO created,and other PO was created | Y59: Closed
A60: 76 | B60: - | D60: 38039 | E60: Butcher's - FS/23/12/0001/EX, FS/23/12/0002/EX | F60: Butchers | G60: To DSV | H60: done | K60: done | L60: Yes | M60: 45398 | N60: 32024 | O60: 115-116 | P60: 412-414 | Q60: 114-115 | R60: 45411 | S60: =IFERROR(IF(DATEDIF(M60,R60,"d")=0,"",DATEDIF(M60,R60,"d")),"") -> 13 | T60: No Need | Y60: Closed
A61: 59 | B61: =IFERROR(__xludf.DUMMYFUNCTION("INDEX(IMPORTRANGE(""https://docs.google.com/spreadsheets/d/1S7deMHO2waboU9dywpXeKIDfCmjiuAc0HUIsFpaXQq8/edit?gid=0#gid=0"", ""Tracking Shipments - PPTCO!o:o""), MATCH(D61, IMPORTRANGE(""https://docs.google.com/spreadsheets/d/1S7deMHO2waboU9dywpXeKIDfCmjiu"&"Ac0HUIsFpaXQq8/edit?gid=0#gid=0"", ""Tracking Shipments - PPTCO!p:p""), 0))"),"#N/A") -> #N/A | E61: Zolux Toys & Accessories | F61: Zolux | O61: 68 | P61: N | Q61: N | S61: =IFERROR(IF(DATEDIF(M61,R61,"d")=0,"",DATEDIF(M61,R61,"d")),"") | X61: Not arrived yet, PO created | Y61: closed
A62: 60 | B62: =IFERROR(__xludf.DUMMYFUNCTION("INDEX(IMPORTRANGE(""https://docs.google.com/spreadsheets/d/1S7deMHO2waboU9dywpXeKIDfCmjiuAc0HUIsFpaXQq8/edit?gid=0#gid=0"", ""Tracking Shipments - PPTCO!o:o""), MATCH(D62, IMPORTRANGE(""https://docs.google.com/spreadsheets/d/1S7deMHO2waboU9dywpXeKIDfCmjiu"&"Ac0HUIsFpaXQq8/edit?gid=0#gid=0"", ""Tracking Shipments - PPTCO!p:p""), 0))"),"#N/A") -> #N/A | E62: Zolux Rodywood | F62: Zolux | O62: 69 | P62: N | Q62: N | S62: =IFERROR(IF(DATEDIF(M62,R62,"d")=0,"",DATEDIF(M62,R62,"d")),"") | X62: Not arrived yet, PO created | Y62: closed
A63: 62 | B63: =IFERROR(__xludf.DUMMYFUNCTION("INDEX(IMPORTRANGE(""https://docs.google.com/spreadsheets/d/1S7deMHO2waboU9dywpXeKIDfCmjiuAc0HUIsFpaXQq8/edit?gid=0#gid=0"", ""Tracking Shipments - PPTCO!o:o""), MATCH(D63, IMPORTRANGE(""https://docs.google.com/spreadsheets/d/1S7deMHO2waboU9dywpXeKIDfCmjiu"&"Ac0HUIsFpaXQq8/edit?gid=0#gid=0"", ""Tracking Shipments - PPTCO!p:p""), 0))"),"PPT-84, PPT-96") -> PPT-84, PPT-96 | D63: 63709 | E63: Applaws x11 | F63: Applaws | G63: done | H63: done | K63: done | L63: Yes | M63: 45389 | N63: 32024 | O63: 73-> 83 | P63: 35->45 | Q63: 74-75-76-78-79-80-81-82-83-85-103 | R63: 45399 | S63: =IFERROR(IF(DATEDIF(M63,R63,"d")=0,"",DATEDIF(M63,R63,"d")),"") -> 10 | Y63: Closed
A64: 63 | B64: =IFERROR(__xludf.DUMMYFUNCTION("INDEX(IMPORTRANGE(""https://docs.google.com/spreadsheets/d/1S7deMHO2waboU9dywpXeKIDfCmjiuAc0HUIsFpaXQq8/edit?gid=0#gid=0"", ""Tracking Shipments - PPTCO!o:o""), MATCH(D64, IMPORTRANGE(""https://docs.google.com/spreadsheets/d/1S7deMHO2waboU9dywpXeKIDfCmjiu"&"Ac0HUIsFpaXQq8/edit?gid=0#gid=0"", ""Tracking Shipments - PPTCO!p:p""), 0))"),"PPT-94") -> PPT-94 | D64: 34288 | E64: Schesir 900271 | F64: Schesir | G64: done | H64: done | K64: done | L64: Yes | M64: 45397 | N64: 32024 | O64: 90 | P64: 69 | Q64: 98 | R64: 45405 | S64: =IFERROR(IF(DATEDIF(M64,R64,"d")=0,"",DATEDIF(M64,R64,"d")),"") -> 8 | W64: Done | Y64: Closed
A65: 64 | B65: =IFERROR(__xludf.DUMMYFUNCTION("INDEX(IMPORTRANGE(""https://docs.google.com/spreadsheets/d/1S7deMHO2waboU9dywpXeKIDfCmjiuAc0HUIsFpaXQq8/edit?gid=0#gid=0"", ""Tracking Shipments - PPTCO!o:o""), MATCH(D65, IMPORTRANGE(""https://docs.google.com/spreadsheets/d/1S7deMHO2waboU9dywpXeKIDfCmjiu"&"Ac0HUIsFpaXQq8/edit?gid=0#gid=0"", ""Tracking Shipments - PPTCO!p:p""), 0))"),"PPT-94") -> PPT-94 | D65: 34293 | E65: Schesir 900272 | F65: Schesir | G65: done | H65: done | K65: done | L65: Yes | M65: 45397 | N65: 32024 | O65: 88 | P65: 65 | Q65: 100 | R65: 45405 | S65: =IFERROR(IF(DATEDIF(M65,R65,"d")=0,"",DATEDIF(M65,R65,"d")),"") -> 8 | W65: Done | Y65: Closed
A66: 65 | B66: =IFERROR(__xludf.DUMMYFUNCTION("INDEX(IMPORTRANGE(""https://docs.google.com/spreadsheets/d/1S7deMHO2waboU9dywpXeKIDfCmjiuAc0HUIsFpaXQq8/edit?gid=0#gid=0"", ""Tracking Shipments - PPTCO!o:o""), MATCH(D66, IMPORTRANGE(""https://docs.google.com/spreadsheets/d/1S7deMHO2waboU9dywpXeKIDfCmjiu"&"Ac0HUIsFpaXQq8/edit?gid=0#gid=0"", ""Tracking Shipments - PPTCO!p:p""), 0))"),"PPT-94") -> PPT-94 | D66: 34297 | E66: Schesir 900273 | F66: Schesir | G66: done | H66: done | K66: done | L66: Yes | M66: 45397 | N66: 32024 | O66: 87 | P66: 67 | Q66: 101 | R66: 45405 | S66: =IFERROR(IF(DATEDIF(M66,R66,"d")=0,"",DATEDIF(M66,R66,"d")),"") -> 8 | W66: Done | Y66: Closed
A67: 66 | B67: =IFERROR(__xludf.DUMMYFUNCTION("INDEX(IMPORTRANGE(""https://docs.google.com/spreadsheets/d/1S7deMHO2waboU9dywpXeKIDfCmjiuAc0HUIsFpaXQq8/edit?gid=0#gid=0"", ""Tracking Shipments - PPTCO!o:o""), MATCH(D67, IMPORTRANGE(""https://docs.google.com/spreadsheets/d/1S7deMHO2waboU9dywpXeKIDfCmjiu"&"Ac0HUIsFpaXQq8/edit?gid=0#gid=0"", ""Tracking Shipments - PPTCO!p:p""), 0))"),"PPT-94") -> PPT-94 | D67: 34291 | E67: Schesir 900274 | F67: Schesir | G67: done | H67: done | K67: done | L67: Yes | M67: 45397 | N67: 32024 | O67: 89 | P67: 368 | Q67: 102 | R67: 45410 | S67: =IFERROR(IF(DATEDIF(M67,R67,"d")=0,"",DATEDIF(M67,R67,"d")),"") -> 13 | W67: Done | Y67: Closed
A68: 67 | B68: =IFERROR(__xludf.DUMMYFUNCTION("INDEX(IMPORTRANGE(""https://docs.google.com/spreadsheets/d/1S7deMHO2waboU9dywpXeKIDfCmjiuAc0HUIsFpaXQq8/edit?gid=0#gid=0"", ""Tracking Shipments - PPTCO!o:o""), MATCH(D68, IMPORTRANGE(""https://docs.google.com/spreadsheets/d/1S7deMHO2waboU9dywpXeKIDfCmjiu"&"Ac0HUIsFpaXQq8/edit?gid=0#gid=0"", ""Tracking Shipments - PPTCO!p:p""), 0))"),"#N/A") -> #N/A | D68: 34716 | E68: Dry & KittyCrunch KCIT230323 | F68: Kit Cat | G68: done | H68: done | K68: done | L68: Yes | M68: 45397 | O68: 107 | P68: 389 | Q68: 99 | R68: 45405 | S68: =IFERROR(IF(DATEDIF(M68,R68,"d")=0,"",DATEDIF(M68,R68,"d")),"") -> 8 | Y68: Closed
A69: 61 | B69: =IFERROR(__xludf.DUMMYFUNCTION("INDEX(IMPORTRANGE(""https://docs.google.com/spreadsheets/d/1S7deMHO2waboU9dywpXeKIDfCmjiuAc0HUIsFpaXQq8/edit?gid=0#gid=0"", ""Tracking Shipments - PPTCO!o:o""), MATCH(D69, IMPORTRANGE(""https://docs.google.com/spreadsheets/d/1S7deMHO2waboU9dywpXeKIDfCmjiu"&"Ac0HUIsFpaXQq8/edit?gid=0#gid=0"", ""Tracking Shipments - PPTCO!p:p""), 0))"),"#N/A") -> #N/A | E69: Zolux Poland Sticks | F69: Zolux | O69: 29 | P69: N | Q69: N | S69: =IFERROR(IF(DATEDIF(M69,R69,"d")=0,"",DATEDIF(M69,R69,"d")),"") | X69: Not arrived yet, PO created, Arrived , and other PO was created | Y69: Closed
A70: 69 | B70: =IFERROR(__xludf.DUMMYFUNCTION("INDEX(IMPORTRANGE(""https://docs.google.com/spreadsheets/d/1S7deMHO2waboU9dywpXeKIDfCmjiuAc0HUIsFpaXQq8/edit?gid=0#gid=0"", ""Tracking Shipments - PPTCO!o:o""), MATCH(D70, IMPORTRANGE(""https://docs.google.com/spreadsheets/d/1S7deMHO2waboU9dywpXeKIDfCmjiu"&"Ac0HUIsFpaXQq8/edit?gid=0#gid=0"", ""Tracking Shipments - PPTCO!p:p""), 0))"),"PPT-104") -> PPT-104 | D70: 67338 | E70: Josera 570264778, 570265037, 570265043 | F70: Josera | G70: done | H70: done | K70: done | L70: Yes | M70: 45399 | N70: 32024 | O70: 117-118-119 | P70: 447-448-449 | Q70: 116-117-118 | R70: 45412 | S70: =IFERROR(IF(DATEDIF(M70,R70,"d")=0,"",DATEDIF(M70,R70,"d")),"") -> 13 | Y70: Closed
A71: 68 | B71: =IFERROR(__xludf.DUMMYFUNCTION("INDEX(IMPORTRANGE(""https://docs.google.com/spreadsheets/d/1S7deMHO2waboU9dywpXeKIDfCmjiuAc0HUIsFpaXQq8/edit?gid=0#gid=0"", ""Tracking Shipments - PPTCO!o:o""), MATCH(D71, IMPORTRANGE(""https://docs.google.com/spreadsheets/d/1S7deMHO2waboU9dywpXeKIDfCmjiu"&"Ac0HUIsFpaXQq8/edit?gid=0#gid=0"", ""Tracking Shipments - PPTCO!p:p""), 0))"),"#N/A") -> #N/A | D71: 34701 | E71: Schesir 900145, 900147 | F71: Schesir | G71: To DSV | H71: done | K71: done | L71: Yes | M71: 45398 | N71: 52024 | O71: 194-195 | P71: 995-996 | Q71: 206-207 | R71: 45483 | S71: =IFERROR(IF(DATEDIF(M71,R71,"d")=0,"",DATEDIF(M71,R71,"d")),"") -> 85 | T71: Received | Y71: Closed
A72: 70 | B72: =IFERROR(__xludf.DUMMYFUNCTION("INDEX(IMPORTRANGE(""https://docs.google.com/spreadsheets/d/1S7deMHO2waboU9dywpXeKIDfCmjiuAc0HUIsFpaXQq8/edit?gid=0#gid=0"", ""Tracking Shipments - PPTCO!o:o""), MATCH(D72, IMPORTRANGE(""https://docs.google.com/spreadsheets/d/1S7deMHO2waboU9dywpXeKIDfCmjiu"&"Ac0HUIsFpaXQq8/edit?gid=0#gid=0"", ""Tracking Shipments - PPTCO!p:p""), 0))"),"#N/A") -> #N/A | E72: Applaws Ocean fish | F72: Applaws | O72: 55-56-57-58 | P72: N | Q72: N | S72: =IFERROR(IF(DATEDIF(M72,R72,"d")=0,"",DATEDIF(M72,R72,"d")),"") | X72: Not arrived yet, PO created | Y72: Closed
A73: 71 | B73: =IFERROR(__xludf.DUMMYFUNCTION("INDEX(IMPORTRANGE(""https://docs.google.com/spreadsheets/d/1S7deMHO2waboU9dywpXeKIDfCmjiuAc0HUIsFpaXQq8/edit?gid=0#gid=0"", ""Tracking Shipments - PPTCO!o:o""), MATCH(D73, IMPORTRANGE(""https://docs.google.com/spreadsheets/d/1S7deMHO2waboU9dywpXeKIDfCmjiu"&"Ac0HUIsFpaXQq8/edit?gid=0#gid=0"", ""Tracking Shipments - PPTCO!p:p""), 0))"),"#N/A") -> #N/A | E73: Versele Laga 880549, 880552, 880556, 880561 | F73: Versele Laga | O73: 47-49 | P73: N | Q73: N | S73: =IFERROR(IF(DATEDIF(M73,R73,"d")=0,"",DATEDIF(M73,R73,"d")),"") | X73: Not arrived yet, PO created, and other PO was created | Y73: Closed
A74: 72 | B74: =IFERROR(__xludf.DUMMYFUNCTION("INDEX(IMPORTRANGE(""https://docs.google.com/spreadsheets/d/1S7deMHO2waboU9dywpXeKIDfCmjiuAc0HUIsFpaXQq8/edit?gid=0#gid=0"", ""Tracking Shipments - PPTCO!o:o""), MATCH(D74, IMPORTRANGE(""https://docs.google.com/spreadsheets/d/1S7deMHO2waboU9dywpXeKIDfCmjiu"&"Ac0HUIsFpaXQq8/edit?gid=0#gid=0"", ""Tracking Shipments - PPTCO!p:p""), 0))"),"#N/A") -> #N/A | E74: Zolux collar | F74: Zolux | O74: 54 | P74: N | Q74: N | S74: =IFERROR(IF(DATEDIF(M74,R74,"d")=0,"",DATEDIF(M74,R74,"d")),"") | X74: Not arrived yet, PO created | Y74: Closed
A75: 73 | B75: =IFERROR(__xludf.DUMMYFUNCTION("INDEX(IMPORTRANGE(""https://docs.google.com/spreadsheets/d/1S7deMHO2waboU9dywpXeKIDfCmjiuAc0HUIsFpaXQq8/edit?gid=0#gid=0"", ""Tracking Shipments - PPTCO!o:o""), MATCH(D75, IMPORTRANGE(""https://docs.google.com/spreadsheets/d/1S7deMHO2waboU9dywpXeKIDfCmjiu"&"Ac0HUIsFpaXQq8/edit?gid=0#gid=0"", ""Tracking Shipments - PPTCO!p:p""), 0))"),"#N/A") -> #N/A | E75: Laviosa | F75: Laviosa | O75: 45 | P75: N | Q75: N | S75: =IFERROR(IF(DATEDIF(M75,R75,"d")=0,"",DATEDIF(M75,R75,"d")),"") | X75: Not arrived yet, PO created, and other PO was created | Y75: Closed
A76: 75 | B76: =IFERROR(__xludf.DUMMYFUNCTION("INDEX(IMPORTRANGE(""https://docs.google.com/spreadsheets/d/1S7deMHO2waboU9dywpXeKIDfCmjiuAc0HUIsFpaXQq8/edit?gid=0#gid=0"", ""Tracking Shipments - PPTCO!o:o""), MATCH(D76, IMPORTRANGE(""https://docs.google.com/spreadsheets/d/1S7deMHO2waboU9dywpXeKIDfCmjiu"&"Ac0HUIsFpaXQq8/edit?gid=0#gid=0"", ""Tracking Shipments - PPTCO!p:p""), 0))"),"PPT-94") -> PPT-94 | D76: 38310 | E76: Schesir - 900338, 900339 | F76: Schesir | G76: To DSV | H76: done | K76: done | L76: Yes | M76: 45407 | N76: Non | O76: 120-121 | P76: 450-451 | Q76: 112-113 | R76: 45411 | S76: =IFERROR(IF(DATEDIF(M76,R76,"d")=0,"",DATEDIF(M76,R76,"d")),"") -> 4 | T76: No Need | Y76: Closed
A77: 77 | B77: =IFERROR(__xludf.DUMMYFUNCTION("INDEX(IMPORTRANGE(""https://docs.google.com/spreadsheets/d/1S7deMHO2waboU9dywpXeKIDfCmjiuAc0HUIsFpaXQq8/edit?gid=0#gid=0"", ""Tracking Shipments - PPTCO!o:o""), MATCH(D77, IMPORTRANGE(""https://docs.google.com/spreadsheets/d/1S7deMHO2waboU9dywpXeKIDfCmjiu"&"Ac0HUIsFpaXQq8/edit?gid=0#gid=0"", ""Tracking Shipments - PPTCO!p:p""), 0))"),"PPT-92") -> PPT-92 | D77: 38031 | E77: KItcat 400g KCIT230315 | F77: Kit Cat | G77: done | H77: done | K77: done | L77: Yes | M77: 45405 | N77: 32024 | O77: 114 | P77: 409 | Q77: 104 | R77: 45411 | S77: =IFERROR(IF(DATEDIF(M77,R77,"d")=0,"",DATEDIF(M77,R77,"d")),"") -> 6 | Y77: Closed
A78: 78 | B78: =IFERROR(__xludf.DUMMYFUNCTION("INDEX(IMPORTRANGE(""https://docs.google.com/spreadsheets/d/1S7deMHO2waboU9dywpXeKIDfCmjiuAc0HUIsFpaXQq8/edit?gid=0#gid=0"", ""Tracking Shipments - PPTCO!o:o""), MATCH(D78, IMPORTRANGE(""https://docs.google.com/spreadsheets/d/1S7deMHO2waboU9dywpXeKIDfCmjiu"&"Ac0HUIsFpaXQq8/edit?gid=0#gid=0"", ""Tracking Shipments - PPTCO!p:p""), 0))"),"PPT-13") -> PPT-13 | D78: 38443 | E78: Kitcat Puree - KCIT220345B | F78: Kit Cat | G78: To DSV | H78: done | K78: done | L78: Yes | M78: 45409 | N78: 42024 | O78: 151 | P78: 567 | Q78: 184 | R78: 45447 | S78: =IFERROR(IF(DATEDIF(M78,R78,"d")=0,"",DATEDIF(M78,R78,"d")),"") -> 38 | T78: No Need | Y78: Closed
A79: 79 | B79: - | D79: 73552 | E79: Appaws x12 | F79: Applaws | G79: no need | H79: done | K79: done | L79: Yes | M79: 45402 | N79: 32024 | O79: 93-94-95-96-97-98-99-100-101-103-104-105 | P79: 76->81 | Q79: 86->97 | R79: 45405 | S79: =IFERROR(IF(DATEDIF(M79,R79,"d")=0,"",DATEDIF(M79,R79,"d")),"") -> 3 | Y79: Closed
A80: 80 | B80: =IFERROR(__xludf.DUMMYFUNCTION("INDEX(IMPORTRANGE(""https://docs.google.com/spreadsheets/d/1S7deMHO2waboU9dywpXeKIDfCmjiuAc0HUIsFpaXQq8/edit?gid=0#gid=0"", ""Tracking Shipments - PPTCO!o:o""), MATCH(D80, IMPORTRANGE(""https://docs.google.com/spreadsheets/d/1S7deMHO2waboU9dywpXeKIDfCmjiu"&"Ac0HUIsFpaXQq8/edit?gid=0#gid=0"", ""Tracking Shipments - PPTCO!p:p""), 0))"),"PPT-101") -> PPT-101 | D80: 73677 | E80: Dr.Clauder 52337205, 52337206, 52337334 | F80: Dr.Clauder | G80: To DSV | H80: done | K80: done | L80: Yes | M80: 45399 | N80: 52024 | O80: 196-197-198 | P80: 1005-1008-1006 | Q80: 202-204 | R80: 45482 | S80: =IFERROR(IF(DATEDIF(M80,R80,"d")=0,"",DATEDIF(M80,R80,"d")),"") -> 83 | T80: Received | W80: Done | Y80: Closed
A81: 81 | B81: =IFERROR(__xludf.DUMMYFUNCTION("INDEX(IMPORTRANGE(""https://docs.google.com/spreadsheets/d/1S7deMHO2waboU9dywpXeKIDfCmjiuAc0HUIsFpaXQq8/edit?gid=0#gid=0"", ""Tracking Shipments - PPTCO!o:o""), MATCH(D81, IMPORTRANGE(""https://docs.google.com/spreadsheets/d/1S7deMHO2waboU9dywpXeKIDfCmjiu"&"Ac0HUIsFpaXQq8/edit?gid=0#gid=0"", ""Tracking Shipments - PPTCO!p:p""), 0))"),"PPT-104") -> PPT-104 | D81: 74595 | E81: Josera 570266397, 570266402, 570266405, 570266518 | F81: Josera | G81: To DSV | H81: done | K81: done | L81: Yes | M81: 45402 | N81: 42024 | O81: 122->125 | P81: 489->492 | Q81: 119->122 | R81: 45413 | S81: =IFERROR(IF(DATEDIF(M81,R81,"d")=0,"",DATEDIF(M81,R81,"d")),"") -> 11 | T81: Received | Y81: Closed
A82: 82 | B82: =IFERROR(__xludf.DUMMYFUNCTION("INDEX(IMPORTRANGE(""https://docs.google.com/spreadsheets/d/1S7deMHO2waboU9dywpXeKIDfCmjiuAc0HUIsFpaXQq8/edit?gid=0#gid=0"", ""Tracking Shipments - PPTCO!o:o""), MATCH(D82, IMPORTRANGE(""https://docs.google.com/spreadsheets/d/1S7deMHO2waboU9dywpXeKIDfCmjiu"&"Ac0HUIsFpaXQq8/edit?gid=0#gid=0"", ""Tracking Shipments - PPTCO!p:p""), 0))"),"PPT-104") -> PPT-104 | D82: 79477 | E82: Josera Dry 570265885, 570265889, 570265891, 570265893 | F82: Josera | G82: To DSV | H82: done | K82: done | L82: Yes | M82: 45407 | N82: 42024 | O82: 126->129 | P82: 494->497 | Q82: 123->126 | R82: 45414 | S82: =IFERROR(IF(DATEDIF(M82,R82,"d")=0,"",DATEDIF(M82,R82,"d")),"") -> 7 | T82: Received | Y82: Closed
A83: 83 | B83: =IFERROR(__xludf.DUMMYFUNCTION("INDEX(IMPORTRANGE(""https://docs.google.com/spreadsheets/d/1S7deMHO2waboU9dywpXeKIDfCmjiuAc0HUIsFpaXQq8/edit?gid=0#gid=0"", ""Tracking Shipments - PPTCO!o:o""), MATCH(D83, IMPORTRANGE(""https://docs.google.com/spreadsheets/d/1S7deMHO2waboU9dywpXeKIDfCmjiu"&"Ac0HUIsFpaXQq8/edit?gid=0#gid=0"", ""Tracking Shipments - PPTCO!p:p""), 0))"),"N/A") -> N/A | D83: 79899 | E83: Versele laga 15006838 | F83: Versele Laga | G83: To DSV | H83: done | K83: done | L83: Yes | M83: 45406 | N83: 52024 | O83: 130 | P83: 501 | Q83: 130 | R83: 45417 | S83: =IFERROR(IF(DATEDIF(M83,R83,"d")=0,"",DATEDIF(M83,R83,"d")),"") -> 11 | T83: Requested | W83: Done | Y83: Closed
A84: 84 | B84: =IFERROR(__xludf.DUMMYFUNCTION("INDEX(IMPORTRANGE(""https://docs.google.com/spreadsheets/d/1S7deMHO2waboU9dywpXeKIDfCmjiuAc0HUIsFpaXQq8/edit?gid=0#gid=0"", ""Tracking Shipments - PPTCO!o:o""), MATCH(D84, IMPORTRANGE(""https://docs.google.com/spreadsheets/d/1S7deMHO2waboU9dywpXeKIDfCmjiu"&"Ac0HUIsFpaXQq8/edit?gid=0#gid=0"", ""Tracking Shipments - PPTCO!p:p""), 0))"),"PPT-104") -> PPT-104 | D84: 79407 | E84: Josera 570268172, 570268179, 570268187, 570268198 | F84: Josera | G84: To DSV | H84: done | K84: done | L84: Yes | M84: 45408 | N84: 42024 | O84: 134->137 | P84: 502->505 | Q84: 131->134 | R84: 45417 | S84: =IFERROR(IF(DATEDIF(M84,R84,"d")=0,"",DATEDIF(M84,R84,"d")),"") -> 9 | T84: Received | Y84: Closed
A85: 85 | B85: =IFERROR(__xludf.DUMMYFUNCTION("INDEX(IMPORTRANGE(""https://docs.google.com/spreadsheets/d/1S7deMHO2waboU9dywpXeKIDfCmjiuAc0HUIsFpaXQq8/edit?gid=0#gid=0"", ""Tracking Shipments - PPTCO!o:o""), MATCH(D85, IMPORTRANGE(""https://docs.google.com/spreadsheets/d/1S7deMHO2waboU9dywpXeKIDfCmjiu"&"Ac0HUIsFpaXQq8/edit?gid=0#gid=0"", ""Tracking Shipments - PPTCO!p:p""), 0))"),"PPT-83") -> PPT-83 | D85: 79755 | E85: Expert 2403313, 2403315, 2403314 | F85: Laroy | G85: No need | H85: done | K85: done | L85: Yes | M85: 45409 | N85: 52024 | O85: 131-132-133 | P85: 498-499-500 | Q85: 127-128-129 | R85: 45414 | S85: =IFERROR(IF(DATEDIF(M85,R85,"d")=0,"",DATEDIF(M85,R85,"d")),"") -> 5 | T85: No Need | Y85: Closed
A86: 86 | B86: - | D86: 82456 | E86: WM Cardboards - 22418071 | F86: Laroy | G86: No need | H86: done | K86: done | L86: Yes | M86: 45409 | N86: 102024 | O86: 277 | P86: 1547 | Q86: 266 | R86: 45532 | S86: =IFERROR(IF(DATEDIF(M86,R86,"d")=0,"",DATEDIF(M86,R86,"d")),"") -> 123 | T86: No Need | X86: Not announced | Y86: Closed
A87: 87 | B87: =IFERROR(__xludf.DUMMYFUNCTION("INDEX(IMPORTRANGE(""https://docs.google.com/spreadsheets/d/1S7deMHO2waboU9dywpXeKIDfCmjiuAc0HUIsFpaXQq8/edit?gid=0#gid=0"", ""Tracking Shipments - PPTCO!o:o""), MATCH(D87, IMPORTRANGE(""https://docs.google.com/spreadsheets/d/1S7deMHO2waboU9dywpXeKIDfCmjiu"&"Ac0HUIsFpaXQq8/edit?gid=0#gid=0"", ""Tracking Shipments - PPTCO!p:p""), 0))"),"PPT-116") -> PPT-116 | D87: 81492 | E87: WM Expert - 22416655, 22416656, 22416667, 22416668 | F87: Laroy | G87: To DSV | H87: done | K87: done | L87: Yes | M87: 45409 | N87: 42024 | O87: 138->141 | P87: 506->509 | Q87: 135->138 | R87: 45417 | S87: =IFERROR(IF(DATEDIF(M87,R87,"d")=0,"",DATEDIF(M87,R87,"d")),"") -> 8 | T87: Received | Y87: Closed
A88: 88 | B88: - | D88: 82091 | E88: Lindocat - LVS2024000000038 | F88: Laviosa | G88: To AJEX | H88: done | K88: done | L88: Yes | M88: 45414 | N88: 42024 | O88: 142 | P88: 510 | Q88: 148-149 | R88: 45420 | S88: =IFERROR(IF(DATEDIF(M88,R88,"d")=0,"",DATEDIF(M88,R88,"d")),"") -> 6 | T88: No Need | X88: 16of24 container received at AJEX first one received on 2May | Y88: Closed
A89: 89 | B89: - | D89: 82094 | E89: Lindocat - LAT2024000000686 | F89: Laviosa | G89: To AJEX | H89: done | K89: done | L89: Yes | M89: 45416 | N89: 42024 | O89: 143 | P89: 511 | Q89: 146-147 | R89: 45420 | S89: =IFERROR(IF(DATEDIF(M89,R89,"d")=0,"",DATEDIF(M89,R89,"d")),"") -> 4 | T89: No Need | X89: 11of15 container received at AJEX first one received on 4May | Y89: Closed
A90: 90 | B90: =IFERROR(__xludf.DUMMYFUNCTION("INDEX(IMPORTRANGE(""https://docs.google.com/spreadsheets/d/1S7deMHO2waboU9dywpXeKIDfCmjiuAc0HUIsFpaXQq8/edit?gid=0#gid=0"", ""Tracking Shipments - PPTCO!o:o""), MATCH(D90, IMPORTRANGE(""https://docs.google.com/spreadsheets/d/1S7deMHO2waboU9dywpXeKIDfCmjiu"&"Ac0HUIsFpaXQq8/edit?gid=0#gid=0"", ""Tracking Shipments - PPTCO!p:p""), 0))"),"PPT-110") -> PPT-110 | D90: 84491 | E90: Beaphar 90003827 | F90: Beaphar | G90: To DSV | H90: done | K90: done | L90: Yes | M90: 45410 | N90: 52024 | O90: 199 | P90: 1007 | Q90: 205 | R90: 45483 | S90: =IFERROR(IF(DATEDIF(M90,R90,"d")=0,"",DATEDIF(M90,R90,"d")),"") -> 73 | T90: Received | Y90: Closed
A91: 91 | B91: - | D91: 44045 | E91: Butcher's FS/24/01/0002/EX, FS/24/01/0003/EX, FS/24/01/0004/EX | F91: Butchers | G91: To DSV | H91: done | K91: done | L91: Yes | M91: 45423 | O91: 187-188-189 | P91: 898-899-900 | Q91: 189-190-191 | R91: 45456 | S91: =IFERROR(IF(DATEDIF(M91,R91,"d")=0,"",DATEDIF(M91,R91,"d")),"") -> 33 | T91: Received | Y91: Closed
A92: 92 | B92: - | D92: 85259 | E92: Applaws Wet - 246489 | F92: Applaws | G92: No need | H92: done | K92: done | L92: Yes | M92: 45413 | N92: 42024 | O92: 144 | P92: 512 | Q92: 139 | R92: 45417 | S92: =IFERROR(IF(DATEDIF(M92,R92,"d")=0,"",DATEDIF(M92,R92,"d")),"") -> 4 | T92: Received | Y92: closed
A93: 93 | B93: =IFERROR(__xludf.DUMMYFUNCTION("INDEX(IMPORTRANGE(""https://docs.google.com/spreadsheets/d/1S7deMHO2waboU9dywpXeKIDfCmjiuAc0HUIsFpaXQq8/edit?gid=0#gid=0"", ""Tracking Shipments - PPTCO!o:o""), MATCH(D93, IMPORTRANGE(""https://docs.google.com/spreadsheets/d/1S7deMHO2waboU9dywpXeKIDfCmjiu"&"Ac0HUIsFpaXQq8/edit?gid=0#gid=0"", ""Tracking Shipments - PPTCO!p:p""), 0))"),"N/A") -> N/A | D93: 44528 | E93: BAB'IN - FA2410192 | F93: Codico | G93: No need | H93: done | K93: done | L93: Yes | M93: 45421 | N93: 72024 | O93: 230 | P93: 1174 | Q93: 233 | R93: 45498 | S93: =IFERROR(IF(DATEDIF(M93,R93,"d")=0,"",DATEDIF(M93,R93,"d")),"") -> 77 | T93: Received | W93: Done | Y93: closed
A94: 94 | B94: =IFERROR(__xludf.DUMMYFUNCTION("INDEX(IMPORTRANGE(""https://docs.google.com/spreadsheets/d/1S7deMHO2waboU9dywpXeKIDfCmjiuAc0HUIsFpaXQq8/edit?gid=0#gid=0"", ""Tracking Shipments - PPTCO!o:o""), MATCH(D94, IMPORTRANGE(""https://docs.google.com/spreadsheets/d/1S7deMHO2waboU9dywpXeKIDfCmjiu"&"Ac0HUIsFpaXQq8/edit?gid=0#gid=0"", ""Tracking Shipments - PPTCO!p:p""), 0))"),"N/A") -> N/A | D94: 41260 | E94: Felyn Go - SC24122000401Z01 | F94: Inner Mongolia | G94: To AJEX | H94: done | K94: done | L94: Yes | M94: 45420 | N94: 42024 | O94: 159 | P94: 600 | Q94: 161 | R94: 45431 | S94: =IFERROR(IF(DATEDIF(M94,R94,"d")=0,"",DATEDIF(M94,R94,"d")),"") -> 11 | T94: No Need | X94: 14of14 container received at AJEX first one received on 8May | Y94: Closed
A95: 95 | B95: =IFERROR(__xludf.DUMMYFUNCTION("INDEX(IMPORTRANGE(""https://docs.google.com/spreadsheets/d/1S7deMHO2waboU9dywpXeKIDfCmjiuAc0HUIsFpaXQq8/edit?gid=0#gid=0"", ""Tracking Shipments - PPTCO!o:o""), MATCH(D95, IMPORTRANGE(""https://docs.google.com/spreadsheets/d/1S7deMHO2waboU9dywpXeKIDfCmjiu"&"Ac0HUIsFpaXQq8/edit?gid=0#gid=0"", ""Tracking Shipments - PPTCO!p:p""), 0))"),"N/A") -> N/A | D95: 45014 | E95: Felyn Go - SC24122000401Z02 | F95: Inner Mongolia | G95: To AJEX | H95: done | K95: done | L95: Yes | M95: 45426 | N95: 42024 | O95: 145 | P95: 513 | Q95: 160 | R95: 45431 | S95: =IFERROR(IF(DATEDIF(M95,R95,"d")=0,"",DATEDIF(M95,R95,"d")),"") -> 5 | T95: No Need | X95: 14of14 container received at AJEX first one received on 15May | Y95: Closed
A96: 96 | B96: =IFERROR(__xludf.DUMMYFUNCTION("INDEX(IMPORTRANGE(""https://docs.google.com/spreadsheets/d/1S7deMHO2waboU9dywpXeKIDfCmjiuAc0HUIsFpaXQq8/edit?gid=0#gid=0"", ""Tracking Shipments - PPTCO!o:o""), MATCH(D96, IMPORTRANGE(""https://docs.google.com/spreadsheets/d/1S7deMHO2waboU9dywpXeKIDfCmjiu"&"Ac0HUIsFpaXQq8/edit?gid=0#gid=0"", ""Tracking Shipments - PPTCO!p:p""), 0))"),"PPT-104") -> PPT-104 | D96: 86208 | E96: Josera x2 - 570268792, 570268791 | F96: Josera | G96: To DSV | H96: done | K96: done | L96: Yes | M96: 45416 | N96: 42024 | O96: 146-147 | P96: 514-515 | Q96: 140-141 | R96: 45417 | S96: =IFERROR(IF(DATEDIF(M96,R96,"d")=0,"",DATEDIF(M96,R96,"d")),"") -> 1 | T96: Received | Y96: Closed
A97: 97 | B97: =IFERROR(__xludf.DUMMYFUNCTION("INDEX(IMPORTRANGE(""https://docs.google.com/spreadsheets/d/1S7deMHO2waboU9dywpXeKIDfCmjiuAc0HUIsFpaXQq8/edit?gid=0#gid=0"", ""Tracking Shipments - PPTCO!o:o""), MATCH(D97, IMPORTRANGE(""https://docs.google.com/spreadsheets/d/1S7deMHO2waboU9dywpXeKIDfCmjiu"&"Ac0HUIsFpaXQq8/edit?gid=0#gid=0"", ""Tracking Shipments - PPTCO!p:p""), 0))"),"PPT-116") -> PPT-116 | D97: 87652 | E97: WM Expert - 2403745, 2403746, 2403747 | F97: Laroy | G97: To DSV | H97: done | K97: done | L97: Yes | M97: 45420 | N97: 42024 | O97: 148-149-150 | P97: 516-517-518 | Q97: 150-151-152 | R97: 45426 | S97: =IFERROR(IF(DATEDIF(M97,R97,"d")=0,"",DATEDIF(M97,R97,"d")),"") -> 6 | T97: No Need | Y97: Closed
A98: 98 | B98: =IFERROR(__xludf.DUMMYFUNCTION("INDEX(IMPORTRANGE(""https://docs.google.com/spreadsheets/d/1S7deMHO2waboU9dywpXeKIDfCmjiuAc0HUIsFpaXQq8/edit?gid=0#gid=0"", ""Tracking Shipments - PPTCO!o:o""), MATCH(D98, IMPORTRANGE(""https://docs.google.com/spreadsheets/d/1S7deMHO2waboU9dywpXeKIDfCmjiu"&"Ac0HUIsFpaXQq8/edit?gid=0#gid=0"", ""Tracking Shipments - PPTCO!p:p""), 0))"),"PPT-112") -> PPT-112 | D98: 90732 | E98: Applaws Dry x7 | F98: Applaws | G98: No need | H98: done | K98: done | L98: Yes | M98: 45426 | N98: 52024 | O98: 152->158 | P98: 568->574 | Q98: 153->159 | R98: 45428 | S98: =IFERROR(IF(DATEDIF(M98,R98,"d")=0,"",DATEDIF(M98,R98,"d")),"") -> 2 | T98: No Need | Y98: Closed
A99: 99 | B99: =IFERROR(__xludf.DUMMYFUNCTION("INDEX(IMPORTRANGE(""https://docs.google.com/spreadsheets/d/1S7deMHO2waboU9dywpXeKIDfCmjiuAc0HUIsFpaXQq8/edit?gid=0#gid=0"", ""Tracking Shipments - PPTCO!o:o""), MATCH(D99, IMPORTRANGE(""https://docs.google.com/spreadsheets/d/1S7deMHO2waboU9dywpXeKIDfCmjiu"&"Ac0HUIsFpaXQq8/edit?gid=0#gid=0"", ""Tracking Shipments - PPTCO!p:p""), 0))"),"N/A") -> N/A | D99: 47452 | E99: Butcher's FS/24/02/0003/EX, FS/24/02/0004/EX, FS/24/02/0005/EX | F99: Butchers | G99: To DSV | H99: done | K99: done | L99: Yes | M99: 45431 | N99: 52024 | O99: 184-185-186 | P99: 901-902-903 | Q99: 192-193-194 | R99: 45456 | S99: =IFERROR(IF(DATEDIF(M99,R99,"d")=0,"",DATEDIF(M99,R99,"d")),"") -> 25 | T99: Received | Y99: Closed
A100: 100 | B100: =IFERROR(__xludf.DUMMYFUNCTION("INDEX(IMPORTRANGE(""https://docs.google.com/spreadsheets/d/1S7deMHO2waboU9dywpXeKIDfCmjiuAc0HUIsFpaXQq8/edit?gid=0#gid=0"", ""Tracking Shipments - PPTCO!o:o""), MATCH(D100, IMPORTRANGE(""https://docs.google.com/spreadsheets/d/1S7deMHO2waboU9dywpXeKIDfCmji"&"uAc0HUIsFpaXQq8/edit?gid=0#gid=0"", ""Tracking Shipments - PPTCO!p:p""), 0))"),2400005.0) -> 2400005 | D100: 97123 | E100: Applaws Dry x17 | F100: Applaws | G100: To AJEX | H100: done | K100: done | L100: Yes | M100: 45432 | N100: 52024 | O100: 165->181 | P100: 795->811 | Q100: 167->183 | R100: 45445 | S100: =IFERROR(IF(DATEDIF(M100,R100,"d")=0,"",DATEDIF(M100,R100,"d")),"") -> 13 | T100: No Need | Y100: Closed
...

Sheet Registration Tracking Sheet
B1: Range | C1: Item Code | D1: Item Name | E1: Request Date | F1: Status | G1: Received Date | H1: Registred | I1: Number | J1: Days to be ready | K1: Remarks
A2: 1 | B2: Inaba Delights | C2: USA-868 | D2: INABA CUP DASHI DELIGHTS CHICKEN WITH SALMON RECIPE (USA-868) | E2: 45579 | F2: =VLOOKUP(D2,Sheet15!D:H,5,FALSE) -> مكتمل | H2: Yes | I2: =VLOOKUP(D2,Sheet15!D:K,8,FALSE) -> 2024-312651 | J2: =G2-E2 -> -45579 | K2: =VLOOKUP(D2,Sheet15!D:G,4,FALSE)
A3: 2 | B3: Inaba Delights | C3: USA-867 | D3: INABA CUP DASHI DELIGHT S CHICKEN WITH BONITO FLAKES RECIPE (USA-867) | E3: 45579 | F3: =VLOOKUP(D3,Sheet15!D:H,5,FALSE) -> مكتمل | H3: Yes | I3: =VLOOKUP(D3,Sheet15!D:K,8,FALSE) -> 2024-312647 | J3: =G3-E3 -> -45579 | K3: =VLOOKUP(D3,Sheet15!D:G,4,FALSE)
A4: 3 | B4: Inaba Delights | C4: USA-862 | D4: INABA CUP DASHI DELIGHTS CHICKEN WITH TUNA SALMON RECIPE (USA-862) | E4: 45579 | F4: =VLOOKUP(D4,Sheet15!D:H,5,FALSE) -> مكتمل | H4: Yes | I4: =VLOOKUP(D4,Sheet15!D:K,8,FALSE) -> 2024-312605 | J4: =G4-E4 -> -45579 | K4: =VLOOKUP(D4,Sheet15!D:G,4,FALSE)
A5: 4 | B5: Inaba Delights | C5: USA-861 | D5: INABA CUP DASHI DELIGHTS CHICKEN WITH TUNA RECIPE (USA-861) | E5: 45579 | F5: =VLOOKUP(D5,Sheet15!D:H,5,FALSE) -> مكتمل | H5: Yes | I5: =VLOOKUP(D5,Sheet15!D:K,8,FALSE) -> 2024-312585 | J5: =G5-E5 -> -45579 | K5: =VLOOKUP(D5,Sheet15!D:G,4,FALSE)
A6: 5 | B6: Inaba Delights | C6: USA-866 | D6: INABA CUP DASHI DELIGHTS CHICKEN W ITH CHEESE RECIPE (USA-866) | E6: 45579 | F6: =VLOOKUP(D6,Sheet15!D:H,5,FALSE) -> مكتمل | H6: Yes | I6: =VLOOKUP(D6,Sheet15!D:K,8,FALSE) -> 2024-312643 | J6: =G6-E6 -> -45579 | K6: =VLOOKUP(D6,Sheet15!D:G,4,FALSE)
A7: 6 | B7: Inaba Delights | C7: USA-865 | D7: INABA CUP DASHI DELIGHTS CHICKEN WITH SCALLOP RECIPE (USA-865) | E7: 45579 | F7: =VLOOKUP(D7,Sheet15!D:H,5,FALSE) -> مكتمل | H7: Yes | I7: =VLOOKUP(D7,Sheet15!D:K,8,FALSE) -> 2024-312633 | J7: =G7-E7 -> -45579 | K7: =VLOOKUP(D7,Sheet15!D:G,4,FALSE)
A8: 7 | B8: Inaba Delights | C8: USA-864 | D8: INABA CUP DASHI DELIGHTS CHICKEN RECIPE (USA-864) | E8: 45579 | F8: =VLOOKUP(D8,Sheet15!D:H,5,FALSE) -> مكتمل | H8: Yes | I8: =VLOOKUP(D8,Sheet15!D:K,8,FALSE) -> 2024-312626 | J8: =G8-E8 -> -45579 | K8: =VLOOKUP(D8,Sheet15!D:G,4,FALSE)
A9: 8 | B9: Inaba Delights | C9: USA-863 | D9: INABA CUP DASHI DELIGHTS CHICKEN WITH TUNA & SCALLOP RECIPE (USA-863) | E9: 45579 | F9: =VLOOKUP(D9,Sheet15!D:H,5,FALSE) -> مكتمل | H9: Yes | I9: =VLOOKUP(D9,Sheet15!D:K,8,FALSE) -> 2024-312617 | J9: =G9-E9 -> -45579 | K9: =VLOOKUP(D9,Sheet15!D:G,4,FALSE)
A10: 9 | B10: Wellness | C10: 10880 | D10: WEL WC CORE 98% Beef Recipe 12/85g | E10: 45581 | F10: =VLOOKUP(D10,Sheet15!D:H,5,FALSE) -> مكتمل | H10: Yes | I10: =VLOOKUP(D10,Sheet15!D:K,8,FALSE) -> 2024-346683 | J10: =G10-E10 -> -45581 | K10: =VLOOKUP(D10,Sheet15!D:G,4,FALSE)
A11: 10 | B11: Wellness | C11: 10881 | D11: WEL WC CORE 98% Turkey Recipe12/85g | E11: 45581 | F11: =VLOOKUP(D11,Sheet15!D:H,5,FALSE) -> مكتمل | H11: Yes | I11: =VLOOKUP(D11,Sheet15!D:K,8,FALSE) -> 2024-346711 | J11: =G11-E11 -> -45581 | K11: =VLOOKUP(D11,Sheet15!D:G,4,FALSE)
A12: 11 | B12: Wellness | C12: 10882 | D12: WEL WC CORE 98% Ckn/SalmRecip12/85g | E12: 45581 | F12: =VLOOKUP(D12,Sheet15!D:H,5,FALSE) -> مكتمل | H12: Yes | I12: =VLOOKUP(D12,Sheet15!D:K,8,FALSE) -> 2024-346720 | J12: =G12-E12 -> -45581 | K12: =VLOOKUP(D12,Sheet15!D:G,4,FALSE)
A13: 12 | B13: Wellness | C13: 10854 | D13: WEL WD CORE 95 Turkey with Kale 400g | E13: 45581 | F13: =VLOOKUP(D13,Sheet15!D:H,5,FALSE) -> مكتمل | H13: Yes | I13: =VLOOKUP(D13,Sheet15!D:K,8,FALSE) -> 2024-330246 | J13: =G13-E13 -> -45581 | K13: =VLOOKUP(D13,Sheet15!D:G,4,FALSE)
A14: 13 | B14: Wellness | C14: 10856 | D14: WEL WD CORE 95 Lamb With Pumpkin 400g | E14: 45581 | F14: =VLOOKUP(D14,Sheet15!D:H,5,FALSE) -> مكتمل | H14: Yes | I14: =VLOOKUP(D14,Sheet15!D:K,8,FALSE) -> 2024-330277 | J14: =G14-E14 -> -45581 | K14: =VLOOKUP(D14,Sheet15!D:G,4,FALSE)
A15: 14 | B15: Wellness | C15: 10857 | D15: WEL WD CORE 95 Beef with Broccoli 400g | E15: 45581 | F15: =VLOOKUP(D15,Sheet15!D:H,5,FALSE) -> مكتمل | H15: Yes | I15: =VLOOKUP(D15,Sheet15!D:K,8,FALSE) -> 2024-330299 | J15: =G15-E15 -> -45581 | K15: =VLOOKUP(D15,Sheet15!D:G,4,FALSE)
A16: 15 | B16: Wellness | C16: 10858 | D16: WEL WD CORE 95 Turkey with Goat 400g | E16: 45581 | F16: =VLOOKUP(D16,Sheet15!D:H,5,FALSE) -> مكتمل | H16: Yes | I16: =VLOOKUP(D16,Sheet15!D:K,8,FALSE) -> 2024-330316 | J16: =G16-E16 -> -45581 | K16: =VLOOKUP(D16,Sheet15!D:G,4,FALSE)
A17: 16 | B17: Wellness | C17: 10859 | D17: WEL WD CORE 95 Chicken with Duck with carrots 400g | E17: 45581 | F17: =VLOOKUP(D17,Sheet15!D:H,5,FALSE) -> مكتمل | H17: Yes | I17: =VLOOKUP(D17,Sheet15!D:K,8,FALSE) -> 2024-330324 | J17: =G17-E17 -> -45581 | K17: =VLOOKUP(D17,Sheet15!D:G,4,FALSE)
A18: 17 | B18: Wellness | C18: 10870 | D18: WEL WD CORE 95 Puppy original 400g | E18: 45581 | F18: =VLOOKUP(D18,Sheet15!D:H,5,FALSE) -> مكتمل | H18: Yes | I18: =VLOOKUP(D18,Sheet15!D:K,8,FALSE) -> 2024-330334 | J18: =G18-E18 -> -45581 | K18: =VLOOKUP(D18,Sheet15!D:G,4,FALSE)
A19: 18 | B19: Wellness | D19: Wellness core purely pate adult chicken | E19: 45589 | F19: =VLOOKUP(D19,Sheet15!D:H,5,FALSE) -> مكتمل | H19: Yes | I19: =VLOOKUP(D19,Sheet15!D:K,8,FALSE) -> 2024-346809 | J19: =G19-E19 -> -45589 | K19: =VLOOKUP(D19,Sheet15!D:G,4,FALSE)
A20: 19 | B20: Wellness | D20: Wellness Core Purely Pate Adult Chicken & Turkey | E20: 45589 | F20: =VLOOKUP(D20,Sheet15!D:H,5,FALSE) -> مكتمل | H20: Yes | I20: =VLOOKUP(D20,Sheet15!D:K,8,FALSE) -> 2024-346825 | J20: =G20-E20 -> -45589 | K20: =VLOOKUP(D20,Sheet15!D:G,4,FALSE)
A21: 20 | B21: Wellness | D21: Wellness core purely pate adult chicken & beef | E21: 45589 | F21: =VLOOKUP(D21,Sheet15!D:H,5,FALSE) -> مكتمل | H21: Yes | I21: =VLOOKUP(D21,Sheet15!D:K,8,FALSE) -> 2024-346831 | J21: =G21-E21 -> -45589 | K21: =VLOOKUP(D21,Sheet15!D:G,4,FALSE)
A22: 21 | B22: Wellness | D22: Wellness Core Purely Pate Adult Duck & Chicken | E22: 45589 | F22: =VLOOKUP(D22,Sheet15!D:H,5,FALSE) -> مكتمل | H22: Yes | I22: =VLOOKUP(D22,Sheet15!D:K,8,FALSE) -> 2024-346837 | J22: =G22-E22 -> -45589 | K22: =VLOOKUP(D22,Sheet15!D:G,4,FALSE)
A23: 22 | B23: Wellness | D23: Wellness core purely pate kitten chicken & Tuna | E23: 45589 | F23: =VLOOKUP(D23,Sheet15!D:H,5,FALSE) -> مكتمل | H23: Yes | I23: =VLOOKUP(D23,Sheet15!D:K,8,FALSE) -> 2024-346845 | J23: =G23-E23 -> -45589 | K23: =VLOOKUP(D23,Sheet15!D:G,4,FALSE)
A24: 23 | B24: zoulx | C24: 482774 | D24: ZOLUX CHICKEN WINGS 100G | E24: 45592 | F24: =VLOOKUP(D24,Sheet15!D:H,5,FALSE) -> مكتمل | H24: Yes | I24: =VLOOKUP(D24,Sheet15!D:K,8,FALSE) -> 2024-356398 | J24: =G24-E24 -> -45592 | K24: =VLOOKUP(D24,Sheet15!D:G,4,FALSE)
A25: 24 | B25: Wellness | D25: Wellness CORE Tender Cuts with Tuna in Savoury Gravy | E25: 45593 | F25: =VLOOKUP(D25,Sheet15!D:H,5,FALSE) -> مكتمل | H25: Yes | I25: =VLOOKUP(D25,Sheet15!D:K,8,FALSE) -> 2024-341003 | J25: =G25-E25 -> -45593 | K25: =VLOOKUP(D25,Sheet15!D:G,4,FALSE)
A26: 25 | B26: Wellness | D26: Wellness CORE Signature Selects Chunky Entree Flavoured with Beef & Boneless Chicken in Sauce | E26: 45593 | F26: =VLOOKUP(D26,Sheet15!D:H,5,FALSE) -> مكتمل | H26: Yes | I26: =VLOOKUP(D26,Sheet15!D:K,8,FALSE) -> 2024-339892 | J26: =G26-E26 -> -45593 | K26: =VLOOKUP(D26,Sheet15!D:G,4,FALSE)
A27: 26 | B27: Wellness | D27: Wellness CORE Signature Selects Flaked Skipjack Tuna with Shrimp Entree in Broth | E27: 45593 | F27: =VLOOKUP(D27,Sheet15!D:H,5,FALSE) -> مكتمل | H27: Yes | I27: =VLOOKUP(D27,Sheet15!D:K,8,FALSE) -> 2024-339955 | J27: =G27-E27 -> -45593 | K27: =VLOOKUP(D27,Sheet15!D:G,4,FALSE)
A28: 27 | B28: Wellness | D28: Wellness CORE Tender Cuts with Chicken & Salmon in Savoury Gravy | E28: 45593 | F28: =VLOOKUP(D28,Sheet15!D:H,5,FALSE) -> مكتمل | H28: Yes | I28: =VLOOKUP(D28,Sheet15!D:K,8,FALSE) -> 2024-341489 | J28: =G28-E28 -> -45593 | K28: =VLOOKUP(D28,Sheet15!D:G,4,FALSE)
A29: 28 | B29: Wellness | D29: Wellness CORE Tender Cuts with Turkey & Duck in Savoury Gravy | E29: 45593 | F29: =VLOOKUP(D29,Sheet15!D:H,5,FALSE) -> مكتمل | H29: Yes | I29: =VLOOKUP(D29,Sheet15!D:K,8,FALSE) -> 2024-341501 | J29: =G29-E29 -> -45593 | K29: =VLOOKUP(D29,Sheet15!D:G,4,FALSE)
A30: 29 | B30: Wellness | D30: Wellness CORE Signature Selects Shredded Boneless Chicken Entree Flavoured with Turkey in Sauce | E30: 45593 | F30: =VLOOKUP(D30,Sheet15!D:H,5,FALSE) -> مكتمل | H30: Yes | I30: =VLOOKUP(D30,Sheet15!D:K,8,FALSE) -> 2024-340000 | J30: =G30-E30 -> -45593 | K30: =VLOOKUP(D30,Sheet15!D:G,4,FALSE)
A31: 30 | B31: Wellness | D31: Wellness CORE Tender Cuts with Chicken & Chicken Liver in Savoury Gravy | E31: 45593 | F31: =VLOOKUP(D31,Sheet15!D:H,5,FALSE) -> مكتمل | H31: Yes | I31: =VLOOKUP(D31,Sheet15!D:K,8,FALSE) -> 2024-341523 | J31: =G31-E31 -> -45593 | K31: =VLOOKUP(D31,Sheet15!D:G,4,FALSE)
A32: 31 | B32: Wellness | D32: Wellness CORE Small Breed Savoury Medleys Flavoured with Roasted Chicken, Duck, Peas & Carrot | E32: 45593 | F32: =VLOOKUP(D32,Sheet15!D:H,5,FALSE) -> مكتمل | H32: Yes | I32: =VLOOKUP(D32,Sheet15!D:K,8,FALSE) -> 2024-343330 | J32: =G32-E32 -> -45593 | K32: =VLOOKUP(D32,Sheet15!D:G,4,FALSE)
A33: 32 | B33: Wellness | D33: Wellness CORE Small Breed Savoury Medleys Flavoured with Tender Chicken, Turkey, Carrots & Green Beans | E33: 45593 | F33: =VLOOKUP(D33,Sheet15!D:H,5,FALSE) -> مكتمل | H33: Yes | I33: =VLOOKUP(D33,Sheet15!D:K,8,FALSE) -> 2024-343359 | J33: =G33-E33 -> -45593 | K33: =VLOOKUP(D33,Sheet15!D:G,4,FALSE)
A34: 33 | B34: Wellness | D34: Wellness CORE Small Breed Savoury Medleys Flavoured with Braised Lamb, Venison, White Sweet Potatoes & CatTots | E34: 45593 | F34: =VLOOKUP(D34,Sheet15!D:H,5,FALSE) -> مكتمل | H34: Yes | I34: =VLOOKUP(D34,Sheet15!D:K,8,FALSE) -> 2024-343379 | J34: =G34-E34 -> -45593 | K34: =VLOOKUP(D34,Sheet15!D:G,4,FALSE)
A35: 34 | B35: Wellness | D35: Wellness CORE Small Breed Savoury Medleys Flavoured with Roasted Chicken, Beef, Green Beans & Red Peppers | E35: 45593 | F35: =VLOOKUP(D35,Sheet15!D:H,5,FALSE) -> مكتمل | H35: Yes | I35: =VLOOKUP(D35,Sheet15!D:K,8,FALSE) -> 2024-343410 | J35: =G35-E35 -> -45593 | K35: =VLOOKUP(D35,Sheet15!D:G,4,FALSE)
A36: 35 | B36: Wellness | D36: Wellness CORE Signature Selects Shredded Boneless Chicken Entree Flavoured with Chicken Liver in Sauce | E36: 45593 | F36: =VLOOKUP(D36,Sheet15!D:H,5,FALSE) -> مكتمل | H36: Yes | I36: =VLOOKUP(D36,Sheet15!D:K,8,FALSE) -> 2024-339974 | J36: =G36-E36 -> -45593 | K36: =VLOOKUP(D36,Sheet15!D:G,4,FALSE)
... A57: 56 | B57: kit cat | D57: Kit Cat Goatmilk Cat | E57: 45614 | F57: =VLOOKUP(D57,Sheet15!D:H,5,FALSE) -> مكتمل | H57: Yes | I57: =VLOOKUP(D57,Sheet15!D:K,8,FALSE) -> 2024-370636 | J57: =G57-E57 -> -45614 | K57: =VLOOKUP(D57,Sheet15!D:G,4,FALSE)
A58: 57 | B58: kit cat | D58: Kit Cat Goatmilk Kitten | E58: 46023 | F58: جديد | H58: Yes | I58: =VLOOKUP(D58,Sheet15!D:K,8,FALSE) -> 2024-370699 | J58: =G58-E58 -> -46023 | K58: =VLOOKUP(D58,Sheet15!D:G,4,FALSE)
A59: 58 | B59: Wellness | C59: WHZ311EU | D59: Whimzees Ricebone 540g | E59: 45614 | F59: =VLOOKUP(D59,Sheet15!D:H,5,FALSE) -> مكتمل | H59: Yes | I59: =VLOOKUP(D59,Sheet15!D:K,8,FALSE) -> 2024-371365 | J59: =G59-E59 -> -45614 | K59: =VLOOKUP(D59,Sheet15!D:G,4,FALSE)
A60: 59 | B60: Wellness | C60: WHZ316EU | D60: Whimzees Stix S 420g | E60: 45614 | F60: =VLOOKUP(D60,Sheet15!D:H,5,FALSE) -> مكتمل | H60: Yes | I60: =VLOOKUP(D60,Sheet15!D:K,8,FALSE) -> 2024-371592 | J60: =G60-E60 -> -45614 | K60: =VLOOKUP(D60,Sheet15!D:G,4,FALSE)
A61: 60 | B61: Wellness | C61: WHZ317EU | D61: Whimzees Stix M 420g | E61: 45614 | F61: =VLOOKUP(D61,Sheet15!D:H,5,FALSE) -> مكتمل | H61: Yes | I61: =VLOOKUP(D61,Sheet15!D:K,8,FALSE) -> 2024-371619 | J61: =G61-E61 -> -45614 | K61: =VLOOKUP(D61,Sheet15!D:G,4,FALSE)
A62: 61 | B62: Wellness | C62: WHZ318EU | D62: Whimzees Stix L 420g | E62: 45614 | F62: =VLOOKUP(D62,Sheet15!D:H,5,FALSE) -> مكتمل | H62: Yes | I62: =VLOOKUP(D62,Sheet15!D:K,8,FALSE) -> 2024-371642 | J62: =G62-E62 -> -45614 | K62: =VLOOKUP(D62,Sheet15!D:G,4,FALSE)
A63: 62 | B63: Wellness | C63: WHZ320EU | D63: Whimzees Alligator M 360g | E63: 45614 | F63: =VLOOKUP(D63,Sheet15!D:H,5,FALSE) -> مكتمل | H63: Yes | I63: =VLOOKUP(D63,Sheet15!D:K,8,FALSE) -> 2024-371662 | J63: =G63-E63 -> -45614 | K63: =VLOOKUP(D63,Sheet15!D:G,4,FALSE)
A64: 63 | B64: Wellness | C64: WHZ322EU | D64: Whimzees Alligator S 360g | E64: 45614 | F64: =VLOOKUP(D64,Sheet15!D:H,5,FALSE) -> مكتمل | H64: Yes | I64: =VLOOKUP(D64,Sheet15!D:K,8,FALSE) -> 2024-371672 | J64: =G64-E64 -> -45614 | K64: =VLOOKUP(D64,Sheet15!D:G,4,FALSE)
A65: 64 | B65: Wellness | C65: WHZ327EU | D65: Whimzees Stix XS 420g | E65: 45614 | F65: =VLOOKUP(D65,Sheet15!D:H,5,FALSE) -> مكتمل | H65: Yes | I65: =VLOOKUP(D65,Sheet15!D:K,8,FALSE) -> 2024-371685 | J65: =G65-E65 -> -45614 | K65: =VLOOKUP(D65,Sheet15!D:G,4,FALSE)
A66: 65 | B66: Wellness | C66: WHZ341EU | D66: Whimzees Toothbrush Star XS 360g | E66: 45614 | F66: =VLOOKUP(D66,Sheet15!D:H,5,FALSE) -> مكتمل | H66: Yes | I66: =VLOOKUP(D66,Sheet15!D:K,8,FALSE) -> 2024-371710 | J66: =G66-E66 -> -45614 | K66: =VLOOKUP(D66,Sheet15!D:G,4,FALSE)
A67: 66 | B67: Wellness | C67: WHZ342EU | D67: Whimzees Toothbrush Star S 360g | E67: 45614 | F67: =VLOOKUP(D67,Sheet15!D:H,5,FALSE) -> مكتمل | H67: Yes | I67: =VLOOKUP(D67,Sheet15!D:K,8,FALSE) -> 2024-371728 | J67: =G67-E67 -> -45614 | K67: =VLOOKUP(D67,Sheet15!D:G,4,FALSE)
A68: 67 | B68: Wellness | C68: WHZ343EU | D68: Whimzees Toothbrush Star M 360g | E68: 45614 | F68: =VLOOKUP(D68,Sheet15!D:H,5,FALSE) -> مكتمل | H68: Yes | I68: =VLOOKUP(D68,Sheet15!D:K,8,FALSE) -> 2024-371738 | J68: =G68-E68 -> -45614 | K68: =VLOOKUP(D68,Sheet15!D:G,4,FALSE)
A69: 68 | B69: Wellness | C69: WHZ344EU | D69: Whimzees Toothbrush Star L 360g | E69: 45614 | F69: =VLOOKUP(D69,Sheet15!D:H,5,FALSE) -> مكتمل | H69: Yes | I69: =VLOOKUP(D69,Sheet15!D:K,8,FALSE) -> 2024-371751 | J69: =G69-E69 -> -45614 | K69: =VLOOKUP(D69,Sheet15!D:G,4,FALSE)
A70: 69 | B70: Sanal Dogs | D70: Sanal Dog Dental Sticks Medium 140g | E70: 45615 | F70: =VLOOKUP(D70,Sheet15!D:H,5,FALSE) -> مكتمل | H70: Yes | I70: =VLOOKUP(D70,Sheet15!D:K,8,FALSE) -> 2024-372268 | J70: =G70-E70 -> -45615 | K70: =VLOOKUP(D70,Sheet15!D:G,4,FALSE)
A71: 70 | B71: Sanal Dogs | D71: Sanal Dog Dental Sticks Small 105g | E71: 45615 | F71: =VLOOKUP(D71,Sheet15!D:H,5,FALSE) -> مكتمل | H71: Yes | I71: =VLOOKUP(D71,Sheet15!D:K,8,FALSE) -> 2024-372287 | J71: =G71-E71 -> -45615 | K71: =VLOOKUP(D71,Sheet15!D:G,4,FALSE)
A72: 71 | B72: Sanal Dogs | D72: Sanal Dog Mini Hearts 100g | E72: 45615 | F72: =VLOOKUP(D72,Sheet15!D:H,5,FALSE) -> مكتمل | H72: Yes | I72: =VLOOKUP(D72,Sheet15!D:K,8,FALSE) -> 2024-372303 | J72: =G72-E72 -> -45615 | K72: =VLOOKUP(D72,Sheet15!D:G,4,FALSE)
A73: 72 | B73: Sanal Dogs | D73: Sanal Dog Trainers Duo Hearts 300g | E73: 45615 | F73: =VLOOKUP(D73,Sheet15!D:H,5,FALSE) -> مكتمل | H73: Yes | I73: =VLOOKUP(D73,Sheet15!D:K,8,FALSE) -> 2024-372322 | J73: =G73-E73 -> -45615 | K73: =VLOOKUP(D73,Sheet15!D:G,4,FALSE)
A74: 73 | B74: Kit Cat | D74: Kit Cat Daily Supplement Gel - Hairball 120g | E74: 45615 | F74: =VLOOKUP(D74,Sheet15!D:H,5,FALSE) -> مكتمل | H74: Yes | I74: =VLOOKUP(D74,Sheet15!D:K,8,FALSE) -> 2024-376027 | J74: =G74-E74 -> -45615 | K74: =VLOOKUP(D74,Sheet15!D:G,4,FALSE)
A75: 74 | B75: Kit Cat | D75: Kit Cat Daily Supplement Gel - Multi Vitamin 120g | E75: 45617 | F75: =VLOOKUP(D75,Sheet15!D:H,5,FALSE) -> مكتمل | H75: Yes | I75: =VLOOKUP(D75,Sheet15!D:K,8,FALSE) -> 2024-376081 | J75: =G75-E75 -> -45617 | K75: =VLOOKUP(D75,Sheet15!D:G,4,FALSE)
A76: 75 | B76: Kit Cat | D76: Kit Cat Daily Supplement Gel - Skin & Coat 120g | E76: 45617 | F76: =VLOOKUP(D76,Sheet15!D:H,5,FALSE) -> مكتمل | H76: Yes | I76: =VLOOKUP(D76,Sheet15!D:K,8,FALSE) -> 2024-376105 | J76: =G76-E76 -> -45617 | K76: =VLOOKUP(D76,Sheet15!D:G,4,FALSE)
A77: 76 | B77: Kit Cat | D77: Kit Cat Daily Supplement Gel -urinaru care | E77: 45617 | F77: =VLOOKUP(D77,Sheet15!D:H,5,FALSE) -> مكتمل | H77: Yes | I77: =VLOOKUP(D77,Sheet15!D:K,8,FALSE) -> 2024-376121 | J77: =G77-E77 -> -45617 | K77: =VLOOKUP(D77,Sheet15!D:G,4,FALSE)
A78: 77 | B78: Kit Cat | D78: Kit Cat Daily Supplement Gel - Weight Gain | E78: 45617 | F78: =VLOOKUP(D78,Sheet15!D:H,5,FALSE) -> مكتمل | H78: Yes | I78: =VLOOKUP(D78,Sheet15!D:K,8,FALSE) -> 2024-376139 | J78: =G78-E78 -> -45617 | K78: =VLOOKUP(D78,Sheet15!D:G,4,FALSE)
A79: 78 | B79: Kit Cat | D79: Kit Cat Kitten Milk Replacer 200g | E79: 45617 | F79: =VLOOKUP(D79,Sheet15!D:H,5,FALSE) -> مكتمل | H79: Yes | I79: =VLOOKUP(D79,Sheet15!D:K,8,FALSE) -> P-1-N-240624-3738 | J79: =G79-E79 -> -45617 | K79: =VLOOKUP(D79,Sheet15!D:G,4,FALSE)
A80: 79 | B80: Josera | D80: Josera Fohlen & Stute 20kg | E80: 45622 | F80: =VLOOKUP(D80,Sheet15!D:H,5,FALSE) -> مرفوض | H80: No | I80: =VLOOKUP(D80,Sheet15!D:K,8,FALSE) -> 2024-393876 | J80: =G80-E80 -> -45622 | K80: =VLOOKUP(D80,Sheet15!D:G,4,FALSE) -> تعليق الموظف: المكون(yeast)ذكر نوع الخميرة مع الرقم المرجعي لها حسب اللوائح والمواصفات الخاصة بالاعلاف.## المكون( extracted linseed)نامل تزويدنا بالملف العلمي والرقم المرجعي حسب اللوائح والمواصفات الخاصة بالاعلاف
A81: 80 | B81: Josera | D81: Josera Joker-Mineral 15kg | E81: 45622 | F81: =VLOOKUP(D81,Sheet15!D:H,5,FALSE) -> مكتمل | H81: Yes | I81: =VLOOKUP(D81,Sheet15!D:K,8,FALSE) -> 2024-393918 | J81: =G81-E81 -> -45622 | K81: =VLOOKUP(D81,Sheet15!D:G,4,FALSE)
... A96: 95 | B96: Josera | D96: Kitten Grainfree 400g / 60 g | E96: 45627 | F96: =VLOOKUP(D96,Sheet15!D:H,5,FALSE) -> مكتمل | H96: Yes | I96: =VLOOKUP(D96,Sheet15!D:K,8,FALSE) -> P-1-N-040521-2465 | J96: =G96-E96 -> -45627 | K96: =VLOOKUP(D96,Sheet15!D:G,4,FALSE)
A97: 96 | B97: Josera | D97: SensiCat 400g / 60 g | E97: 45627 | F97: مكتمل | H97: Yes | I97: =VLOOKUP(D97,Sheet15!D:K,8,FALSE) -> #N/A | J97: =G97-E97 -> -45627 | K97: =VLOOKUP(D97,Sheet15!D:G,4,FALSE) -> #N/A
A98: 97 | B98: Dr.clauder | D98: DC Stripes Beef Snack Small 80g | E98: 45630 | F98: =VLOOKUP(D98,Sheet15!D:H,5,FALSE) -> مكتمل | H98: Yes | I98: =VLOOKUP(D98,Sheet15!D:K,8,FALSE) -> 2024-415807 | J98: =G98-E98 -> -45630 | K98: =VLOOKUP(D98,Sheet15!D:G,4,FALSE)
A99: 98 | B99: Dr.clauder | D99: DC Stripes Chicken Snack Small 80g | E99: 45630 | F99: =VLOOKUP(D99,Sheet15!D:H,5,FALSE) -> مكتمل | H99: Yes | I99: =VLOOKUP(D99,Sheet15!D:K,8,FALSE) -> 2024-415821 | J99: =G99-E99 -> -45630 | K99: =VLOOKUP(D99,Sheet15!D:G,4,FALSE)
A100: 99 | B100: Dr.clauder | D100: DC Stripes Duck Snack Small 80g | E100: 45630 | F100: =VLOOKUP(D100,Sheet15!D:H,5,FALSE) -> مكتمل | H100: Yes | I100: =VLOOKUP(D100,Sheet15!D:K,8,FALSE) -> 2024-415828 | J100: =G100-E100 -> -45630 | K100: =VLOOKUP(D100,Sheet15!D:G,4,FALSE)
A101: 100 | B101: Dr.clauder | D101: DC Stripes Lamb Snack Small 80g | E101: 45630 | F101: =VLOOKUP(D101,Sheet15!D:H,5,FALSE) -> مكتمل | H101: Yes | I101: =VLOOKUP(D101,Sheet15!D:K,8,FALSE) -> 2024-415839 | J101: =G101-E101 -> -45630 | K101: =VLOOKUP(D101,Sheet15!D:G,4,FALSE)
A102: 101 | B102: Dr.clauder | D102: DC F&C Mother & Puppy Emulsion 150g | E102: 45630 | F102: مرفوض | H102: No | I102: =VLOOKUP(D102,Sheet15!D:K,8,FALSE) -> 2024-415845 | J102: =G102-E102 -> -45630 | K102: =VLOOKUP(D102,Sheet15!D:G,4,FALSE)
A103: 102 | B103: Dr.clauder | D103: DC High Premium Indoor 1.5kg | E103: 45630 | F103: مرفوض | H103: No | I103: =VLOOKUP(D103,Sheet15!D:K,8,FALSE) -> 2024-415851 | J103: =G103-E103 -> -45630 | K103: =VLOOKUP(D103,Sheet15!D:G,4,FALSE) -> المكون (linseed) ليس من المدخلات العلفية ,
A104: 103 | B104: Josera | D104: Josera Meat Bars Beef 40g | E104: 45634 | F104: =VLOOKUP(D104,Sheet15!D:H,5,FALSE) -> مكتمل | H104: Yes | I104: =VLOOKUP(D104,Sheet15!D:K,8,FALSE) -> 2024-406431 | J104: =G104-E104 -> -45634 | K104: =VLOOKUP(D104,Sheet15!D:G,4,FALSE)
A105: 104 | B105: Josera | D105: Josera Meat Bars Chicken 40g | E105: 45634 | F105: =VLOOKUP(D105,Sheet15!D:H,5,FALSE) -> مكتمل | H105: Yes | I105: =VLOOKUP(D105,Sheet15!D:K,8,FALSE) -> 2024-406441 | J105: =G105-E105 -> -45634 | K105: =VLOOKUP(D105,Sheet15!D:G,4,FALSE)
A106: 105 | B106: Josera | D106: .Josera Meat Bars Turkey 40g | E106: 45634 | F106: مكتمل | H106: Yes | I106: =VLOOKUP(D106,Sheet15!D:K,8,FALSE) -> #N/A | J106: =G106-E106 -> -45634 | K106: =VLOOKUP(D106,Sheet15!D:G,4,FALSE) -> #N/A
A107: 106 | B107: Josera | D107: Josera Meat Chunks Beef 70g | E107: 45634 | F107: =VLOOKUP(D107,Sheet15!D:H,5,FALSE) -> مكتمل | H107: Yes | I107: =VLOOKUP(D107,Sheet15!D:K,8,FALSE) -> 2024-406474 | J107: =G107-E107 -> -45634 | K107: =VLOOKUP(D107,Sheet15!D:G,4,FALSE)
A108: 107 | B108: Josera | D108: Josera Meat Chunks Chicken 70g | E108: 45634 | F108: =VLOOKUP(D108,Sheet15!D:H,5,FALSE) -> مكتمل | H108: Yes | I108: =VLOOKUP(D108,Sheet15!D:K,8,FALSE) -> 2024-406491 | J108: =G108-E108 -> -45634 | K108: =VLOOKUP(D108,Sheet15!D:G,4,FALSE)
A109: 108 | B109: Josera | D109: Josera Meat Chunks Turkey 70g | E109: 45634 | F109: =VLOOKUP(D109,Sheet15!D:H,5,FALSE) -> مكتمل | H109: Yes | I109: =VLOOKUP(D109,Sheet15!D:K,8,FALSE) -> 2024-406497 | J109: =G109-E109 -> -45634 | K109: =VLOOKUP(D109,Sheet15!D:G,4,FALSE)
A110: 109 | B110: Josera | D110: Josera Meat Bites Mini Beef 70g | E110: 45634 | F110: =VLOOKUP(D110,Sheet15!D:H,5,FALSE) -> مكتمل | H110: Yes | I110: =VLOOKUP(D110,Sheet15!D:K,8,FALSE) -> 2024-406508 | J110: =G110-E110 -> -45634 | K110: =VLOOKUP(D110,Sheet15!D:G,4,FALSE)
A111: 110 | B111: Josera | D111: Josera Meat Bites Mini Chicken 70g | E111: 45634 | F111: =VLOOKUP(D111,Sheet15!D:H,5,FALSE) -> مكتمل | H111: Yes | I111: =VLOOKUP(D111,Sheet15!D:K,8,FALSE) -> 2024-406529 | J111: =G111-E111 -> -45634 | K111: =VLOOKUP(D111,Sheet15!D:G,4,FALSE)
A112: 111 | B112: Josera | D112: Josera Meat Bites Mini Turkey 70g | E112: 45634 | F112: =VLOOKUP(D112,Sheet15!D:H,5,FALSE) -> مكتمل | H112: Yes | I112: =VLOOKUP(D112,Sheet15!D:K,8,FALSE) -> 2024-406563 | J112: =G112-E112 -> -45634 | K112: =VLOOKUP(D112,Sheet15!D:G,4,FALSE)
A113: 112 | B113: Josera | D113: Josera Meat Hearts Beef 70g | E113: 45634 | F113: =VLOOKUP(D113,Sheet15!D:H,5,FALSE) -> مكتمل | H113: Yes | I113: =VLOOKUP(D113,Sheet15!D:K,8,FALSE) -> 2024-406575 | J113: =G113-E113 -> -45634 | K113: =VLOOKUP(D113,Sheet15!D:G,4,FALSE)
A114: 113 | B114: Josera | D114: Josera Meat Hearts Chicken 70g | E114: 45634 | F114: =VLOOKUP(D114,Sheet15!D:H,5,FALSE) -> مكتمل | H114: Yes | I114: =VLOOKUP(D114,Sheet15!D:K,8,FALSE) -> 2024-406600 | J114: =G114-E114 -> -45634 | K114: =VLOOKUP(D114,Sheet15!D:G,4,FALSE)
A115: 114 | B115: Josera | D115: Josera Meat Hearts Turkey 70g | E115: 45634 | F115: =VLOOKUP(D115,Sheet15!D:H,5,FALSE) -> مكتمل | H115: Yes | I115: =VLOOKUP(D115,Sheet15!D:K,8,FALSE) -> 2024-406611 | J115: =G115-E115 -> -45634 | K115: =VLOOKUP(D115,Sheet15!D:G,4,FALSE)
A116: 115 | B116: JOSI | D116: JosiCat Meat Sticks Beef Lamb 20 x 35 g | E116: 45634 | F116: =VLOOKUP(D116,Sheet15!D:H,5,FALSE) -> مكتمل | H116: Yes | I116: =VLOOKUP(D116,Sheet15!D:K,8,FALSE) -> 2024-404647 | J116: =G116-E116 -> -45634 | K116: =VLOOKUP(D116,Sheet15!D:G,4,FALSE)
A117: 116 | B117: JOSI | D117: JosiCat Meat Sticks Chicken & Duck 20 x 35 g | E117: 45634 | F117: =VLOOKUP(D117,Sheet15!D:H,5,FALSE) -> مكتمل | H117: Yes | I117: =VLOOKUP(D117,Sheet15!D:K,8,FALSE) -> 2024-404683 | J117: =G117-E117 -> -45634 | K117: =VLOOKUP(D117,Sheet15!D:G,4,FALSE)
A118: 117 | B118: JOSI | D118: JosiCat Meat Sticks Salmon & Trout 20 x 35 g | E118: 45634 | F118: =VLOOKUP(D118,Sheet15!D:H,5,FALSE) -> مكتمل | H118: Yes | I118: =VLOOKUP(D118,Sheet15!D:K,8,FALSE) -> 2024-404692 | J118: =G118-E118 -> -45634 | K118: =VLOOKUP(D118,Sheet15!D:G,4,FALSE)
... A121: 120 | B121: JOSI | D121: JosiDog Meat Sticks Chicken 20 x 33 g | E121: 45634 | F121: =VLOOKUP(D121,Sheet15!D:H,5,FALSE) -> مكتمل | H121: Yes | I121: =VLOOKUP(D121,Sheet15!D:K,8,FALSE) -> 2024-404728 | J121: =G121-E121 -> -45634 | K121: =VLOOKUP(D121,Sheet15!D:G,4,FALSE)
A122: 121 | B122: Wellness | C122: 10738 | D122: WEL DD CORE SB Hlthy Wt 1.5kg | E122: 45651 | F122: =VLOOKUP(D122,Sheet15!D:H,5,FALSE) -> مكتمل | H122: Yes | I122: =VLOOKUP(D122,Sheet15!D:K,8,FALSE) -> 2025-18532 | J122: =G122-E122 -> -45651 | K122: =VLOOKUP(D122,Sheet15!D:G,4,FALSE)
A123: 122 | B123: Wellness | C123: 10739 | D123: WEL DD CORE SB Adult Ocean 1.5kg 5kg | E123: 45651 | F123: =VLOOKUP(D123,Sheet15!D:H,5,FALSE) -> مكتمل | H123: Yes | I123: =VLOOKUP(D123,Sheet15!D:K,8,FALSE) -> 2025-18473 | J123: =G123-E123 -> -45651 | K123: =VLOOKUP(D123,Sheet15!D:G,4,FALSE)
A124: 123 | B124: Wellness | C124: 10747 | D124: WEL DD CORE Puppy 1.5kg | E124: 45651 | F124: مكتمل | H124: Yes | I124: =VLOOKUP(D124,Sheet15!D:K,8,FALSE) -> #N/A | J124: =G124-E124 -> -45651 | K124: =VLOOKUP(D124,Sheet15!D:G,4,FALSE) -> #N/A
A125: 124 | B125: Wellness | C125: 10752 | D125: WEL DD CORE SB Original 1.5kg | E125: 45651 | F125: =VLOOKUP(D125,Sheet15!D:H,5,FALSE) -> مكتمل | H125: Yes | I125: =VLOOKUP(D125,Sheet15!D:K,8,FALSE) -> 2025-18511 | J125: =G125-E125 -> -45651 | K125: =VLOOKUP(D125,Sheet15!D:G,4,FALSE)
A126: 125 | B126: Wellness | C126: 10748 | D126: WEL DD CORE Senior 4/1.8kg | E126: 45651 | F126: مكتمل | H126: Yes | I126: =VLOOKUP(D126,Sheet15!D:K,8,FALSE) -> #N/A | J126: =G126-E126 -> -45651 | K126: =VLOOKUP(D126,Sheet15!D:G,4,FALSE) -> #N/A
A127: 126 | B127: Wellness | C127: 10749 | D127: WEL DD CORE Original 411.8kg | E127: 45651 | F127: =VLOOKUP(D127,Sheet15!D:H,5,FALSE) -> #N/A | I127: =VLOOKUP(D127,Sheet15!D:K,8,FALSE) -> #N/A | J127: =G127-E127 -> -45651 | K127: =VLOOKUP(D127,Sheet15!D:G,4,FALSE) -> #N/A
A128: 128 | B128: Wellness | C128: 10751 | D128: WEL DD CORE Healthy Weight 1.8kg | E128: 45651 | F128: مكتمل | I128: =VLOOKUP(D128,Sheet15!D:K,8,FALSE) -> #N/A | J128: =G128-E128 -> -45651 | K128: =VLOOKUP(D128,Sheet15!D:G,4,FALSE) -> #N/A
A129: 129 | B129: Wellness | C129: 10787 | D129: WEL DC CORE lamb 1.8kg , 10kg | E129: 45651 | F129: =VLOOKUP(D129,Sheet15!D:H,5,FALSE) -> مكتمل | I129: =VLOOKUP(D129,Sheet15!D:K,8,FALSE) -> 2025-117932 | J129: =G129-E129 -> -45651 | K129: =VLOOKUP(D129,Sheet15!D:G,4,FALSE)
A130: 130 | B130: Wellness | C130: 10809 | D130: WEL DD CORE LB Puppy 2.75kg 10kg | E130: 45651 | F130: =VLOOKUP(D130,Sheet15!D:H,5,FALSE) -> مكتمل | H130: Yes | I130: =VLOOKUP(D130,Sheet15!D:K,8,FALSE) -> 2025-18561 | J130: =G130-E130 -> -45651 | K130: =VLOOKUP(D130,Sheet15!D:G,4,FALSE)
A131: 131 | B131: Wellness | C131: 10811 | D131: WEL DD CORE SB Adult Original 5kg | E131: 45651 | F131: =VLOOKUP(D131,Sheet15!D:H,5,FALSE) -> مكتمل | H131: Yes | I131: =VLOOKUP(D131,Sheet15!D:K,8,FALSE) -> 2025-18517 | J131: =G131-E131 -> -45651 | K131: =VLOOKUP(D131,Sheet15!D:G,4,FALSE)
A132: 132 | B132: Wellness | C132: 10812 | D132: WEL DD CORE SB Adult Ocean 1.5kg 5kg | E132: 45651 | F132: =VLOOKUP(D132,Sheet15!D:H,5,FALSE) -> مكتمل | H132: Yes | I132: =VLOOKUP(D132,Sheet15!D:K,8,FALSE) -> 2025-18473 | J132: =G132-E132 -> -45651 | K132: =VLOOKUP(D132,Sheet15!D:G,4,FALSE)
A133: 133 | B133: Wellness | C133: 10813 | D133: WEL DD CORE SB Adult Low Fat 5kg | E133: 45651 | F133: =VLOOKUP(D133,Sheet15!D:H,5,FALSE) -> مكتمل | H133: Yes | I133: =VLOOKUP(D133,Sheet15!D:K,8,FALSE) -> 2025-18539 | J133: =G133-E133 -> -45651 | K133: =VLOOKUP(D133,Sheet15!D:G,4,FALSE)
A134: 134 | B134: Wellness | C134: 10746 | D134: WEL DD CORE OCEAN 1.8 & 10 KG | E134: 45651 | F134: =VLOOKUP(D134,Sheet15!D:H,5,FALSE) -> مكتمل | H134: Yes | I134: =VLOOKUP(D134,Sheet15!D:K,8,FALSE) -> 2025-5766 | J134: =G134-E134 -> -45651 | K134: =VLOOKUP(D134,Sheet15!D:G,4,FALSE)
A135: 135 | B135: Wellness | C135: 10753 | D135: WEL DD CORE Original 10kg | E135: 45651 | F135: =VLOOKUP(D135,Sheet15!D:H,5,FALSE) -> #N/A | I135: =VLOOKUP(D135,Sheet15!D:K,8,FALSE) -> #N/A | J135: =G135-E135 -> -45651 | K135: =VLOOKUP(D135,Sheet15!D:G,4,FALSE) -> #N/A
A136: 136 | B136: Wellness | C136: 10754 | D136: WEL DD CORE Healthy Weight 10kg | E136: 45651 | F136: =VLOOKUP(D136,Sheet15!D:H,5,FALSE) -> #N/A | I136: =VLOOKUP(D136,Sheet15!D:K,8,FALSE) -> #N/A | J136: =G136-E136 -> -45651 | K136: =VLOOKUP(D136,Sheet15!D:G,4,FALSE) -> #N/A
...

Sheet POed not arrived
A1: PPT Number | B1: Description | C1: Invoice Number | D1: PO Number
A2: PPT-288 | B2: KC 400g SOKC000819 | C2: SOKC000819 | D2: 2600044
A3: PPT-293 | B3: Applaws Dry x13 262567 262568 262569 262570 262571 262572 262573 262574 262575 262576 262577 262578 262579 | C3: 262567 262568 262569 262570 262571 262572 262573 262574 262575 262576 262577 262578 262579 | D3: 2600048->60

Sheet FDA Registration Priority
A1: brand | B1: Priority
A2: Instinct | B2: 1
A3: forza | B3: 2
A4: catidea | B4: 7
A5: bioPetActive | B5: 6
A6: josera | B6: 4
A7: zolux | B7: 3
A8: Absolute | B8: 5

Sheet Sheet1
B1: Clearance | C1: Arrived | D1: Ads | E1: PO | F1: Grr | G1: PI | H1: Review | I1: Notes | J1: Arabic Stickers
A2: Profine x3 | B2: x | C2: x | D2: x | E2: done | F2: done | G2: done
A3: Profine x2 | B3: x | E3: 273-274 | F3: 270-271 | G3: done
A4: Schesir Wet 900611 | B4: x | C4: x | D4: x | E4: 267 | F4: 264 | G4: done
A5: Schesir Wet 900609 | B5: x | C5: x | D5: x | E5: 266 | F5: 266 | G5: done
A6: KCIT220052A 10L x8 | B6: x | C6: x | D6: x | E6: 259 | F6: 261 | G6: done
A7: Zolux Rodywood | B7: x | C7: x | D7: x | E7: 260 - 261 | F7: 258-259 | G7: done
A8: Zolux Annah | B8: x | C8: x | E8: 269 | F8: 268 | G8: done
A9: MPS 357 | B9: x | C9: x | E9: 265 | F9: 265 | G9: done
A10: KCIT220102 Soya | B10: x | C10: x | D10: x | E10: 258 | F10: 257 | G10: done
A11: Applaws x2 228152 - 228153 | B11: x | C11: x | E11: 263-264 | F11: 262-263 | G11: done
A12: MPS 293 | B12: x | C12: x | E12: 262 | F12: 260 | G12: done
A13: Whitebridge | B13: x | C13: x | D13: x | E13: 277 | F13: 272
A14: MC | B14: x | C14: x | D14: x | E14: 285
A15: Zolux Rody.3 | B15: x | C15: x | D15: x | E15: 276 | F15: 275
A16: Nestle 9304235626 | B16: x | C16: x | D16: x | E16: 268 | F16: x
A17: Nestle 9304235820 | B17: x | C17: x | E17: 270 | F17: 276
A18: MPS404 | B18: x | C18: x | E18: 271 | F18: 269
A19: Kitcat Litter 10L x7 | B19: x | C19: x | E19: 272 | F19: 273
A20: KCIT220053C | B20: x | C20: x | D20: x | E20: 275 | F20: 274
A21: Zolux Tunisia 833520 | B21: x | C21: x | E21: 286 | F21: 282 | H21: تدخيل عالسستم
A22: Zolux Shenzen 837260 | B22: x | C22: x | D22: x | E22: 279 | F22: 281
A23: Nestle 9304236412 | B23: x | C23: x | E23: 280
A24: Nestle 9304235917 | B24: x | C24: x | E24: 278 | F24: 277
A25: Biosand 109/111/112 | B25: x | C25: x | H25: New itm
A26: Beaphar 2022S20613 | B26: x | C26: x | E26: 284
A27: Applaws Dry 229916+228713 | B27: x | C27: x | E27: 282-283 | F27: 279
A28: Nestle 9304236423 | B28: x | C28: x | E28: 281 | F28: 280
A29: Zolux Nantong 831605 | B29: x | C29: x | E29: x | F29: x | H29: تدخيل عالسستم
A30: Applaws 228154, 228155, 228157, 228714
A31: KCIT21011 | B31: x | C31: x | E31: 294
A32: LindoCat *3 - 2300000288 - 2300000283 - 2100002082 | B32: x | C32: x
A33: Sanal 5220366 | B33: x | C33: x | E33: 295 | F33: x | G33: x
A34: MPS 477 | B34: x | C34: x | D34: x | E34: x | F34: x | G34: x
A35: MPS 492 | B35: x | C35: x | D35: x | E35: x | F35: x | G35: x
A36: Zolux - China Rody.3 3442+ 3443 | B36: x | C36: x | E36: x | F36: x | G36: x
A37: LindoCat x3 - 2300000267 - 2300000271 - 2300000272 | B37: x | C37: x | D37: x | E37: x | F37: x | G37: x
A38: Schesir Wet 502098 7th 900608 | B38: x | C38: x | D38: x | E38: x | F38: x | G38: x
A39: Schesir Wet 502098 9th 900610 | B39: x | C39: x | D39: x | E39: x | F39: x | G39: x
A40: Schesir order 502175 - 2nd container 900670 | B40: x | C40: x | D40: x | E40: x | F40: x | G40: x
A41: Schesir order 502175 - 3rd container 900783 | B41: x | C41: x | D41: x | E41: x | F41: x | G41: x
A42: Schesir order 502175 - 6th container 900824 | B42: x | C42: x | D42: x | E42: x | F42: x | G42: x
A43: Schesir order 502175 - 5th container 900823 | B43: x | C43: x | D43: x | E43: x | F43: x | G43: x
A44: Schesir order 502175 - 4th container 900822 | B44: x | C44: x | D44: x | E44: x | F44: x | G44: x
A45: Zolux Ningbo Toys & Accessories | B45: x | C45: x | D45: x | E45: x | F45: x | G45: x
A46: CatIdea | B46: x | C46: x | D46: x | E46: x | F46: x | G46: x
A47: Prevue pet Bird Toys | B47: x | C47: x | E47: x
A48: Nestle 9304235673 | B48: x | C48: x | E48: 296
A49: Nestle 9304240995 | B49: x | C49: x | E49: x | F49: x | G49: x
A50: Nestle 9304241398 | B50: x | C50: x | E50: x | F50: x | G50: x
A51: Prevue Pet Cat trees ( 3565444 , 3565445 , 3565446 , 3565447 , 3565448 ) | B51: x | C51: x | D51: x | E51: x
A52: Manna Pro PO 8515 fruitables | B52: x | C52: x | E52: x
A53: Josera 570191315 - 570191499 | B53: x | C53: x | E53: x | F53: x | G53: x
A54: Josera 570195962 - 570195963 - 570195965 | B54: x | C54: x | E54: x | F54: x | G54: x
A55: Josera 570195676-570195678 | B55: x | C55: x | E55: x | F55: x | G55: x
A56: Prevue Pet 3565449 | B56: x | C56: x | D56: x
A57: CatIdea 2111MS032 | B57: x | C57: x | D57: x | E57: x | F57: x | G57: x
A58: Prevue Pet Dogs crate 3567631 | B58: x | C58: x
A59: KCIT220133A 10L | B59: x | C59: x | D59: x | E59: x | F59: x | G59: x
A60: Zolux - China (Gloves and leashes) 840896 | B60: x | C60: x
A61: Sanal 5220366 | B61: x | C61: x | D61: x | E61: x | F61: x | G61: x
A62: Laviosa (LindoCat +signor gatto ) 2300000334 - 2300000336 - 2300000339 | B62: x | C62: x | D62: x | E62: x | F62: x | G62: x
A63: Laviosa (Lindocat +Signor Gatto) 2300000326 -2300000327-2300000331 | B63: x | C63: x | D63: x | E63: x | F63: x | G63: x
A64: Nestle 9304241398 | B64: x | C64: x | D64: x | E64: x | F64: x | G64: x
A65: Nestle 9304240995 | B65: x | C65: x | D65: x | E65: x | F65: x | G65: x
A66: Schesir 900822 | B66: x | C66: x | D66: x | E66: x | F66: x | G66: x
A67: Schiser 900670 | B67: x | C67: x | D67: x | E67: x | F67: x | G67: x
A68: Schesir 900824 | B68: x | C68: x | D68: x | E68: x | F68: x | G68: x
A69: Schesir 900608 | B69: x | C69: x | D69: x | E69: x | F69: x | G69: x
A70: Schesir 900610 | B70: x | C70: x | D70: x | E70: x | F70: x | G70: x
A71: Schesir 900783 | B71: x | C71: x | D71: x | E71: x | F71: x | G71: x
A72: Schesir 900823 | B72: x | C72: x | D72: x | E72: x | F72: x | G72: x
... A82: LindoCat *3 - 2300000288 - 2300000283 - 2100002082 | B82: x | C82: x | D82: x | E82: x | F82: x | G82: x
A83: KCIT210498 - KCIT210499 PUREE | B83: x | C83: x | E83: 340-341
A84: KCIT210112+KCIT210113 400g | B84: x | C84: x | E84: 342-343
A85: KCIT220139 - Cuisine | B85: x | C85: x | E85: 346

Sheet Dashboard
A1: ='Arrived Shipments'!F2 -> Josera | B1: ='Arrived Shipments'!M2 -> 45225 | C1: ='Arrived Shipments'!R2 -> SMACC | D1: ='Arrived Shipments'!S2 | E1: {=UNIQUE(A1:A296)} -> Josera | F1: =COUNTIF(A1:A244,E1) -> 23 | G1: =COUNTA(B:B) -> 343 | H1: =COUNTA(C:C) -> 342 | I1: =H1/G1 -> 0.99708455 | J1: =K1-I1 -> 0.0029154519 | K1: 1
A2: ='Arrived Shipments'!F3 -> Kit Cat | B2: ='Arrived Shipments'!M3 -> 45236 | C2: ='Arrived Shipments'!R3 -> SMACC | D2: ='Arrived Shipments'!S3 | E2: Kit Cat | F2: =COUNTIF(A2:A245,E2) -> 44 | G2: =COUNTIFS(B1:B1000, ">=" & EDATE(TODAY(), -3), B1:B1000, "<=" & TODAY()) -> 0 | H2: =COUNTIFS(B1:B1000, ">=" & EDATE(TODAY(), -3), B1:B1000, "<=" & TODAY(), C1:C1000, "<>") -> 0 | I2: =H2/G2 -> #DIV/0! | J2: =K2-I2 -> #DIV/0! | K2: 1
A3: ='Arrived Shipments'!F4 -> Laroy | B3: ='Arrived Shipments'!M4 -> 45229 | C3: ='Arrived Shipments'!R4 -> SMACC | D3: ='Arrived Shipments'!S4 | E3: Laroy | F3: =COUNTIF(A3:A246,E3) -> 20 | J3: =AVERAGE(D:D) -> 14.568905
A4: ='Arrived Shipments'!F5 -> Kit Cat | B4: ='Arrived Shipments'!M5 -> 45200 | C4: ='Arrived Shipments'!R5 -> SMACC | D4: ='Arrived Shipments'!S5 | E4: Schesir | F4: =COUNTIF(A4:A247,E4) -> 20 | J4: =COUNTIF(D:D,"<8") -> 139 | K4: =COUNTIF(D:D,">7") -> 144
A5: ='Arrived Shipments'!F6 -> Schesir | B5: ='Arrived Shipments'!M6 -> 45225 | C5: ='Arrived Shipments'!R6 -> SMACC | D5: ='Arrived Shipments'!S6 | E5: Inner Mongolia | F5: =COUNTIF(A5:A248,E5) -> 5 | H5: =J4/K4 -> 0.96527778 | I5: =K5-H5 -> 0.034722222 | K5: 1
A6: ='Arrived Shipments'!F7 -> Schesir | B6: ='Arrived Shipments'!M7 -> 45225 | C6: ='Arrived Shipments'!R7 -> SMACC | D6: ='Arrived Shipments'!S7 | E6: INABA | F6: =COUNTIF(A6:A249,E6) -> 5
A7: ='Arrived Shipments'!F8 -> Laroy | B7: ='Arrived Shipments'!M8 -> 45241 | C7: ='Arrived Shipments'!R8 -> SMACC | D7: ='Arrived Shipments'!S8 | E7: Sanal | F7: =COUNTIF(A7:A250,E7) -> 6
A8: ='Arrived Shipments'!F9 -> Inner Mongolia | B8: ='Arrived Shipments'!M9 -> 45238 | C8: ='Arrived Shipments'!R9 -> SMACC | D8: ='Arrived Shipments'!S9 | E8: Butchers | F8: =COUNTIF(A8:A251,E8) -> 12
A9: ='Arrived Shipments'!F10 -> Kit Cat | B9: ='Arrived Shipments'!M10 -> 45241 | C9: ='Arrived Shipments'!R10 -> SMACC | D9: ='Arrived Shipments'!S10 | E9: Applaws | F9: =COUNTIF(A9:A252,E9) -> 20
A10: ='Arrived Shipments'!F11 -> INABA | B10: ='Arrived Shipments'!M11 -> 45270 | C10: ='Arrived Shipments'!R11 -> SMACC | D10: ='Arrived Shipments'!S11 | E10: CatIdea | F10: =COUNTIF(A10:A253,E10) -> 1
A11: ='Arrived Shipments'!F12 -> Sanal | B11: ='Arrived Shipments'!M12 -> 45265 | C11: ='Arrived Shipments'!R12 -> SMACC | D11: ='Arrived Shipments'!S12 | E11: MyFamily | F11: =COUNTIF(A11:A254,E11) -> 2
A12: ='Arrived Shipments'!F13 -> Schesir | B12: ='Arrived Shipments'!M13 -> 45248 | C12: ='Arrived Shipments'!R13 -> SMACC | D12: ='Arrived Shipments'!S13 | E12: Versele Laga
A13: ='Arrived Shipments'!F14 -> Schesir | B13: ='Arrived Shipments'!M14 -> 44907 | C13: ='Arrived Shipments'!R14 -> SMACC | D13: ='Arrived Shipments'!S14 | E13: Laviosa | F13: =COUNTIF(A13:A256,E13) -> 18
A14: ='Arrived Shipments'!F15 -> Laroy | B14: ='Arrived Shipments'!M15 -> 45270 | C14: ='Arrived Shipments'!R15 -> SMACC | D14: ='Arrived Shipments'!S15 | E14: Biosand | F14: =COUNTIF(A14:A257,E14) -> 5
A15: ='Arrived Shipments'!F16 -> Butchers | B15: ='Arrived Shipments'!M16 -> 45273 | C15: ='Arrived Shipments'!R16 -> SMACC | D15: ='Arrived Shipments'!S16 | E15: Princess | F15: =COUNTIF(A15:A258,E15) -> 3
A16: ='Arrived Shipments'!F17 -> Kit Cat | B16: ='Arrived Shipments'!M17 -> 45281 | C16: ='Arrived Shipments'!R17 -> SMACC | D16: ='Arrived Shipments'!S17 | F16: =COUNTIF(A16:A259,E16) -> 0
A17: ='Arrived Shipments'!F18 -> Kit Cat | B17: ='Arrived Shipments'!M18 -> 45280 | C17: ='Arrived Shipments'!R18 -> SMACC | D17: ='Arrived Shipments'!S18 | E17: Dr.Clauder | F17: =COUNTIF(A17:A260,E17) -> 5
A18: ='Arrived Shipments'!F19 -> Butchers | B18: ='Arrived Shipments'!M19 -> 45273 | C18: ='Arrived Shipments'!R19 -> SMACC | D18: ='Arrived Shipments'!S19 | E18: Beaphar | F18: =COUNTIF(A18:A261,E18) -> 3
A19: ='Arrived Shipments'!F20 -> Kit Cat | B19: ='Arrived Shipments'!M20 -> 45293 | C19: ='Arrived Shipments'!R20 -> SMACC | D19: ='Arrived Shipments'!S20 | E19: Codico | F19: =COUNTIF(A19:A262,E19) -> 3
A20: ='Arrived Shipments'!F21 -> Kit Cat | B20: ='Arrived Shipments'!M21 -> 45293 | C20: ='Arrived Shipments'!R21 -> SMACC | D20: ='Arrived Shipments'!S21 | E20: Zolux | F20: =COUNTIF(A20:A263,E20) -> 12
A21: ='Arrived Shipments'!F22 -> Applaws | B21: ='Arrived Shipments'!M22 -> 45278 | C21: ='Arrived Shipments'!R22 -> SMACC | D21: ='Arrived Shipments'!S22 | E21: HEALTH & HAPPINESS | F21: =COUNTIF(A21:A264,E21) -> 5
A22: ='Arrived Shipments'!F23 -> Applaws | B22: ='Arrived Shipments'!M23 -> 45291 | C22: ='Arrived Shipments'!R23 -> SMACC | D22: ='Arrived Shipments'!S23 | E22: Dubex | F22: =COUNTIF(A22:A265,E22) -> 2
A23: ='Arrived Shipments'!F24 -> CatIdea | B23: ='Arrived Shipments'!M24 -> 45300 | C23: ='Arrived Shipments'!R24 -> 45328 | D23: ='Arrived Shipments'!S24 -> 28 | E23: MPS | F23: =COUNTIF(A23:A266,E23) -> 5
A24: ='Arrived Shipments'!F25 -> MyFamily | B24: ='Arrived Shipments'!M25 -> 45277 | C24: ='Arrived Shipments'!R25 -> SMACC | D24: ='Arrived Shipments'!S25 | E24: Dairy Pet | F24: =COUNTIF(A24:A267,E24) -> 1
A25: ='Arrived Shipments'!F26 -> Laroy | B25: ='Arrived Shipments'!M26 | C25: ='Arrived Shipments'!R26 | D25: ='Arrived Shipments'!S26 | E25: zupreem | F25: =COUNTIF(A25:A268,E25) -> 3
A26: ='Arrived Shipments'!F27 -> Kit Cat | B26: ='Arrived Shipments'!M27 -> 45302 | C26: ='Arrived Shipments'!R27 -> 45328 | D26: ='Arrived Shipments'!S27 -> 26 | E26: MPB | F26: =COUNTIF(A26:A269,E26) -> 1
A27: ='Arrived Shipments'!F28 -> Versele Laga | B27: ='Arrived Shipments'!M28 -> 45325 | C27: ='Arrived Shipments'!R28 -> 45329 | D27: ='Arrived Shipments'!S28 -> 4 | E27: Nasta | F27: =COUNTIF(A27:A270,E27) -> 1
A28: ='Arrived Shipments'!F29 -> Versele Laga | B28: ='Arrived Shipments'!M29 -> 45325 | C28: ='Arrived Shipments'!R29 -> 45329 | D28: ='Arrived Shipments'!S29 -> 4 | E28: Stefanplast | F28: =COUNTIF(A28:A271,E28) -> 1
... A37: ='Arrived Shipments'!F38 -> Schesir | B37: ='Arrived Shipments'!M38 -> 45321 | C37: ='Arrived Shipments'!R38 -> 45328 | D37: ='Arrived Shipments'!S38 -> 7 | E37: Felyn Go | F37: =COUNTIF(A37:A280,E37) -> 1
A38: ='Arrived Shipments'!F39 -> Laviosa | B38: ='Arrived Shipments'!M39 -> 45324 | C38: ='Arrived Shipments'!R39 -> 45328 | D38: ='Arrived Shipments'!S39 -> 4 | F38: =COUNTIF(A38:A281,E38) -> 0
A39: ='Arrived Shipments'!F40 -> Biosand | B39: ='Arrived Shipments'!M40 -> 45311 | C39: ='Arrived Shipments'!R40 -> 45329 | D39: ='Arrived Shipments'!S40 -> 18 | F39: =COUNTIF(A39:A282,E39) -> 0
A40: ='Arrived Shipments'!F41 -> Schesir | B40: ='Arrived Shipments'!M41 -> 45321 | C40: ='Arrived Shipments'!R41 -> 45329 | D40: ='Arrived Shipments'!S41 -> 8 | F40: =COUNTIF(A40:A283,E40) -> 0
A41: ='Arrived Shipments'!F42 -> INABA | B41: ='Arrived Shipments'!M42 -> 45321 | C41: ='Arrived Shipments'!R42 -> 45329 | D41: ='Arrived Shipments'!S42 -> 8 | F41: =COUNTIF(A41:A284,E41) -> 0
A42: ='Arrived Shipments'!F43 -> Kit Cat | B42: ='Arrived Shipments'!M43 -> 45330 | C42: ='Arrived Shipments'!R43 -> 45333 | D42: ='Arrived Shipments'!S43 -> 3 | F42: =COUNTIF(A42:A285,E42) -> 0
A43: ='Arrived Shipments'!F44 -> Kit Cat | B43: ='Arrived Shipments'!M44 -> 45329 | C43: ='Arrived Shipments'!R44 -> 45333 | D43: ='Arrived Shipments'!S44 -> 4 | F43: =COUNTIF(A43:A286,E43) -> 0
A44: ='Arrived Shipments'!F45 -> Schesir | B44: ='Arrived Shipments'!M45 -> 45335 | C44: ='Arrived Shipments'!R45 -> 45336 | D44: ='Arrived Shipments'!S45 -> 1 | F44: =COUNTIF(A44:A287,E44) -> 0
A45: ='Arrived Shipments'!F46 -> Schesir | B45: ='Arrived Shipments'!M46 -> 45307 | C45: ='Arrived Shipments'!R46 -> 45361 | D45: ='Arrived Shipments'!S46 -> 54 | F45: =COUNTIF(A45:A288,E45) -> 0
A46: ='Arrived Shipments'!F47 -> Schesir | B46: ='Arrived Shipments'!M47 -> 45308 | C46: ='Arrived Shipments'!R47 -> 45360 | D46: ='Arrived Shipments'!S47 -> 52 | F46: =COUNTIF(A46:A289,E46) -> 0
A47: ='Arrived Shipments'!F48 -> Applaws | B47: ='Arrived Shipments'!M48 -> 45353 | C47: ='Arrived Shipments'!R48 -> 45357 | D47: ='Arrived Shipments'!S48 -> 4 | F47: =COUNTIF(A47:A290,E47) -> 0
A48: ='Arrived Shipments'!F49 -> Sanal | B48: ='Arrived Shipments'!M49 -> 45353 | C48: ='Arrived Shipments'!R49 -> 45361 | D48: ='Arrived Shipments'!S49 -> 8 | F48: =COUNTIF(A48:A291,E48) -> 0
A49: ='Arrived Shipments'!F50 -> Applaws | B49: ='Arrived Shipments'!M50 -> 45362 | C49: ='Arrived Shipments'!R50 -> 45364 | D49: ='Arrived Shipments'!S50 -> 2 | F49: =COUNTIF(A49:A292,E49) -> 0
... A56: ='Arrived Shipments'!F57 -> Applaws | B56: ='Arrived Shipments'!M57 -> 45378 | C56: ='Arrived Shipments'!R57 -> 45399 | D56: ='Arrived Shipments'!S57 -> 21 | F56: =COUNTIF(A56:A299,E56) -> 0
B57: ='Arrived Shipments'!M58 | C57: ='Arrived Shipments'!R58 | D57: ='Arrived Shipments'!S58 | F57: =COUNTIF(A57:A300,E57) -> 0
B58: ='Arrived Shipments'!M59 | C58: ='Arrived Shipments'!R59 | D58: ='Arrived Shipments'!S59 | F58: =COUNTIF(A58:A301,E58) -> 0
A59: ='Arrived Shipments'!F60 -> Butchers | B59: ='Arrived Shipments'!M60 -> 45398 | C59: ='Arrived Shipments'!R60 -> 45411 | D59: ='Arrived Shipments'!S60 -> 13 | F59: =COUNTIF(A59:A302,E59) -> 0
B60: ='Arrived Shipments'!M61 | C60: ='Arrived Shipments'!R61 | D60: ='Arrived Shipments'!S61 | F60: =COUNTIF(A60:A303,E60) -> 0
B61: ='Arrived Shipments'!M62 | C61: ='Arrived Shipments'!R62 | D61: ='Arrived Shipments'!S62 | F61: =COUNTIF(A61:A304,E61) -> 0
A62: ='Arrived Shipments'!F63 -> Applaws | B62: ='Arrived Shipments'!M63 -> 45389 | C62: ='Arrived Shipments'!R63 -> 45399 | D62: ='Arrived Shipments'!S63 -> 10 | F62: =COUNTIF(A62:A305,E62) -> 0
A63: ='Arrived Shipments'!F64 -> Schesir | B63: ='Arrived Shipments'!M64 -> 45397 | C63: ='Arrived Shipments'!R64 -> 45405 | D63: ='Arrived Shipments'!S64 -> 8 | F63: =COUNTIF(A63:A306,E63) -> 0
A64: ='Arrived Shipments'!F65 -> Schesir | B64: ='Arrived Shipments'!M65 -> 45397 | C64: ='Arrived Shipments'!R65 -> 45405 | D64: ='Arrived Shipments'!S65 -> 8 | F64: =COUNTIF(A64:A307,E64) -> 0
A65: ='Arrived Shipments'!F66 -> Schesir | B65: ='Arrived Shipments'!M66 -> 45397 | C65: ='Arrived Shipments'!R66 -> 45405 | D65: ='Arrived Shipments'!S66 -> 8 | F65: =COUNTIF(A65:A308,E65) -> 0
A66: ='Arrived Shipments'!F67 -> Schesir | B66: ='Arrived Shipments'!M67 -> 45397 | C66: ='Arrived Shipments'!R67 -> 45410 | D66: ='Arrived Shipments'!S67 -> 13 | F66: =COUNTIF(A66:A309,E66) -> 0
A67: ='Arrived Shipments'!F68 -> Kit Cat | B67: ='Arrived Shipments'!M68 -> 45397 | C67: ='Arrived Shipments'!R68 -> 45405 | D67: ='Arrived Shipments'!S68 -> 8 | F67: =COUNTIF(A67:A310,E67) -> 0
B68: ='Arrived Shipments'!M69 | C68: ='Arrived Shipments'!R69 | D68: ='Arrived Shipments'!S69 | F68: =COUNTIF(A68:A311,E68) -> 0
A69: ='Arrived Shipments'!F70 -> Josera | B69: ='Arrived Shipments'!M70 -> 45399 | C69: ='Arrived Shipments'!R70 -> 45412 | D69: ='Arrived Shipments'!S70 -> 13 | F69: =COUNTIF(A69:A312,E69) -> 0
A70: ='Arrived Shipments'!F71 -> Schesir | B70: ='Arrived Shipments'!M71 -> 45398 | C70: ='Arrived Shipments'!R71 -> 45483 | D70: ='Arrived Shipments'!S71 -> 85 | F70: =COUNTIF(A70:A313,E70) -> 0
B71: ='Arrived Shipments'!M72 | C71: ='Arrived Shipments'!R72 | D71: ='Arrived Shipments'!S72 | F71: =COUNTIF(A71:A314,E71) -> 0
B72: ='Arrived Shipments'!M73 | C72: ='Arrived Shipments'!R73 | D72: ='Arrived Shipments'!S73 | F72: =COUNTIF(A72:A315,E72) -> 0
B73: ='Arrived Shipments'!M74 | C73: ='Arrived Shipments'!R74 | D73: ='Arrived Shipments'!S74 | F73: =COUNTIF(A73:A316,E73) -> 0
B74: ='Arrived Shipments'!M75 | C74: ='Arrived Shipments'!R75 | D74: ='Arrived Shipments'!S75 | F74: =COUNTIF(A74:A317,E74) -> 0
A75: ='Arrived Shipments'!F76 -> Schesir | B75: ='Arrived Shipments'!M76 -> 45407 | C75: ='Arrived Shipments'!R76 -> 45411 | D75: ='Arrived Shipments'!S76 -> 4 | F75: =COUNTIF(A75:A318,E75) -> 0
A76: ='Arrived Shipments'!F77 -> Kit Cat | B76: ='Arrived Shipments'!M77 -> 45405 | C76: ='Arrived Shipments'!R77 -> 45411 | D76: ='Arrived Shipments'!S77 -> 6 | F76: =COUNTIF(A76:A319,E76) -> 0
A77: ='Arrived Shipments'!F78 -> Kit Cat | B77: ='Arrived Shipments'!M78 -> 45409 | C77: ='Arrived Shipments'!R78 -> 45447 | D77: ='Arrived Shipments'!S78 -> 38 | F77: =COUNTIF(A77:A320,E77) -> 0
A78: ='Arrived Shipments'!F79 -> Applaws | B78: ='Arrived Shipments'!M79 -> 45402 | C78: ='Arrived Shipments'!R79 -> 45405 | D78: ='Arrived Shipments'!S79 -> 3 | F78: =COUNTIF(A78:A321,E78) -> 0
A79: ='Arrived Shipments'!F80 -> Dr.Clauder | B79: ='Arrived Shipments'!M80 -> 45399 | C79: ='Arrived Shipments'!R80 -> 45482 | D79: ='Arrived Shipments'!S80 -> 83 | F79: =COUNTIF(A79:A322,E79) -> 0
A80: ='Arrived Shipments'!F81 -> Josera | B80: ='Arrived Shipments'!M81 -> 45402 | C80: ='Arrived Shipments'!R81 -> 45413 | D80: ='Arrived Shipments'!S81 -> 11 | F80: =COUNTIF(A80:A323,E80) -> 0
A81: ='Arrived Shipments'!F82 -> Josera | B81: ='Arrived Shipments'!M82 -> 45407 | C81: ='Arrived Shipments'!R82 -> 45414 | D81: ='Arrived Shipments'!S82 -> 7 | F81: =COUNTIF(A81:A324,E81) -> 0
A82: ='Arrived Shipments'!F83 -> Versele Laga | B82: ='Arrived Shipments'!M83 -> 45406 | C82: ='Arrived Shipments'!R83 -> 45417 | D82: ='Arrived Shipments'!S83 -> 11 | F82: =COUNTIF(A82:A325,E82) -> 0
A83: ='Arrived Shipments'!F84 -> Josera | B83: ='Arrived Shipments'!M84 -> 45408 | C83: ='Arrived Shipments'!R84 -> 45417 | D83: ='Arrived Shipments'!S84 -> 9 | F83: =COUNTIF(A83:A326,E83) -> 0
A84: ='Arrived Shipments'!F85 -> Laroy | B84: ='Arrived Shipments'!M85 -> 45409 | C84: ='Arrived Shipments'!R85 -> 45414 | D84: ='Arrived Shipments'!S85 -> 5 | F84: =COUNTIF(A84:A327,E84) -> 0
A85: ='Arrived Shipments'!F86 -> Laroy | B85: ='Arrived Shipments'!M86 -> 45409 | C85: ='Arrived Shipments'!R86 -> 45532 | D85: ='Arrived Shipments'!S86 -> 123 | F85: =COUNTIF(A85:A328,E85) -> 0
A86: ='Arrived Shipments'!F87 -> Laroy | B86: ='Arrived Shipments'!M87 -> 45409 | C86: ='Arrived Shipments'!R87 -> 45417 | D86: ='Arrived Shipments'!S87 -> 8 | F86: =COUNTIF(A86:A329,E86) -> 0
... A88: ='Arrived Shipments'!F89 -> Laviosa | B88: ='Arrived Shipments'!M89 -> 45416 | C88: ='Arrived Shipments'!R89 -> 45420 | D88: ='Arrived Shipments'!S89 -> 4 | F88: =COUNTIF(A88:A331,E88) -> 0
A89: ='Arrived Shipments'!F90 -> Beaphar | B89: ='Arrived Shipments'!M90 -> 45410 | C89: ='Arrived Shipments'!R90 -> 45483 | D89: ='Arrived Shipments'!S90 -> 73
A90: ='Arrived Shipments'!F91 -> Butchers | B90: ='Arrived Shipments'!M91 -> 45423 | C90: ='Arrived Shipments'!R91 -> 45456 | D90: ='Arrived Shipments'!S91 -> 33
A91: ='Arrived Shipments'!F92 -> Applaws | B91: ='Arrived Shipments'!M92 -> 45413 | C91: ='Arrived Shipments'!R92 -> 45417 | D91: ='Arrived Shipments'!S92 -> 4
A92: ='Arrived Shipments'!F93 -> Codico | B92: ='Arrived Shipments'!M93 -> 45421 | C92: ='Arrived Shipments'!R93 -> 45498 | D92: ='Arrived Shipments'!S93 -> 77
A93: ='Arrived Shipments'!F94 -> Inner Mongolia | B93: ='Arrived Shipments'!M94 -> 45420 | C93: ='Arrived Shipments'!R94 -> 45431 | D93: ='Arrived Shipments'!S94 -> 11
A94: ='Arrived Shipments'!F95 -> Inner Mongolia | B94: ='Arrived Shipments'!M95 -> 45426 | C94: ='Arrived Shipments'!R95 -> 45431 | D94: ='Arrived Shipments'!S95 -> 5
A95: ='Arrived Shipments'!F96 -> Josera | B95: ='Arrived Shipments'!M96 -> 45416 | C95: ='Arrived Shipments'!R96 -> 45417 | D95: ='Arrived Shipments'!S96 -> 1
A96: ='Arrived Shipments'!F97 -> Laroy | B96: ='Arrived Shipments'!M97 -> 45420 | C96: ='Arrived Shipments'!R97 -> 45426 | D96: ='Arrived Shipments'!S97 -> 6
A97: ='Arrived Shipments'!F98 -> Applaws | B97: ='Arrived Shipments'!M98 -> 45426 | C97: ='Arrived Shipments'!R98 -> 45428 | D97: ='Arrived Shipments'!S98 -> 2
A98: ='Arrived Shipments'!F99 -> Butchers | B98: ='Arrived Shipments'!M99 -> 45431 | C98: ='Arrived Shipments'!R99 -> 45456 | D98: ='Arrived Shipments'!S99 -> 25
A99: ='Arrived Shipments'!F100 -> Applaws | B99: ='Arrived Shipments'!M100 -> 45432 | C99: ='Arrived Shipments'!R100 -> 45445 | D99: ='Arrived Shipments'!S100 -> 13
A100: ='Arrived Shipments'!F101 -> Dr.Clauder | B100: ='Arrived Shipments'!M101 -> 45437 | C100: ='Arrived Shipments'!R101 -> 45476 | D100: ='Arrived Shipments'!S101 -> 39
... A196: ='Arrived Shipments'!F197 -> Kit Cat | B196: ='Arrived Shipments'!M197 -> 45641 | C196: ='Arrived Shipments'!R197 -> 45641 | D196: ='Arrived Shipments'!S197
A197: ='Arrived Shipments'!F198 -> Josera | B197: =#REF! -> #REF! | C197: ='Arrived Shipments'!R198 -> 45638 | D197: ='Arrived Shipments'!S198 -> 4
A198: ='Arrived Shipments'!F199 -> Laviosa | B198: ='Arrived Shipments'!M198 -> 45634 | C198: ='Arrived Shipments'!R199 -> 45638 | D198: ='Arrived Shipments'!S199
A199: ='Arrived Shipments'!F200 -> Butchers | B199: ='Arrived Shipments'!M200 -> 45641 | C199: ='Arrived Shipments'!R200 -> 45642 | D199: ='Arrived Shipments'!S200 -> 1
A200: ='Arrived Shipments'!F201 -> Applaws | B200: ='Arrived Shipments'!M201 -> 45651 | C200: ='Arrived Shipments'!R201 -> 45693 | D200: ='Arrived Shipments'!S201 -> 42
A201: ='Arrived Shipments'!F202 -> Inner Mongolia | B201: ='Arrived Shipments'!M202 -> 45670 | C201: ='Arrived Shipments'!R202 -> 45676 | D201: ='Arrived Shipments'!S202 -> 6
A202: ='Arrived Shipments'!F203 -> Inner Mongolia | B202: ='Arrived Shipments'!M203 -> 45670 | C202: ='Arrived Shipments'!R203 -> 45676 | D202: ='Arrived Shipments'!S203 -> 6
A203: ='Arrived Shipments'!F204 -> Josera | B203: ='Arrived Shipments'!M204 -> 45651 | C203: ='Arrived Shipments'!R204 -> 45652 | D203: ='Arrived Shipments'!S204 -> 1
A204: ='Arrived Shipments'!F205 -> Kit Cat | B204: ='Arrived Shipments'!M205 -> 45690 | C204: ='Arrived Shipments'!R205 -> 45690 | D204: ='Arrived Shipments'!S205
A205: ='Arrived Shipments'!F206 -> Josera | B205: ='Arrived Shipments'!M206 -> 45670 | C205: ='Arrived Shipments'!R206 -> 45676 | D205: ='Arrived Shipments'!S206 -> 6
A206: ='Arrived Shipments'!F207 -> Laviosa | B206: ='Arrived Shipments'!M207 -> 45673 | C206: ='Arrived Shipments'!R207 -> 45677 | D206: ='Arrived Shipments'!S207 -> 4
A207: ='Arrived Shipments'!F208 -> Applaws | B207: ='Arrived Shipments'!M208 -> 45670 | C207: ='Arrived Shipments'!R208 -> 45677 | D207: ='Arrived Shipments'!S208 -> 7
A208: ='Arrived Shipments'!F209 -> Applaws | B208: ='Arrived Shipments'!M209 -> 45692 | C208: ='Arrived Shipments'!R209 -> 45693 | D208: ='Arrived Shipments'!S209 -> 1
A209: ='Arrived Shipments'!F210 -> Sanal | B209: ='Arrived Shipments'!M210 -> 45690 | C209: ='Arrived Shipments'!R210 -> 45691 | D209: ='Arrived Shipments'!S210 -> 1
A210: ='Arrived Shipments'!F211 -> Josera | B210: ='Arrived Shipments'!M211 -> 45670 | C210: ='Arrived Shipments'!R211 -> 45678 | D210: ='Arrived Shipments'!S211 -> 8
...

Sheet Saud
A1: =IFERROR(__xludf.DUMMYFUNCTION("IMPORTRANGE(""https://docs.google.com/spreadsheets/d/1Xa44tXRk3vht04Hc9meui-dd7ZRS0F6gZUdCCapKJ5E/edit?gid=1471429910#gid=1471429910"",""2024!A1:Z20000"")")," ") | B1: =IFERROR(__xludf.DUMMYFUNCTION("""COMPUTED_VALUE"""),"Vendor Code") -> Vendor Code | C1: =IFERROR(__xludf.DUMMYFUNCTION("""COMPUTED_VALUE"""),"Reference number") -> Reference number | E1: =IFERROR(__xludf.DUMMYFUNCTION("""COMPUTED_VALUE"""),"Status") -> Status | F1: =IFERROR(__xludf.DUMMYFUNCTION("""COMPUTED_VALUE"""),"Description") -> Description | G1: =IFERROR(__xludf.DUMMYFUNCTION("""COMPUTED_VALUE"""),"NAME AR") -> NAME AR | H1: =IFERROR(__xludf.DUMMYFUNCTION("""COMPUTED_VALUE"""),"Product Registration") -> Product Registration | J1: =IFERROR(__xludf.DUMMYFUNCTION("""COMPUTED_VALUE"""),"EXPIRY DATE ") -> EXPIRY DATE | L1: =IFERROR(__xludf.DUMMYFUNCTION("""COMPUTED_VALUE"""),"Vendor Code") -> Vendor Code
A2: =IFERROR(__xludf.DUMMYFUNCTION("""COMPUTED_VALUE"""),1.0) -> 1 | B2: =IFERROR(__xludf.DUMMYFUNCTION("""COMPUTED_VALUE""")," ") | C2: =IFERROR(__xludf.DUMMYFUNCTION("""COMPUTED_VALUE"""),"P-1-N-180820-2290") -> P-1-N-180820-2290 | E2: =IFERROR(__xludf.DUMMYFUNCTION("""COMPUTED_VALUE"""),"REJECTED") -> REJECTED | F2: =IFERROR(__xludf.DUMMYFUNCTION("""COMPUTED_VALUE"""),"Butcher's Natural & Healthy Dog with Chicken and Rice Pate 390g") -> Butcher's Natural & Healthy Dog with Chicken and Rice Pate 390g | G2: =IFERROR(__xludf.DUMMYFUNCTION("""COMPUTED_VALUE"""),"بوتشرز طبيعي وصحي للكلاب مع الدجاج والرز باتي 390 جم") -> بوتشرز طبيعي وصحي للكلاب مع الدجاج والرز باتي 390 جم | K2: =IFERROR(__xludf.DUMMYFUNCTION("""COMPUTED_VALUE"""),"بوتشرز بت كير ال تي دي") -> بوتشرز بت كير ال تي دي | L2: =IFERROR(__xludf.DUMMYFUNCTION("""COMPUTED_VALUE"""),"B1104") -> B1104
A3: =IFERROR(__xludf.DUMMYFUNCTION("""COMPUTED_VALUE"""),2.0) -> 2 | B3: =IFERROR(__xludf.DUMMYFUNCTION("""COMPUTED_VALUE"""),"B1107") -> B1107 | C3: =IFERROR(__xludf.DUMMYFUNCTION("""COMPUTED_VALUE"""),"P-1-N-180820-2291") -> P-1-N-180820-2291 | E3: =IFERROR(__xludf.DUMMYFUNCTION("""COMPUTED_VALUE"""),"REJECTED") -> REJECTED | F3: =IFERROR(__xludf.DUMMYFUNCTION("""COMPUTED_VALUE"""),"Butcher's Natural & Healthy Dog with Beef and Rice Pate 390g") -> Butcher's Natural & Healthy Dog with Beef and Rice Pate 390g | G3: =IFERROR(__xludf.DUMMYFUNCTION("""COMPUTED_VALUE"""),"بوتشرز طبيعي وصحي للكلاب مع لحم البقر والرز باتي 390 جم") -> بوتشرز طبيعي وصحي للكلاب مع لحم البقر والرز باتي 390 جم | K3: =IFERROR(__xludf.DUMMYFUNCTION("""COMPUTED_VALUE"""),"Factory") -> Factory | L3: =IFERROR(__xludf.DUMMYFUNCTION("""COMPUTED_VALUE"""),"B1107") -> B1107
A4: =IFERROR(__xludf.DUMMYFUNCTION("""COMPUTED_VALUE"""),3.0) -> 3 | B4: =IFERROR(__xludf.DUMMYFUNCTION("""COMPUTED_VALUE"""),"B1110") -> B1110 | C4: =IFERROR(__xludf.DUMMYFUNCTION("""COMPUTED_VALUE"""),"P-1-N-180820-2292") -> P-1-N-180820-2292 | E4: =IFERROR(__xludf.DUMMYFUNCTION("""COMPUTED_VALUE"""),"REJECTED") -> REJECTED | F4: =IFERROR(__xludf.DUMMYFUNCTION("""COMPUTED_VALUE"""),"Butcher's Natural & Healthy Dog with Lamb and Rice Pate 390g") -> Butcher's Natural & Healthy Dog with Lamb and Rice Pate 390g | G4: =IFERROR(__xludf.DUMMYFUNCTION("""COMPUTED_VALUE"""),"بوتشرز طبيعي وصحي للكلاب مع لحم ضأن والرز باتي 390 جم") -> بوتشرز طبيعي وصحي للكلاب مع لحم ضأن والرز باتي 390 جم | K4: =IFERROR(__xludf.DUMMYFUNCTION("""COMPUTED_VALUE"""),"بوتشرز بت كير ال تي دي") -> بوتشرز بت كير ال تي دي | L4: =IFERROR(__xludf.DUMMYFUNCTION("""COMPUTED_VALUE"""),"B1110") -> B1110
A5: =IFERROR(__xludf.DUMMYFUNCTION("""COMPUTED_VALUE"""),4.0) -> 4 | B5: =IFERROR(__xludf.DUMMYFUNCTION("""COMPUTED_VALUE"""),"SC1571") -> SC1571 | C5: =IFERROR(__xludf.DUMMYFUNCTION("""COMPUTED_VALUE"""),"P-1-N-190820-2298") -> P-1-N-190820-2298 | E5: =IFERROR(__xludf.DUMMYFUNCTION("""COMPUTED_VALUE"""),"تمت طباعة الشهادة") -> تمت طباعة الشهادة | F5: =IFERROR(__xludf.DUMMYFUNCTION("""COMPUTED_VALUE"""),"Sanal Anti-Hairball Bites Malt 75g") -> Sanal Anti-Hairball Bites Malt 75g | G5: =IFERROR(__xludf.DUMMYFUNCTION("""COMPUTED_VALUE"""),"سانال قطع مكافحة كرة الشعر الشعير 75 جم") -> سانال قطع مكافحة كرة الشعر الشعير 75 جم | H5: =IFERROR(__xludf.DUMMYFUNCTION("""COMPUTED_VALUE"""),"MAFE2020940") -> MAFE2020940 | K5: =IFERROR(__xludf.DUMMYFUNCTION("""COMPUTED_VALUE"""),"نيدرما بي في") -> نيدرما بي في | L5: =IFERROR(__xludf.DUMMYFUNCTION("""COMPUTED_VALUE"""),"SC1571") -> SC1571
A6: =IFERROR(__xludf.DUMMYFUNCTION("""COMPUTED_VALUE"""),5.0) -> 5 | B6: =IFERROR(__xludf.DUMMYFUNCTION("""COMPUTED_VALUE"""),"SC1572") -> SC1572 | C6: =IFERROR(__xludf.DUMMYFUNCTION("""COMPUTED_VALUE"""),"P-1-N-190820-2300") -> P-1-N-190820-2300 | E6: =IFERROR(__xludf.DUMMYFUNCTION("""COMPUTED_VALUE"""),"تمت طباعة الشهادة") -> تمت طباعة الشهادة | F6: =IFERROR(__xludf.DUMMYFUNCTION("""COMPUTED_VALUE"""),"Sanal Cheese Bites 75g") -> Sanal Cheese Bites 75g | G6: =IFERROR(__xludf.DUMMYFUNCTION("""COMPUTED_VALUE"""),"سانال قطع الجبن 75 جم") -> سانال قطع الجبن 75 جم | H6: =IFERROR(__xludf.DUMMYFUNCTION("""COMPUTED_VALUE"""),"MAFE2020939") -> MAFE2020939 | K6: =IFERROR(__xludf.DUMMYFUNCTION("""COMPUTED_VALUE"""),"نيدرما بي في") -> نيدرما بي في | L6: =IFERROR(__xludf.DUMMYFUNCTION("""COMPUTED_VALUE"""),"SC1572") -> SC1572
A7: =IFERROR(__xludf.DUMMYFUNCTION("""COMPUTED_VALUE"""),6.0) -> 6 | B7: =IFERROR(__xludf.DUMMYFUNCTION("""COMPUTED_VALUE"""),"SC1573") -> SC1573 | C7: =IFERROR(__xludf.DUMMYFUNCTION("""COMPUTED_VALUE"""),"P-1-N-200820-2316") -> P-1-N-200820-2316 | E7: =IFERROR(__xludf.DUMMYFUNCTION("""COMPUTED_VALUE"""),"تمت طباعة الشهادة") -> تمت طباعة الشهادة | F7: =IFERROR(__xludf.DUMMYFUNCTION("""COMPUTED_VALUE"""),"Sanal Denta’s 75g") -> Sanal Denta’s 75g | G7: =IFERROR(__xludf.DUMMYFUNCTION("""COMPUTED_VALUE"""),"سانال دنتاس 75 جم") -> سانال دنتاس 75 جم | H7: =IFERROR(__xludf.DUMMYFUNCTION("""COMPUTED_VALUE"""),"MAFE2020963") -> MAFE2020963 | K7: =IFERROR(__xludf.DUMMYFUNCTION("""COMPUTED_VALUE"""),"نيدرما بي في") -> نيدرما بي في | L7: =IFERROR(__xludf.DUMMYFUNCTION("""COMPUTED_VALUE"""),"SC1573") -> SC1573
A8: =IFERROR(__xludf.DUMMYFUNCTION("""COMPUTED_VALUE"""),7.0) -> 7 | B8: =IFERROR(__xludf.DUMMYFUNCTION("""COMPUTED_VALUE"""),"SC1574") -> SC1574 | C8: =IFERROR(__xludf.DUMMYFUNCTION("""COMPUTED_VALUE"""),"P-1-N-200820-2318") -> P-1-N-200820-2318 | E8: =IFERROR(__xludf.DUMMYFUNCTION("""COMPUTED_VALUE"""),"تمت طباعة الشهادة") -> تمت طباعة الشهادة | F8: =IFERROR(__xludf.DUMMYFUNCTION("""COMPUTED_VALUE"""),"Sanal Fish Bites 75g") -> Sanal Fish Bites 75g | G8: =IFERROR(__xludf.DUMMYFUNCTION("""COMPUTED_VALUE"""),"سانال قطع السمك 75 جم") -> سانال قطع السمك 75 جم | H8: =IFERROR(__xludf.DUMMYFUNCTION("""COMPUTED_VALUE"""),"MAFE2020961") -> MAFE2020961 | K8: =IFERROR(__xludf.DUMMYFUNCTION("""COMPUTED_VALUE"""),"نيدرما بي في") -> نيدرما بي في | L8: =IFERROR(__xludf.DUMMYFUNCTION("""COMPUTED_VALUE"""),"SC1574") -> SC1574
A9: =IFERROR(__xludf.DUMMYFUNCTION("""COMPUTED_VALUE"""),8.0) -> 8 | B9: =IFERROR(__xludf.DUMMYFUNCTION("""COMPUTED_VALUE"""),"SC1577") -> SC1577 | C9: =IFERROR(__xludf.DUMMYFUNCTION("""COMPUTED_VALUE"""),"P-1-N-200820-2319") -> P-1-N-200820-2319 | E9: =IFERROR(__xludf.DUMMYFUNCTION("""COMPUTED_VALUE"""),"تمت طباعة الشهادة") -> تمت طباعة الشهادة | F9: =IFERROR(__xludf.DUMMYFUNCTION("""COMPUTED_VALUE"""),"Sanal Fiesta 75g") -> Sanal Fiesta 75g | G9: =IFERROR(__xludf.DUMMYFUNCTION("""COMPUTED_VALUE"""),"سانال فييستا 75 جم") -> سانال فييستا 75 جم | H9: =IFERROR(__xludf.DUMMYFUNCTION("""COMPUTED_VALUE"""),"MAFE2020960") -> MAFE2020960 | K9: =IFERROR(__xludf.DUMMYFUNCTION("""COMPUTED_VALUE"""),"نيدرما بي في") -> نيدرما بي في | L9: =IFERROR(__xludf.DUMMYFUNCTION("""COMPUTED_VALUE"""),"SC1577") -> SC1577
A10: =IFERROR(__xludf.DUMMYFUNCTION("""COMPUTED_VALUE"""),9.0) -> 9 | B10: =IFERROR(__xludf.DUMMYFUNCTION("""COMPUTED_VALUE"""),"SC1578") -> SC1578 | C10: =IFERROR(__xludf.DUMMYFUNCTION("""COMPUTED_VALUE"""),"P-1-N-200820-2321") -> P-1-N-200820-2321 | E10: =IFERROR(__xludf.DUMMYFUNCTION("""COMPUTED_VALUE"""),"تمت طباعة الشهادة") -> تمت طباعة الشهادة | F10: =IFERROR(__xludf.DUMMYFUNCTION("""COMPUTED_VALUE"""),"Sanal Cranberry & Chicken Bites 75g") -> Sanal Cranberry & Chicken Bites 75g | G10: =IFERROR(__xludf.DUMMYFUNCTION("""COMPUTED_VALUE"""),"سانال قطع التوت البري والدجاج 75 جم") -> سانال قطع التوت البري والدجاج 75 جم | H10: =IFERROR(__xludf.DUMMYFUNCTION("""COMPUTED_VALUE"""),"MAFE2020959") -> MAFE2020959 | K10: =IFERROR(__xludf.DUMMYFUNCTION("""COMPUTED_VALUE"""),"نيدرما بي في") -> نيدرما بي في | L10: =IFERROR(__xludf.DUMMYFUNCTION("""COMPUTED_VALUE"""),"SC1578") -> SC1578
A11: =IFERROR(__xludf.DUMMYFUNCTION("""COMPUTED_VALUE"""),10.0) -> 10 | B11: =IFERROR(__xludf.DUMMYFUNCTION("""COMPUTED_VALUE"""),"421171") -> 421171 | C11: =IFERROR(__xludf.DUMMYFUNCTION("""COMPUTED_VALUE"""),"P-1-N-220820-2331") -> P-1-N-220820-2331 | E11: =IFERROR(__xludf.DUMMYFUNCTION("""COMPUTED_VALUE"""),"تمت طباعة الشهادة") -> تمت طباعة الشهادة | F11: =IFERROR(__xludf.DUMMYFUNCTION("""COMPUTED_VALUE"""),"Prestige Premium Canary 800 G") -> Prestige Premium Canary 800 G | G11: =IFERROR(__xludf.DUMMYFUNCTION("""COMPUTED_VALUE"""),"برستيج بريميوم كناري 800 جرام") -> برستيج بريميوم كناري 800 جرام | H11: =IFERROR(__xludf.DUMMYFUNCTION("""COMPUTED_VALUE"""),"MAFE2020969") -> MAFE2020969 | K11: =IFERROR(__xludf.DUMMYFUNCTION("""COMPUTED_VALUE"""),"فيرسل لاقا ان في") -> فيرسل لاقا ان في | L11: =IFERROR(__xludf.DUMMYFUNCTION("""COMPUTED_VALUE"""),"421171") -> 421171
A12: =IFERROR(__xludf.DUMMYFUNCTION("""COMPUTED_VALUE"""),11.0) -> 11 | B12: =IFERROR(__xludf.DUMMYFUNCTION("""COMPUTED_VALUE"""),"421172") -> 421172 | C12: =IFERROR(__xludf.DUMMYFUNCTION("""COMPUTED_VALUE"""),"P-1-N-220820-2332") -> P-1-N-220820-2332 | E12: =IFERROR(__xludf.DUMMYFUNCTION("""COMPUTED_VALUE"""),"تمت طباعة الشهادة") -> تمت طباعة الشهادة | F12: =IFERROR(__xludf.DUMMYFUNCTION("""COMPUTED_VALUE"""),"Prestige Premium Canary 2.50 KG") -> Prestige Premium Canary 2.50 KG | G12: =IFERROR(__xludf.DUMMYFUNCTION("""COMPUTED_VALUE"""),"برستيج بريميوم كناري 2.50 كيلو") -> برستيج بريميوم كناري 2.50 كيلو | H12: =IFERROR(__xludf.DUMMYFUNCTION("""COMPUTED_VALUE"""),"MAFE2020974") -> MAFE2020974 | K12: =IFERROR(__xludf.DUMMYFUNCTION("""COMPUTED_VALUE"""),"فيرسل لاقا ان في") -> فيرسل لاقا ان في | L12: =IFERROR(__xludf.DUMMYFUNCTION("""COMPUTED_VALUE"""),"421172") -> 421172
A13: =IFERROR(__xludf.DUMMYFUNCTION("""COMPUTED_VALUE"""),12.0) -> 12 | B13: =IFERROR(__xludf.DUMMYFUNCTION("""COMPUTED_VALUE"""),"421699") -> 421699 | C13: =IFERROR(__xludf.DUMMYFUNCTION("""COMPUTED_VALUE"""),"P-1-N-220820-2333") -> P-1-N-220820-2333 | E13: =IFERROR(__xludf.DUMMYFUNCTION("""COMPUTED_VALUE"""),"تمت طباعة الشهادة") -> تمت طباعة الشهادة | F13: =IFERROR(__xludf.DUMMYFUNCTION("""COMPUTED_VALUE"""),"Prestige Premium Budgie 800g") -> Prestige Premium Budgie 800g | G13: =IFERROR(__xludf.DUMMYFUNCTION("""COMPUTED_VALUE"""),"برستيج بريميوم ببغاء صغير 800 جرام") -> برستيج بريميوم ببغاء صغير 800 جرام | H13: =IFERROR(__xludf.DUMMYFUNCTION("""COMPUTED_VALUE"""),"MAFE2020996") -> MAFE2020996 | K13: =IFERROR(__xludf.DUMMYFUNCTION("""COMPUTED_VALUE"""),"فيرسل لاقا ان في") -> فيرسل لاقا ان في | L13: =IFERROR(__xludf.DUMMYFUNCTION("""COMPUTED_VALUE"""),"421699") -> 421699
A14: =IFERROR(__xludf.DUMMYFUNCTION("""COMPUTED_VALUE"""),13.0) -> 13 | B14: =IFERROR(__xludf.DUMMYFUNCTION("""COMPUTED_VALUE"""),"421700") -> 421700 | C14: =IFERROR(__xludf.DUMMYFUNCTION("""COMPUTED_VALUE"""),"P-1-N-220820-2334") -> P-1-N-220820-2334 | E14: =IFERROR(__xludf.DUMMYFUNCTION("""COMPUTED_VALUE"""),"تمت طباعة الشهادة") -> تمت طباعة الشهادة | F14: =IFERROR(__xludf.DUMMYFUNCTION("""COMPUTED_VALUE"""),"Prestige Premium Budgie 2.50 KG") -> Prestige Premium Budgie 2.50 KG | G14: =IFERROR(__xludf.DUMMYFUNCTION("""COMPUTED_VALUE"""),"برستيج بريميوم ببغاء صغير 2.50 كيلو") -> برستيج بريميوم ببغاء صغير 2.50 كيلو | H14: =IFERROR(__xludf.DUMMYFUNCTION("""COMPUTED_VALUE"""),"MAFE2020973") -> MAFE2020973 | K14: =IFERROR(__xludf.DUMMYFUNCTION("""COMPUTED_VALUE"""),"فيرسل لاقا ان في") -> فيرسل لاقا ان في | L14: =IFERROR(__xludf.DUMMYFUNCTION("""COMPUTED_VALUE"""),"421700") -> 421700
A15: =IFERROR(__xludf.DUMMYFUNCTION("""COMPUTED_VALUE"""),14.0) -> 14 | B15: =IFERROR(__xludf.DUMMYFUNCTION("""COMPUTED_VALUE"""),"421512") -> 421512 | C15: =IFERROR(__xludf.DUMMYFUNCTION("""COMPUTED_VALUE"""),"P-1-N-220820-2335") -> P-1-N-220820-2335 | E15: =IFERROR(__xludf.DUMMYFUNCTION("""COMPUTED_VALUE"""),"تمت طباعة الشهادة") -> تمت طباعة الشهادة | F15: =IFERROR(__xludf.DUMMYFUNCTION("""COMPUTED_VALUE"""),"Prestige Premium Tropical Finches 800g") -> Prestige Premium Tropical Finches 800g | G15: =IFERROR(__xludf.DUMMYFUNCTION("""COMPUTED_VALUE"""),"برستيج بريميوم عصافير استوائية 800 جرام") -> برستيج بريميوم عصافير استوائية 800 جرام | H15: =IFERROR(__xludf.DUMMYFUNCTION("""COMPUTED_VALUE"""),"MAFE2020972") -> MAFE2020972 | K15: =IFERROR(__xludf.DUMMYFUNCTION("""COMPUTED_VALUE"""),"فيرسل لاقا ان في") -> فيرسل لاقا ان في | L15: =IFERROR(__xludf.DUMMYFUNCTION("""COMPUTED_VALUE"""),"421512") -> 421512
A16: =IFERROR(__xludf.DUMMYFUNCTION("""COMPUTED_VALUE"""),15.0) -> 15 | B16: =IFERROR(__xludf.DUMMYFUNCTION("""COMPUTED_VALUE"""),"421913") -> 421913 | C16: =IFERROR(__xludf.DUMMYFUNCTION("""COMPUTED_VALUE"""),"P-1-N-220820-2336") -> P-1-N-220820-2336 | E16: =IFERROR(__xludf.DUMMYFUNCTION("""COMPUTED_VALUE"""),"تمت طباعة الشهادة") -> تمت طباعة الشهادة | F16: =IFERROR(__xludf.DUMMYFUNCTION("""COMPUTED_VALUE"""),"Prestige Premium Parrots 2 KG") -> Prestige Premium Parrots 2 KG | G16: =IFERROR(__xludf.DUMMYFUNCTION("""COMPUTED_VALUE"""),"برستيج بريميوم ببغاء 2 كيلو") -> برستيج بريميوم ببغاء 2 كيلو | H16: =IFERROR(__xludf.DUMMYFUNCTION("""COMPUTED_VALUE"""),"MAFE2020990") -> MAFE2020990 | K16: =IFERROR(__xludf.DUMMYFUNCTION("""COMPUTED_VALUE"""),"فيرسل لاقا ان في") -> فيرسل لاقا ان في | L16: =IFERROR(__xludf.DUMMYFUNCTION("""COMPUTED_VALUE"""),"421913") -> 421913
A17: =IFERROR(__xludf.DUMMYFUNCTION("""COMPUTED_VALUE"""),16.0) -> 16 | B17: =IFERROR(__xludf.DUMMYFUNCTION("""COMPUTED_VALUE"""),"SC3830") -> SC3830 | C17: =IFERROR(__xludf.DUMMYFUNCTION("""COMPUTED_VALUE"""),"P-1-N-230820-2342") -> P-1-N-230820-2342 | E17: =IFERROR(__xludf.DUMMYFUNCTION("""COMPUTED_VALUE"""),"تمت طباعة الشهادة") -> تمت طباعة الشهادة | F17: =IFERROR(__xludf.DUMMYFUNCTION("""COMPUTED_VALUE"""),"Sanal Soft Sticks Salmon & Trout 15g") -> Sanal Soft Sticks Salmon & Trout 15g | G17: =IFERROR(__xludf.DUMMYFUNCTION("""COMPUTED_VALUE"""),"سانال فيتا بونز 100 جم") -> سانال فيتا بونز 100 جم | H17: =IFERROR(__xludf.DUMMYFUNCTION("""COMPUTED_VALUE"""),"MAFE2020958") -> MAFE2020958 | K17: =IFERROR(__xludf.DUMMYFUNCTION("""COMPUTED_VALUE"""),"نيدرما بي في") -> نيدرما بي في | L17: =IFERROR(__xludf.DUMMYFUNCTION("""COMPUTED_VALUE"""),"SD2972") -> SD2972
A18: =IFERROR(__xludf.DUMMYFUNCTION("""COMPUTED_VALUE"""),17.0) -> 17 | B18: =IFERROR(__xludf.DUMMYFUNCTION("""COMPUTED_VALUE"""),"SC3830") -> SC3830 | C18: =IFERROR(__xludf.DUMMYFUNCTION("""COMPUTED_VALUE"""),"P-1-N-230820-2347") -> P-1-N-230820-2347 | E18: =IFERROR(__xludf.DUMMYFUNCTION("""COMPUTED_VALUE"""),"تمت طباعة الشهادة") -> تمت طباعة الشهادة | G18: =IFERROR(__xludf.DUMMYFUNCTION("""COMPUTED_VALUE"""),"سانال عصا طرية بسمك السالمون و التراوت 15 جم") -> سانال عصا طرية بسمك السالمون و التراوت 15 جم | H18: =IFERROR(__xludf.DUMMYFUNCTION("""COMPUTED_VALUE"""),"MAFE2020971") -> MAFE2020971 | K18: =IFERROR(__xludf.DUMMYFUNCTION("""COMPUTED_VALUE"""),"نيدرما بي في") -> نيدرما بي في | L18: =IFERROR(__xludf.DUMMYFUNCTION("""COMPUTED_VALUE"""),"SC3830") -> SC3830
A19: =IFERROR(__xludf.DUMMYFUNCTION("""COMPUTED_VALUE"""),18.0) -> 18 | B19: =IFERROR(__xludf.DUMMYFUNCTION("""COMPUTED_VALUE"""),"SC3840") -> SC3840 | C19: =IFERROR(__xludf.DUMMYFUNCTION("""COMPUTED_VALUE"""),"P-1-N-230820-2348") -> P-1-N-230820-2348 | E19: =IFERROR(__xludf.DUMMYFUNCTION("""COMPUTED_VALUE"""),"تمت طباعة الشهادة") -> تمت طباعة الشهادة | F19: =IFERROR(__xludf.DUMMYFUNCTION("""COMPUTED_VALUE"""),"Sanal Soft Sticks Turkey & Liver 15g") -> Sanal Soft Sticks Turkey & Liver 15g | G19: =IFERROR(__xludf.DUMMYFUNCTION("""COMPUTED_VALUE"""),"سانال عصا طرية بالديك الرومي والكبد 15 جم") -> سانال عصا طرية بالديك الرومي والكبد 15 جم | H19: =IFERROR(__xludf.DUMMYFUNCTION("""COMPUTED_VALUE"""),"MAFE2020970") -> MAFE2020970 | K19: =IFERROR(__xludf.DUMMYFUNCTION("""COMPUTED_VALUE"""),"نيدرما بي في") -> نيدرما بي في | L19: =IFERROR(__xludf.DUMMYFUNCTION("""COMPUTED_VALUE"""),"SC3840") -> SC3840
A20: =IFERROR(__xludf.DUMMYFUNCTION("""COMPUTED_VALUE"""),19.0) -> 19 | B20: =IFERROR(__xludf.DUMMYFUNCTION("""COMPUTED_VALUE"""),"SC3850") -> SC3850 | C20: =IFERROR(__xludf.DUMMYFUNCTION("""COMPUTED_VALUE"""),"P-1-N-230820-2350") -> P-1-N-230820-2350 | E20: =IFERROR(__xludf.DUMMYFUNCTION("""COMPUTED_VALUE"""),"تمت طباعة الشهادة") -> تمت طباعة الشهادة | F20: =IFERROR(__xludf.DUMMYFUNCTION("""COMPUTED_VALUE"""),"Sanal Soft Sticks Lamb & Rice 15g") -> Sanal Soft Sticks Lamb & Rice 15g | G20: =IFERROR(__xludf.DUMMYFUNCTION("""COMPUTED_VALUE"""),"سانال عصا طرية بلحم الضأن والأرز 15 جم") -> سانال عصا طرية بلحم الضأن والأرز 15 جم | H20: =IFERROR(__xludf.DUMMYFUNCTION("""COMPUTED_VALUE"""),"MAFE2020968") -> MAFE2020968 | K20: =IFERROR(__xludf.DUMMYFUNCTION("""COMPUTED_VALUE"""),"نيدرما بي في") -> نيدرما بي في | L20: =IFERROR(__xludf.DUMMYFUNCTION("""COMPUTED_VALUE"""),"SC3850") -> SC3850
A21: =IFERROR(__xludf.DUMMYFUNCTION("""COMPUTED_VALUE"""),20.0) -> 20 | B21: =IFERROR(__xludf.DUMMYFUNCTION("""COMPUTED_VALUE"""),"SD2900") -> SD2900 | C21: =IFERROR(__xludf.DUMMYFUNCTION("""COMPUTED_VALUE"""),"P-1-N-230820-2354") -> P-1-N-230820-2354 | E21: =IFERROR(__xludf.DUMMYFUNCTION("""COMPUTED_VALUE"""),"تمت طباعة الشهادة") -> تمت طباعة الشهادة | F21: =IFERROR(__xludf.DUMMYFUNCTION("""COMPUTED_VALUE"""),"Sanal Soft Stick Beef 12g") -> Sanal Soft Stick Beef 12g | G21: =IFERROR(__xludf.DUMMYFUNCTION("""COMPUTED_VALUE"""),"سانال عصا طرية باللحم البقري 12 جم") -> سانال عصا طرية باللحم البقري 12 جم | H21: =IFERROR(__xludf.DUMMYFUNCTION("""COMPUTED_VALUE"""),"MAFE2020967") -> MAFE2020967 | K21: =IFERROR(__xludf.DUMMYFUNCTION("""COMPUTED_VALUE"""),"نيدرما بي في") -> نيدرما بي في | L21: =IFERROR(__xludf.DUMMYFUNCTION("""COMPUTED_VALUE"""),"SD2900") -> SD2900
A22: =IFERROR(__xludf.DUMMYFUNCTION("""COMPUTED_VALUE"""),21.0) -> 21 | B22: =IFERROR(__xludf.DUMMYFUNCTION("""COMPUTED_VALUE"""),"SD2920") -> SD2920 | C22: =IFERROR(__xludf.DUMMYFUNCTION("""COMPUTED_VALUE"""),"P-1-N-230820-2356") -> P-1-N-230820-2356 | E22: =IFERROR(__xludf.DUMMYFUNCTION("""COMPUTED_VALUE"""),"تمت طباعة الشهادة") -> تمت طباعة الشهادة | F22: =IFERROR(__xludf.DUMMYFUNCTION("""COMPUTED_VALUE"""),"Sanal Soft Stick Poultry 12g") -> Sanal Soft Stick Poultry 12g | G22: =IFERROR(__xludf.DUMMYFUNCTION("""COMPUTED_VALUE"""),"سانال عصا طرية بالدواجن 12 جم") -> سانال عصا طرية بالدواجن 12 جم | H22: =IFERROR(__xludf.DUMMYFUNCTION("""COMPUTED_VALUE"""),"MAFE2020989") -> MAFE2020989 | K22: =IFERROR(__xludf.DUMMYFUNCTION("""COMPUTED_VALUE"""),"نيدرما بي في") -> نيدرما بي في | L22: =IFERROR(__xludf.DUMMYFUNCTION("""COMPUTED_VALUE"""),"SD2920") -> SD2920
A23: =IFERROR(__xludf.DUMMYFUNCTION("""COMPUTED_VALUE"""),22.0) -> 22 | C23: =IFERROR(__xludf.DUMMYFUNCTION("""COMPUTED_VALUE"""),"P-1-N-240820-2390") -> P-1-N-240820-2390 | E23: =IFERROR(__xludf.DUMMYFUNCTION("""COMPUTED_VALUE"""),"REJECTED") -> REJECTED | F23: =IFERROR(__xludf.DUMMYFUNCTION("""COMPUTED_VALUE"""),"Prestige Loro Parque African Parrot 1 KG") -> Prestige Loro Parque African Parrot 1 KG | G23: =IFERROR(__xludf.DUMMYFUNCTION("""COMPUTED_VALUE"""),"برستيج لورو بارك ببغاء افريقي 1 كيلو") -> برستيج لورو بارك ببغاء افريقي 1 كيلو | K23: =IFERROR(__xludf.DUMMYFUNCTION("""COMPUTED_VALUE"""),"فيرسل لاقا ان في") -> فيرسل لاقا ان في
A24: =IFERROR(__xludf.DUMMYFUNCTION("""COMPUTED_VALUE"""),23.0) -> 23 | C24: =IFERROR(__xludf.DUMMYFUNCTION("""COMPUTED_VALUE"""),"P-1-N-240820-2391") -> P-1-N-240820-2391 | E24: =IFERROR(__xludf.DUMMYFUNCTION("""COMPUTED_VALUE"""),"REJECTED") -> REJECTED | F24: =IFERROR(__xludf.DUMMYFUNCTION("""COMPUTED_VALUE"""),"Prestige Loro Parque African Parrot 2.50 KG") -> Prestige Loro Parque African Parrot 2.50 KG | G24: =IFERROR(__xludf.DUMMYFUNCTION("""COMPUTED_VALUE"""),"برستيج لورو بارك ببغاء افريقي 2.50 كيلو") -> برستيج لورو بارك ببغاء افريقي 2.50 كيلو | K24: =IFERROR(__xludf.DUMMYFUNCTION("""COMPUTED_VALUE"""),"فيرسل لاقا ان في") -> فيرسل لاقا ان في
A25: =IFERROR(__xludf.DUMMYFUNCTION("""COMPUTED_VALUE"""),24.0) -> 24 | B25: =IFERROR(__xludf.DUMMYFUNCTION("""COMPUTED_VALUE"""),"422208") -> 422208 | C25: =IFERROR(__xludf.DUMMYFUNCTION("""COMPUTED_VALUE"""),"P-1-N-240820-2392") -> P-1-N-240820-2392 | E25: =IFERROR(__xludf.DUMMYFUNCTION("""COMPUTED_VALUE"""),"REJECTED") -> REJECTED | F25: =IFERROR(__xludf.DUMMYFUNCTION("""COMPUTED_VALUE"""),"Prestige Loro Parque Amazone Parrot 1 KG") -> Prestige Loro Parque Amazone Parrot 1 KG | G25: =IFERROR(__xludf.DUMMYFUNCTION("""COMPUTED_VALUE"""),"برستيج لورو بارك ببغاء امازوني 1 كيلو") -> برستيج لورو بارك ببغاء امازوني 1 كيلو | K25: =IFERROR(__xludf.DUMMYFUNCTION("""COMPUTED_VALUE"""),"فيرسل لاقا ان في") -> فيرسل لاقا ان في | L25: =IFERROR(__xludf.DUMMYFUNCTION("""COMPUTED_VALUE"""),"422208") -> 422208
A26: =IFERROR(__xludf.DUMMYFUNCTION("""COMPUTED_VALUE"""),25.0) -> 25 | B26: =IFERROR(__xludf.DUMMYFUNCTION("""COMPUTED_VALUE"""),"422211") -> 422211 | C26: =IFERROR(__xludf.DUMMYFUNCTION("""COMPUTED_VALUE"""),"P-1-N-240820-2393") -> P-1-N-240820-2393 | E26: =IFERROR(__xludf.DUMMYFUNCTION("""COMPUTED_VALUE"""),"تمت طباعة الشهادة") -> تمت طباعة الشهادة | F26: =IFERROR(__xludf.DUMMYFUNCTION("""COMPUTED_VALUE"""),"Prestige Loro Parque Amazone Parrot 15 KG") -> Prestige Loro Parque Amazone Parrot 15 KG | G26: =IFERROR(__xludf.DUMMYFUNCTION("""COMPUTED_VALUE"""),"برستيج لورو بارك ببغاء امازوني 15 كيلو") -> برستيج لورو بارك ببغاء امازوني 15 كيلو | H26: =IFERROR(__xludf.DUMMYFUNCTION("""COMPUTED_VALUE"""),"MAFE20201203") -> MAFE20201203 | K26: =IFERROR(__xludf.DUMMYFUNCTION("""COMPUTED_VALUE"""),"فيرسل لاقا ان في") -> فيرسل لاقا ان في | L26: =IFERROR(__xludf.DUMMYFUNCTION("""COMPUTED_VALUE"""),"422211") -> 422211
A27: =IFERROR(__xludf.DUMMYFUNCTION("""COMPUTED_VALUE"""),26.0) -> 26 | B27: =IFERROR(__xludf.DUMMYFUNCTION("""COMPUTED_VALUE"""),"422212") -> 422212 | C27: =IFERROR(__xludf.DUMMYFUNCTION("""COMPUTED_VALUE"""),"P-1-N-240820-2394") -> P-1-N-240820-2394 | E27: =IFERROR(__xludf.DUMMYFUNCTION("""COMPUTED_VALUE"""),"REJECTED") -> REJECTED | F27: =IFERROR(__xludf.DUMMYFUNCTION("""COMPUTED_VALUE"""),"Prestige Loro Parque Australian Parrot 1 KG") -> Prestige Loro Parque Australian Parrot 1 KG | G27: =IFERROR(__xludf.DUMMYFUNCTION("""COMPUTED_VALUE"""),"برستيج لورو بارك ببغاء استرالي 1 كيلو") -> برستيج لورو بارك ببغاء استرالي 1 كيلو | K27: =IFERROR(__xludf.DUMMYFUNCTION("""COMPUTED_VALUE"""),"فيرسل لاقا ان في") -> فيرسل لاقا ان في | L27: =IFERROR(__xludf.DUMMYFUNCTION("""COMPUTED_VALUE"""),"422212") -> 422212
A28: =IFERROR(__xludf.DUMMYFUNCTION("""COMPUTED_VALUE"""),27.0) -> 27 | C28: =IFERROR(__xludf.DUMMYFUNCTION("""COMPUTED_VALUE"""),"P-1-N-250820-2416") -> P-1-N-250820-2416 | E28: =IFERROR(__xludf.DUMMYFUNCTION("""COMPUTED_VALUE"""),"REJECTED") -> REJECTED | F28: =IFERROR(__xludf.DUMMYFUNCTION("""COMPUTED_VALUE"""),"Butcher's Natural & Healthy with Trout Chunks in Jelly ") -> Butcher's Natural & Healthy with Trout Chunks in Jelly | G28: =IFERROR(__xludf.DUMMYFUNCTION("""COMPUTED_VALUE"""),"بوتشرز طبيعي وصحي مع التراوت في الجلي 400 جم") -> بوتشرز طبيعي وصحي مع التراوت في الجلي 400 جم | K28: =IFERROR(__xludf.DUMMYFUNCTION("""COMPUTED_VALUE"""),"بوتشرز بت كير ال تي دي") -> بوتشرز بت كير ال تي دي
A29: =IFERROR(__xludf.DUMMYFUNCTION("""COMPUTED_VALUE"""),28.0) -> 28 | C29: =IFERROR(__xludf.DUMMYFUNCTION("""COMPUTED_VALUE"""),"P-1-N-250820-2420") -> P-1-N-250820-2420 | E29: =IFERROR(__xludf.DUMMYFUNCTION("""COMPUTED_VALUE"""),"REJECTED") -> REJECTED | F29: =IFERROR(__xludf.DUMMYFUNCTION("""COMPUTED_VALUE"""),"Butcher's Natural & Healthy with Game Chunks in Jelly ") -> Butcher's Natural & Healthy with Game Chunks in Jelly | G29: =IFERROR(__xludf.DUMMYFUNCTION("""COMPUTED_VALUE"""),"بوتشرز طبيعي وصحي مع قطع لحوم الطرائد في الجلي 400 جم") -> بوتشرز طبيعي وصحي مع قطع لحوم الطرائد في الجلي 400 جم | K29: =IFERROR(__xludf.DUMMYFUNCTION("""COMPUTED_VALUE"""),"بوتشرز بت كير ال تي دي") -> بوتشرز بت كير ال تي دي
A30: =IFERROR(__xludf.DUMMYFUNCTION("""COMPUTED_VALUE"""),29.0) -> 29 | B30: =IFERROR(__xludf.DUMMYFUNCTION("""COMPUTED_VALUE"""),"B1135") -> B1135 | C30: =IFERROR(__xludf.DUMMYFUNCTION("""COMPUTED_VALUE"""),"P-1-N-250820-2421") -> P-1-N-250820-2421 | E30: =IFERROR(__xludf.DUMMYFUNCTION("""COMPUTED_VALUE"""),"REJECTED") -> REJECTED | F30: =IFERROR(__xludf.DUMMYFUNCTION("""COMPUTED_VALUE"""),"Butcher's Natural & Healthy with Ocean Fish Chunks in Jelly ") -> Butcher's Natural & Healthy with Ocean Fish Chunks in Jelly | G30: =IFERROR(__xludf.DUMMYFUNCTION("""COMPUTED_VALUE"""),"بوتشرز طبيعي وصحي مع قطع أسماك المحيط في الجلي 400 جم") -> بوتشرز طبيعي وصحي مع قطع أسماك المحيط في الجلي 400 جم | K30: =IFERROR(__xludf.DUMMYFUNCTION("""COMPUTED_VALUE"""),"بوتشرز بت كير ال تي دي") -> بوتشرز بت كير ال تي دي | L30: =IFERROR(__xludf.DUMMYFUNCTION("""COMPUTED_VALUE"""),"B1135") -> B1135
A31: =IFERROR(__xludf.DUMMYFUNCTION("""COMPUTED_VALUE"""),30.0) -> 30 | C31: =IFERROR(__xludf.DUMMYFUNCTION("""COMPUTED_VALUE"""),"P-1-N-250820-2422") -> P-1-N-250820-2422 | E31: =IFERROR(__xludf.DUMMYFUNCTION("""COMPUTED_VALUE"""),"REJECTED") -> REJECTED | F31: =IFERROR(__xludf.DUMMYFUNCTION("""COMPUTED_VALUE"""),"Butcher's Natural & Healthy with Chicken Chunks in Jelly ") -> Butcher's Natural & Healthy with Chicken Chunks in Jelly | G31: =IFERROR(__xludf.DUMMYFUNCTION("""COMPUTED_VALUE"""),"بوتشرز طبيعي وصحي مع قطع دجاج في الجلي 400 جم") -> بوتشرز طبيعي وصحي مع قطع دجاج في الجلي 400 جم | K31: =IFERROR(__xludf.DUMMYFUNCTION("""COMPUTED_VALUE"""),"بوتشرز بت كير ال تي دي") -> بوتشرز بت كير ال تي دي
A32: =IFERROR(__xludf.DUMMYFUNCTION("""COMPUTED_VALUE"""),31.0) -> 31 | C32: =IFERROR(__xludf.DUMMYFUNCTION("""COMPUTED_VALUE"""),"P-1-N-250820-2423") -> P-1-N-250820-2423 | E32: =IFERROR(__xludf.DUMMYFUNCTION("""COMPUTED_VALUE"""),"REJECTED") -> REJECTED | F32: =IFERROR(__xludf.DUMMYFUNCTION("""COMPUTED_VALUE"""),"Butcher's Natural & Healthy with Beef Chunks in Jelly ") -> Butcher's Natural & Healthy with Beef Chunks in Jelly | G32: =IFERROR(__xludf.DUMMYFUNCTION("""COMPUTED_VALUE"""),"بوتشرز طبيعي وصحي مع قطع اللحم البقري في الجلي 400 جم") -> بوتشرز طبيعي وصحي مع قطع اللحم البقري في الجلي 400 جم | K32: =IFERROR(__xludf.DUMMYFUNCTION("""COMPUTED_VALUE"""),"بوتشرز بت كير ال تي دي") -> بوتشرز بت كير ال تي دي
A33: =IFERROR(__xludf.DUMMYFUNCTION("""COMPUTED_VALUE"""),32.0) -> 32 | B33: =IFERROR(__xludf.DUMMYFUNCTION("""COMPUTED_VALUE"""),"MC1216") -> MC1216 | C33: =IFERROR(__xludf.DUMMYFUNCTION("""COMPUTED_VALUE"""),"P-1-N-250820-2430") -> P-1-N-250820-2430 | E33: =IFERROR(__xludf.DUMMYFUNCTION("""COMPUTED_VALUE"""),"تمت طباعة الشهادة") -> تمت طباعة الشهادة | F33: =IFERROR(__xludf.DUMMYFUNCTION("""COMPUTED_VALUE"""),"Healthy Treats Skin & Coat For Dogs and Puppies 70g") -> Healthy Treats Skin & Coat For Dogs and Puppies 70g | G33: =IFERROR(__xludf.DUMMYFUNCTION("""COMPUTED_VALUE"""),"هيلثي تريتس للجلد والفرو للكلاب والجراء 70 جم") -> هيلثي تريتس للجلد والفرو للكلاب والجراء 70 جم | H33: =IFERROR(__xludf.DUMMYFUNCTION("""COMPUTED_VALUE"""),"MAFE20201062") -> MAFE20201062 | K33: =IFERROR(__xludf.DUMMYFUNCTION("""COMPUTED_VALUE"""),"مارك اند شابل ليمتد") -> مارك اند شابل ليمتد | L33: =IFERROR(__xludf.DUMMYFUNCTION("""COMPUTED_VALUE"""),"MC1216") -> MC1216
A34: =IFERROR(__xludf.DUMMYFUNCTION("""COMPUTED_VALUE"""),33.0) -> 33 | B34: =IFERROR(__xludf.DUMMYFUNCTION("""COMPUTED_VALUE"""),"MC2473") -> MC2473 | C34: =IFERROR(__xludf.DUMMYFUNCTION("""COMPUTED_VALUE"""),"P-1-N-260820-2435") -> P-1-N-260820-2435 | E34: =IFERROR(__xludf.DUMMYFUNCTION("""COMPUTED_VALUE"""),"تمت طباعة الشهادة") -> تمت طباعة الشهادة | F34: =IFERROR(__xludf.DUMMYFUNCTION("""COMPUTED_VALUE"""),"Healthy Treats Breath & Dental 70g") -> Healthy Treats Breath & Dental 70g | G34: =IFERROR(__xludf.DUMMYFUNCTION("""COMPUTED_VALUE"""),"وجبة ممتعة صحية لرائحة الفم والأسنان 70 جم") -> وجبة ممتعة صحية لرائحة الفم والأسنان 70 جم | H34: =IFERROR(__xludf.DUMMYFUNCTION("""COMPUTED_VALUE"""),"MAFE20201061") -> MAFE20201061 | K34: =IFERROR(__xludf.DUMMYFUNCTION("""COMPUTED_VALUE"""),"مارك اند شابل ليمتد") -> مارك اند شابل ليمتد | L34: =IFERROR(__xludf.DUMMYFUNCTION("""COMPUTED_VALUE"""),"MC2473") -> MC2473
A35: =IFERROR(__xludf.DUMMYFUNCTION("""COMPUTED_VALUE"""),34.0) -> 34 | B35: =IFERROR(__xludf.DUMMYFUNCTION("""COMPUTED_VALUE"""),"MC3357") -> MC3357 | C35: =IFERROR(__xludf.DUMMYFUNCTION("""COMPUTED_VALUE"""),"P-1-N-260820-2438") -> P-1-N-260820-2438 | E35: =IFERROR(__xludf.DUMMYFUNCTION("""COMPUTED_VALUE"""),"تمت طباعة الشهادة") -> تمت طباعة الشهادة | F35: =IFERROR(__xludf.DUMMYFUNCTION("""COMPUTED_VALUE"""),"Healthy Treats Nutri-Booster 50g") -> Healthy Treats Nutri-Booster 50g | G35: =IFERROR(__xludf.DUMMYFUNCTION("""COMPUTED_VALUE"""),"وجبة ممتعة صحية نيوتري بوستر 50 جم") -> وجبة ممتعة صحية نيوتري بوستر 50 جم | H35: =IFERROR(__xludf.DUMMYFUNCTION("""COMPUTED_VALUE"""),"MAFE20201002") -> MAFE20201002 | K35: =IFERROR(__xludf.DUMMYFUNCTION("""COMPUTED_VALUE"""),"مارك اند شابل ليمتد") -> مارك اند شابل ليمتد | L35: =IFERROR(__xludf.DUMMYFUNCTION("""COMPUTED_VALUE"""),"MC3357") -> MC3357
A36: =IFERROR(__xludf.DUMMYFUNCTION("""COMPUTED_VALUE"""),35.0) -> 35 | B36: =IFERROR(__xludf.DUMMYFUNCTION("""COMPUTED_VALUE"""),"MC3456") -> MC3456 | C36: =IFERROR(__xludf.DUMMYFUNCTION("""COMPUTED_VALUE"""),"P-1-N-260820-2440") -> P-1-N-260820-2440 | E36: =IFERROR(__xludf.DUMMYFUNCTION("""COMPUTED_VALUE"""),"تمت طباعة الشهادة") -> تمت طباعة الشهادة | F36: =IFERROR(__xludf.DUMMYFUNCTION("""COMPUTED_VALUE"""),"Healthy Treats Teething 50g") -> Healthy Treats Teething 50g | G36: =IFERROR(__xludf.DUMMYFUNCTION("""COMPUTED_VALUE"""),"هيلثي تريتس للتسنين 50 جم") -> هيلثي تريتس للتسنين 50 جم | H36: =IFERROR(__xludf.DUMMYFUNCTION("""COMPUTED_VALUE"""),"MAFE20201059") -> MAFE20201059 | K36: =IFERROR(__xludf.DUMMYFUNCTION("""COMPUTED_VALUE"""),"مارك اند شابل ليمتد") -> مارك اند شابل ليمتد | L36: =IFERROR(__xludf.DUMMYFUNCTION("""COMPUTED_VALUE"""),"MC3456") -> MC3456
A37: =IFERROR(__xludf.DUMMYFUNCTION("""COMPUTED_VALUE"""),36.0) -> 36 | B37: =IFERROR(__xludf.DUMMYFUNCTION("""COMPUTED_VALUE"""),"HS30236") -> HS30236 | C37: =IFERROR(__xludf.DUMMYFUNCTION("""COMPUTED_VALUE"""),"P-1-N-260820-2441") -> P-1-N-260820-2441 | E37: =IFERROR(__xludf.DUMMYFUNCTION("""COMPUTED_VALUE"""),"تمت طباعة الشهادة") -> تمت طباعة الشهادة | F37: =IFERROR(__xludf.DUMMYFUNCTION("""COMPUTED_VALUE"""),"Sunburst Macaw 1.36 KG") -> Sunburst Macaw 1.36 KG | G37: =IFERROR(__xludf.DUMMYFUNCTION("""COMPUTED_VALUE"""),"صن بيرست مكاو 1.36 كيلو") -> صن بيرست مكاو 1.36 كيلو | H37: =IFERROR(__xludf.DUMMYFUNCTION("""COMPUTED_VALUE"""),"MAFE20201001") -> MAFE20201001 | K37: =IFERROR(__xludf.DUMMYFUNCTION("""COMPUTED_VALUE"""),"مؤسسة مجموعة ذا هيغينز") -> مؤسسة مجموعة ذا هيغينز | L37: =IFERROR(__xludf.DUMMYFUNCTION("""COMPUTED_VALUE"""),"HS30236") -> HS30236
A38: =IFERROR(__xludf.DUMMYFUNCTION("""COMPUTED_VALUE"""),37.0) -> 37 | B38: =IFERROR(__xludf.DUMMYFUNCTION("""COMPUTED_VALUE"""),"MC5894") -> MC5894 | C38: =IFERROR(__xludf.DUMMYFUNCTION("""COMPUTED_VALUE"""),"P-1-N-270820-2458") -> P-1-N-270820-2458 | E38: =IFERROR(__xludf.DUMMYFUNCTION("""COMPUTED_VALUE"""),"تمت طباعة الشهادة") -> تمت طباعة الشهادة | F38: =IFERROR(__xludf.DUMMYFUNCTION("""COMPUTED_VALUE"""),"Healthy Treats Calming For Puppies 50g") -> Healthy Treats Calming For Puppies 50g | G38: =IFERROR(__xludf.DUMMYFUNCTION("""COMPUTED_VALUE"""),"هيلثي تريتس مهدئ للجراء 50 جم") -> هيلثي تريتس مهدئ للجراء 50 جم | H38: =IFERROR(__xludf.DUMMYFUNCTION("""COMPUTED_VALUE"""),"MAFE20201058") -> MAFE20201058 | K38: =IFERROR(__xludf.DUMMYFUNCTION("""COMPUTED_VALUE"""),"مارك اند شابل ليمتد") -> مارك اند شابل ليمتد | L38: =IFERROR(__xludf.DUMMYFUNCTION("""COMPUTED_VALUE"""),"MC5894") -> MC5894
A39: =IFERROR(__xludf.DUMMYFUNCTION("""COMPUTED_VALUE"""),38.0) -> 38 | B39: =IFERROR(__xludf.DUMMYFUNCTION("""COMPUTED_VALUE"""),"MC5887") -> MC5887 | C39: =IFERROR(__xludf.DUMMYFUNCTION("""COMPUTED_VALUE"""),"P-1-N-270820-2459") -> P-1-N-270820-2459 | E39: =IFERROR(__xludf.DUMMYFUNCTION("""COMPUTED_VALUE"""),"تمت طباعة الشهادة") -> تمت طباعة الشهادة | F39: =IFERROR(__xludf.DUMMYFUNCTION("""COMPUTED_VALUE"""),"Healthy Treats Intestinal Aid For Puppies 50g") -> Healthy Treats Intestinal Aid For Puppies 50g | G39: =IFERROR(__xludf.DUMMYFUNCTION("""COMPUTED_VALUE"""),"هيلثي تريتس مساعدات معوية للجراء 50 جم") -> هيلثي تريتس مساعدات معوية للجراء 50 جم | H39: =IFERROR(__xludf.DUMMYFUNCTION("""COMPUTED_VALUE"""),"MAFE20201057") -> MAFE20201057 | K39: =IFERROR(__xludf.DUMMYFUNCTION("""COMPUTED_VALUE"""),"مارك اند شابل ليمتد") -> مارك اند شابل ليمتد | L39: =IFERROR(__xludf.DUMMYFUNCTION("""COMPUTED_VALUE"""),"MC5887") -> MC5887
A40: =IFERROR(__xludf.DUMMYFUNCTION("""COMPUTED_VALUE"""),39.0) -> 39 | B40: =IFERROR(__xludf.DUMMYFUNCTION("""COMPUTED_VALUE"""),"MC5917") -> MC5917 | C40: =IFERROR(__xludf.DUMMYFUNCTION("""COMPUTED_VALUE"""),"P-1-N-270820-2462") -> P-1-N-270820-2462 | E40: =IFERROR(__xludf.DUMMYFUNCTION("""COMPUTED_VALUE"""),"تمت طباعة الشهادة") -> تمت طباعة الشهادة | F40: =IFERROR(__xludf.DUMMYFUNCTION("""COMPUTED_VALUE"""),"Healthy Treats Fleaguard For Dogs & Puppies 70g") -> Healthy Treats Fleaguard For Dogs & Puppies 70g | G40: =IFERROR(__xludf.DUMMYFUNCTION("""COMPUTED_VALUE"""),"هيلثي تريتس فليجارد للكلاب والجراء 70 جم") -> هيلثي تريتس فليجارد للكلاب والجراء 70 جم | H40: =IFERROR(__xludf.DUMMYFUNCTION("""COMPUTED_VALUE"""),"MAFE20201056") -> MAFE20201056 | K40: =IFERROR(__xludf.DUMMYFUNCTION("""COMPUTED_VALUE"""),"مارك اند شابل ليمتد") -> مارك اند شابل ليمتد | L40: =IFERROR(__xludf.DUMMYFUNCTION("""COMPUTED_VALUE"""),"MC5917") -> MC5917
A41: =IFERROR(__xludf.DUMMYFUNCTION("""COMPUTED_VALUE"""),40.0) -> 40 | B41: =IFERROR(__xludf.DUMMYFUNCTION("""COMPUTED_VALUE"""),"HS30310") -> HS30310 | C41: =IFERROR(__xludf.DUMMYFUNCTION("""COMPUTED_VALUE"""),"P-1-N-270820-2464") -> P-1-N-270820-2464 | E41: =IFERROR(__xludf.DUMMYFUNCTION("""COMPUTED_VALUE"""),"تمت طباعة الشهادة") -> تمت طباعة الشهادة | F41: =IFERROR(__xludf.DUMMYFUNCTION("""COMPUTED_VALUE"""),"InTune Harmony Macaw 1.36 KG") -> InTune Harmony Macaw 1.36 KG | G41: =IFERROR(__xludf.DUMMYFUNCTION("""COMPUTED_VALUE"""),"ان تون هارموني ببغاء مكاو 1.36 كيلو") -> ان تون هارموني ببغاء مكاو 1.36 كيلو | H41: =IFERROR(__xludf.DUMMYFUNCTION("""COMPUTED_VALUE"""),"MAFE20201035") -> MAFE20201035 | K41: =IFERROR(__xludf.DUMMYFUNCTION("""COMPUTED_VALUE"""),"مؤسسة مجموعة ذا هيغينز") -> مؤسسة مجموعة ذا هيغينز | L41: =IFERROR(__xludf.DUMMYFUNCTION("""COMPUTED_VALUE"""),"HS30310") -> HS30310
A42: =IFERROR(__xludf.DUMMYFUNCTION("""COMPUTED_VALUE"""),41.0) -> 41 | B42: =IFERROR(__xludf.DUMMYFUNCTION("""COMPUTED_VALUE"""),"HS30325") -> HS30325 | C42: =IFERROR(__xludf.DUMMYFUNCTION("""COMPUTED_VALUE"""),"P-1-N-270820-2465") -> P-1-N-270820-2465 | E42: =IFERROR(__xludf.DUMMYFUNCTION("""COMPUTED_VALUE"""),"تمت طباعة الشهادة") -> تمت طباعة الشهادة | F42: =IFERROR(__xludf.DUMMYFUNCTION("""COMPUTED_VALUE"""),"InTune Harmony Parakeet 0.91 KG") -> InTune Harmony Parakeet 0.91 KG | G42: =IFERROR(__xludf.DUMMYFUNCTION("""COMPUTED_VALUE"""),"ان تون هارموني الببغاء الصغير 0.91 كيلو") -> ان تون هارموني الببغاء الصغير 0.91 كيلو | H42: =IFERROR(__xludf.DUMMYFUNCTION("""COMPUTED_VALUE"""),"MAFE20201008") -> MAFE20201008 | K42: =IFERROR(__xludf.DUMMYFUNCTION("""COMPUTED_VALUE"""),"مؤسسة مجموعة ذا هيغينز") -> مؤسسة مجموعة ذا هيغينز | L42: =IFERROR(__xludf.DUMMYFUNCTION("""COMPUTED_VALUE"""),"HS30325") -> HS30325
A43: =IFERROR(__xludf.DUMMYFUNCTION("""COMPUTED_VALUE"""),42.0) -> 42 | B43: =IFERROR(__xludf.DUMMYFUNCTION("""COMPUTED_VALUE"""),"HS30315") -> HS30315 | C43: =IFERROR(__xludf.DUMMYFUNCTION("""COMPUTED_VALUE"""),"P-1-N-270820-2466") -> P-1-N-270820-2466 | E43: =IFERROR(__xludf.DUMMYFUNCTION("""COMPUTED_VALUE"""),"تمت طباعة الشهادة") -> تمت طباعة الشهادة | F43: =IFERROR(__xludf.DUMMYFUNCTION("""COMPUTED_VALUE"""),"InTune Harmony Parrot 1.36 KG") -> InTune Harmony Parrot 1.36 KG | G43: =IFERROR(__xludf.DUMMYFUNCTION("""COMPUTED_VALUE"""),"ان تون هارموني ببغاء 1.36 كيلو") -> ان تون هارموني ببغاء 1.36 كيلو | H43: =IFERROR(__xludf.DUMMYFUNCTION("""COMPUTED_VALUE"""),"MAFE20201007") -> MAFE20201007 | K43: =IFERROR(__xludf.DUMMYFUNCTION("""COMPUTED_VALUE"""),"مؤسسة مجموعة ذا هيغينز") -> مؤسسة مجموعة ذا هيغينز | L43: =IFERROR(__xludf.DUMMYFUNCTION("""COMPUTED_VALUE"""),"HS30315") -> HS30315
A44: =IFERROR(__xludf.DUMMYFUNCTION("""COMPUTED_VALUE"""),43.0) -> 43 | B44: =IFERROR(__xludf.DUMMYFUNCTION("""COMPUTED_VALUE"""),"HS30317") -> HS30317 | C44: =IFERROR(__xludf.DUMMYFUNCTION("""COMPUTED_VALUE"""),"P-1-N-270820-2467") -> P-1-N-270820-2467 | E44: =IFERROR(__xludf.DUMMYFUNCTION("""COMPUTED_VALUE"""),"تمت طباعة الشهادة") -> تمت طباعة الشهادة | F44: =IFERROR(__xludf.DUMMYFUNCTION("""COMPUTED_VALUE"""),"InTune Harmony Parrot 7.94 KG") -> InTune Harmony Parrot 7.94 KG | G44: =IFERROR(__xludf.DUMMYFUNCTION("""COMPUTED_VALUE"""),"ان تون هارموني ببغاء 7.94 كيلو") -> ان تون هارموني ببغاء 7.94 كيلو | H44: =IFERROR(__xludf.DUMMYFUNCTION("""COMPUTED_VALUE"""),"MAFE20201006") -> MAFE20201006 | K44: =IFERROR(__xludf.DUMMYFUNCTION("""COMPUTED_VALUE"""),"مؤسسة مجموعة ذا هيغينز") -> مؤسسة مجموعة ذا هيغينز | L44: =IFERROR(__xludf.DUMMYFUNCTION("""COMPUTED_VALUE"""),"HS30317") -> HS30317
A45: =IFERROR(__xludf.DUMMYFUNCTION("""COMPUTED_VALUE"""),44.0) -> 44 | B45: =IFERROR(__xludf.DUMMYFUNCTION("""COMPUTED_VALUE"""),"HS30312") -> HS30312 | C45: =IFERROR(__xludf.DUMMYFUNCTION("""COMPUTED_VALUE"""),"P-1-N-270820-2468") -> P-1-N-270820-2468 | E45: =IFERROR(__xludf.DUMMYFUNCTION("""COMPUTED_VALUE"""),"تمت طباعة الشهادة") -> تمت طباعة الشهادة | F45: =IFERROR(__xludf.DUMMYFUNCTION("""COMPUTED_VALUE"""),"InTune Harmony Macaw 7.94 KG") -> InTune Harmony Macaw 7.94 KG | G45: =IFERROR(__xludf.DUMMYFUNCTION("""COMPUTED_VALUE"""),"ان تون هارموني ببغاء مكاو 7.94 كيلو") -> ان تون هارموني ببغاء مكاو 7.94 كيلو | H45: =IFERROR(__xludf.DUMMYFUNCTION("""COMPUTED_VALUE"""),"MAFE20201055") -> MAFE20201055 | K45: =IFERROR(__xludf.DUMMYFUNCTION("""COMPUTED_VALUE"""),"مؤسسة مجموعة ذا هيغينز") -> مؤسسة مجموعة ذا هيغينز | L45: =IFERROR(__xludf.DUMMYFUNCTION("""COMPUTED_VALUE"""),"HS30312") -> HS30312
A46: =IFERROR(__xludf.DUMMYFUNCTION("""COMPUTED_VALUE"""),45.0) -> 45 | B46: =IFERROR(__xludf.DUMMYFUNCTION("""COMPUTED_VALUE"""),"HS30320") -> HS30320 | C46: =IFERROR(__xludf.DUMMYFUNCTION("""COMPUTED_VALUE"""),"P-1-N-270820-2469") -> P-1-N-270820-2469 | E46: =IFERROR(__xludf.DUMMYFUNCTION("""COMPUTED_VALUE"""),"تمت طباعة الشهادة") -> تمت طباعة الشهادة | F46: =IFERROR(__xludf.DUMMYFUNCTION("""COMPUTED_VALUE"""),"InTune Harmony Conure & Cockatiel 0.91 KG") -> InTune Harmony Conure & Cockatiel 0.91 KG | G46: =IFERROR(__xludf.DUMMYFUNCTION("""COMPUTED_VALUE"""),"ان تون هارموني الكنيور/ الكوكاتيل 0.91 كيلو") -> ان تون هارموني الكنيور/ الكوكاتيل 0.91 كيلو | H46: =IFERROR(__xludf.DUMMYFUNCTION("""COMPUTED_VALUE"""),"MAFE20201080") -> MAFE20201080 | K46: =IFERROR(__xludf.DUMMYFUNCTION("""COMPUTED_VALUE"""),"مؤسسة مجموعة ذا هيغينز") -> مؤسسة مجموعة ذا هيغينز | L46: =IFERROR(__xludf.DUMMYFUNCTION("""COMPUTED_VALUE"""),"HS30320") -> HS30320
A47: =IFERROR(__xludf.DUMMYFUNCTION("""COMPUTED_VALUE"""),46.0) -> 46 | B47: =IFERROR(__xludf.DUMMYFUNCTION("""COMPUTED_VALUE"""),"MC5023") -> MC5023 | C47: =IFERROR(__xludf.DUMMYFUNCTION("""COMPUTED_VALUE"""),"P-1-N-270820-2470") -> P-1-N-270820-2470 | E47: =IFERROR(__xludf.DUMMYFUNCTION("""COMPUTED_VALUE"""),"REJECTED") -> REJECTED | F47: =IFERROR(__xludf.DUMMYFUNCTION("""COMPUTED_VALUE"""),"Healthy Bites Breath & Dental For Cats & Kittens 65g") -> Healthy Bites Breath & Dental For Cats & Kittens 65g | G47: =IFERROR(__xludf.DUMMYFUNCTION("""COMPUTED_VALUE"""),"هيلثي بايتس لرائحة الفم والأسنان للقطط الصغيرة و البالغة 65 جم") -> هيلثي بايتس لرائحة الفم والأسنان للقطط الصغيرة و البالغة 65 جم | K47: =IFERROR(__xludf.DUMMYFUNCTION("""COMPUTED_VALUE"""),"مارك اند شابل ليمتد") -> مارك اند شابل ليمتد | L47: =IFERROR(__xludf.DUMMYFUNCTION("""COMPUTED_VALUE"""),"MC5023") -> MC5023
A48: =IFERROR(__xludf.DUMMYFUNCTION("""COMPUTED_VALUE"""),47.0) -> 47 | B48: =IFERROR(__xludf.DUMMYFUNCTION("""COMPUTED_VALUE"""),"HS30322") -> HS30322 | C48: =IFERROR(__xludf.DUMMYFUNCTION("""COMPUTED_VALUE"""),"P-1-N-270820-2471") -> P-1-N-270820-2471 | E48: =IFERROR(__xludf.DUMMYFUNCTION("""COMPUTED_VALUE"""),"تمت طباعة الشهادة") -> تمت طباعة الشهادة | F48: =IFERROR(__xludf.DUMMYFUNCTION("""COMPUTED_VALUE"""),"InTune Harmony Conure & Cockatiel 7.94 KG") -> InTune Harmony Conure & Cockatiel 7.94 KG | G48: =IFERROR(__xludf.DUMMYFUNCTION("""COMPUTED_VALUE"""),"ان تون هارموني ببغاء الكنيور و الكوكاتيل 7.94 كيلو") -> ان تون هارموني ببغاء الكنيور و الكوكاتيل 7.94 كيلو | H48: =IFERROR(__xludf.DUMMYFUNCTION("""COMPUTED_VALUE"""),"MAFE20201079") -> MAFE20201079 | K48: =IFERROR(__xludf.DUMMYFUNCTION("""COMPUTED_VALUE"""),"مؤسسة مجموعة ذا هيغينز") -> مؤسسة مجموعة ذا هيغينز | L48: =IFERROR(__xludf.DUMMYFUNCTION("""COMPUTED_VALUE"""),"HS30322") -> HS30322
A49: =IFERROR(__xludf.DUMMYFUNCTION("""COMPUTED_VALUE"""),48.0) -> 48 | B49: =IFERROR(__xludf.DUMMYFUNCTION("""COMPUTED_VALUE"""),"HS30270") -> HS30270 | C49: =IFERROR(__xludf.DUMMYFUNCTION("""COMPUTED_VALUE"""),"P-1-N-270820-2473") -> P-1-N-270820-2473 | E49: =IFERROR(__xludf.DUMMYFUNCTION("""COMPUTED_VALUE"""),"تمت طباعة الشهادة") -> تمت طباعة الشهادة | F49: =IFERROR(__xludf.DUMMYFUNCTION("""COMPUTED_VALUE"""),"InTune Hand Feed 283 G") -> InTune Hand Feed 283 G | G49: =IFERROR(__xludf.DUMMYFUNCTION("""COMPUTED_VALUE"""),"ان تون تغذية يدوية (اكل غر) 283 جرام") -> ان تون تغذية يدوية (اكل غر) 283 جرام | H49: =IFERROR(__xludf.DUMMYFUNCTION("""COMPUTED_VALUE"""),"MAFE20201054") -> MAFE20201054 | K49: =IFERROR(__xludf.DUMMYFUNCTION("""COMPUTED_VALUE"""),"مؤسسة مجموعة ذا هيغينز") -> مؤسسة مجموعة ذا هيغينز | L49: =IFERROR(__xludf.DUMMYFUNCTION("""COMPUTED_VALUE"""),"HS30270") -> HS30270
A50: =IFERROR(__xludf.DUMMYFUNCTION("""COMPUTED_VALUE"""),49.0) -> 49 | B50: =IFERROR(__xludf.DUMMYFUNCTION("""COMPUTED_VALUE"""),"HS30272") -> HS30272 | C50: =IFERROR(__xludf.DUMMYFUNCTION("""COMPUTED_VALUE"""),"P-1-N-270820-2474") -> P-1-N-270820-2474 | E50: =IFERROR(__xludf.DUMMYFUNCTION("""COMPUTED_VALUE"""),"تمت طباعة الشهادة") -> تمت طباعة الشهادة | F50: =IFERROR(__xludf.DUMMYFUNCTION("""COMPUTED_VALUE"""),"InTune Hand Feed 2.27 KG") -> InTune Hand Feed 2.27 KG | G50: =IFERROR(__xludf.DUMMYFUNCTION("""COMPUTED_VALUE"""),"ان تون تغذية يدوية (اكل غر) 2.27 كيلو") -> ان تون تغذية يدوية (اكل غر) 2.27 كيلو | H50: =IFERROR(__xludf.DUMMYFUNCTION("""COMPUTED_VALUE"""),"MAFE20201053") -> MAFE20201053 | K50: =IFERROR(__xludf.DUMMYFUNCTION("""COMPUTED_VALUE"""),"مؤسسة مجموعة ذا هيغينز") -> مؤسسة مجموعة ذا هيغينز | L50: =IFERROR(__xludf.DUMMYFUNCTION("""COMPUTED_VALUE"""),"HS30272") -> HS30272
A51: =IFERROR(__xludf.DUMMYFUNCTION("""COMPUTED_VALUE"""),50.0) -> 50 | B51: =IFERROR(__xludf.DUMMYFUNCTION("""COMPUTED_VALUE"""),"HS30275") -> HS30275 | C51: =IFERROR(__xludf.DUMMYFUNCTION("""COMPUTED_VALUE"""),"P-1-N-270820-2475") -> P-1-N-270820-2475 | E51: =IFERROR(__xludf.DUMMYFUNCTION("""COMPUTED_VALUE"""),"تمت طباعة الشهادة") -> تمت طباعة الشهادة | F51: =IFERROR(__xludf.DUMMYFUNCTION("""COMPUTED_VALUE"""),"InTune Hand Feed HE 2.27 KG") -> InTune Hand Feed HE 2.27 KG | G51: =IFERROR(__xludf.DUMMYFUNCTION("""COMPUTED_VALUE"""),"ان تون تغذية يدوية عالي الطاقة (اكل غر) 2.27 كيلو") -> ان تون تغذية يدوية عالي الطاقة (اكل غر) 2.27 كيلو | H51: =IFERROR(__xludf.DUMMYFUNCTION("""COMPUTED_VALUE"""),"MAFE20201052") -> MAFE20201052 | K51: =IFERROR(__xludf.DUMMYFUNCTION("""COMPUTED_VALUE"""),"مؤسسة مجموعة ذا هيغينز") -> مؤسسة مجموعة ذا هيغينز | L51: =IFERROR(__xludf.DUMMYFUNCTION("""COMPUTED_VALUE"""),"HS30275") -> HS30275
A52: =IFERROR(__xludf.DUMMYFUNCTION("""COMPUTED_VALUE"""),51.0) -> 51 | B52: =IFERROR(__xludf.DUMMYFUNCTION("""COMPUTED_VALUE"""),"HS30274") -> HS30274 | C52: =IFERROR(__xludf.DUMMYFUNCTION("""COMPUTED_VALUE"""),"P-1-N-270820-2476") -> P-1-N-270820-2476 | E52: =IFERROR(__xludf.DUMMYFUNCTION("""COMPUTED_VALUE"""),"تمت طباعة الشهادة") -> تمت طباعة الشهادة | F52: =IFERROR(__xludf.DUMMYFUNCTION("""COMPUTED_VALUE"""),"InTune Hand Feed HE 283 G") -> InTune Hand Feed HE 283 G | G52: =IFERROR(__xludf.DUMMYFUNCTION("""COMPUTED_VALUE"""),"ان تون تغذية يدوية عالي الطاقة (اكل غر) 283 جرام") -> ان تون تغذية يدوية عالي الطاقة (اكل غر) 283 جرام | H52: =IFERROR(__xludf.DUMMYFUNCTION("""COMPUTED_VALUE"""),"MAFE20201005") -> MAFE20201005 | K52: =IFERROR(__xludf.DUMMYFUNCTION("""COMPUTED_VALUE"""),"مؤسسة مجموعة ذا هيغينز") -> مؤسسة مجموعة ذا هيغينز | L52: =IFERROR(__xludf.DUMMYFUNCTION("""COMPUTED_VALUE"""),"HS30274") -> HS30274
A53: =IFERROR(__xludf.DUMMYFUNCTION("""COMPUTED_VALUE"""),52.0) -> 52 | B53: =IFERROR(__xludf.DUMMYFUNCTION("""COMPUTED_VALUE"""),"MC5016") -> MC5016 | C53: =IFERROR(__xludf.DUMMYFUNCTION("""COMPUTED_VALUE"""),"P-1-N-300820-2488") -> P-1-N-300820-2488 | E53: =IFERROR(__xludf.DUMMYFUNCTION("""COMPUTED_VALUE"""),"REJECTED") -> REJECTED | F53: =IFERROR(__xludf.DUMMYFUNCTION("""COMPUTED_VALUE"""),"Healthy Bites Hairball Remedy For Cats & Kittens 65g") -> Healthy Bites Hairball Remedy For Cats & Kittens 65g | G53: =IFERROR(__xludf.DUMMYFUNCTION("""COMPUTED_VALUE"""),"هيلثي بايتس لمنع كرات الشعر للقطط الصغيرة و البالغة 65 جم") -> هيلثي بايتس لمنع كرات الشعر للقطط الصغيرة و البالغة 65 جم | K53: =IFERROR(__xludf.DUMMYFUNCTION("""COMPUTED_VALUE"""),"مارك اند شابل ليمتد") -> مارك اند شابل ليمتد | L53: =IFERROR(__xludf.DUMMYFUNCTION("""COMPUTED_VALUE"""),"MC5016") -> MC5016
A54: =IFERROR(__xludf.DUMMYFUNCTION("""COMPUTED_VALUE"""),53.0) -> 53 | B54: =IFERROR(__xludf.DUMMYFUNCTION("""COMPUTED_VALUE"""),"MC4965") -> MC4965 | C54: =IFERROR(__xludf.DUMMYFUNCTION("""COMPUTED_VALUE"""),"P-1-N-300820-2489") -> P-1-N-300820-2489 | E54: =IFERROR(__xludf.DUMMYFUNCTION("""COMPUTED_VALUE"""),"REJECTED") -> REJECTED | F54: =IFERROR(__xludf.DUMMYFUNCTION("""COMPUTED_VALUE"""),"Healthy Bites Nutri Booster For Kittens 65g") -> Healthy Bites Nutri Booster For Kittens 65g | G54: =IFERROR(__xludf.DUMMYFUNCTION("""COMPUTED_VALUE"""),"هيلثي بايتس نيوتري بوستر للقطط الصغيرة 65 جم") -> هيلثي بايتس نيوتري بوستر للقطط الصغيرة 65 جم | K54: =IFERROR(__xludf.DUMMYFUNCTION("""COMPUTED_VALUE"""),"مارك اند شابل ليمتد") -> مارك اند شابل ليمتد | L54: =IFERROR(__xludf.DUMMYFUNCTION("""COMPUTED_VALUE"""),"MC4965") -> MC4965
A55: =IFERROR(__xludf.DUMMYFUNCTION("""COMPUTED_VALUE"""),54.0) -> 54 | B55: =IFERROR(__xludf.DUMMYFUNCTION("""COMPUTED_VALUE"""),"MC5030") -> MC5030 | C55: =IFERROR(__xludf.DUMMYFUNCTION("""COMPUTED_VALUE"""),"P-1-N-300820-2492") -> P-1-N-300820-2492 | E55: =IFERROR(__xludf.DUMMYFUNCTION("""COMPUTED_VALUE"""),"تمت طباعة الشهادة") -> تمت طباعة الشهادة | F55: =IFERROR(__xludf.DUMMYFUNCTION("""COMPUTED_VALUE"""),"Healthy Bites Urinary Care For Cats & Kittens 65g") -> Healthy Bites Urinary Care For Cats & Kittens 65g | G55: =IFERROR(__xludf.DUMMYFUNCTION("""COMPUTED_VALUE"""),"هيلثي بايتس للعناية البولية للقطط الصغيرة والبالغة 65 جم") -> هيلثي بايتس للعناية البولية للقطط الصغيرة والبالغة 65 جم | H55: =IFERROR(__xludf.DUMMYFUNCTION("""COMPUTED_VALUE"""),"MAFE20201078") -> MAFE20201078 | K55: =IFERROR(__xludf.DUMMYFUNCTION("""COMPUTED_VALUE"""),"مارك اند شابل ليمتد") -> مارك اند شابل ليمتد | L55: =IFERROR(__xludf.DUMMYFUNCTION("""COMPUTED_VALUE"""),"MC5030") -> MC5030
A56: =IFERROR(__xludf.DUMMYFUNCTION("""COMPUTED_VALUE"""),55.0) -> 55 | B56: =IFERROR(__xludf.DUMMYFUNCTION("""COMPUTED_VALUE"""),"MC5924") -> MC5924 | C56: =IFERROR(__xludf.DUMMYFUNCTION("""COMPUTED_VALUE"""),"P-1-N-300820-2499") -> P-1-N-300820-2499 | E56: =IFERROR(__xludf.DUMMYFUNCTION("""COMPUTED_VALUE"""),"تمت طباعة الشهادة") -> تمت طباعة الشهادة | F56: =IFERROR(__xludf.DUMMYFUNCTION("""COMPUTED_VALUE"""),"Healthy Bites Growth Support For Kittens 65g") -> Healthy Bites Growth Support For Kittens 65g | G56: =IFERROR(__xludf.DUMMYFUNCTION("""COMPUTED_VALUE"""),"هيلثي بايتس دعم النمو للقطط الصغيرة 65 جم") -> هيلثي بايتس دعم النمو للقطط الصغيرة 65 جم | H56: =IFERROR(__xludf.DUMMYFUNCTION("""COMPUTED_VALUE"""),"MAFE20201077") -> MAFE20201077 | K56: =IFERROR(__xludf.DUMMYFUNCTION("""COMPUTED_VALUE"""),"مارك اند شابل ليمتد") -> مارك اند شابل ليمتد | L56: =IFERROR(__xludf.DUMMYFUNCTION("""COMPUTED_VALUE"""),"MC5924") -> MC5924
A57: =IFERROR(__xludf.DUMMYFUNCTION("""COMPUTED_VALUE"""),56.0) -> 56 | B57: =IFERROR(__xludf.DUMMYFUNCTION("""COMPUTED_VALUE"""),"MC5627") -> MC5627 | C57: =IFERROR(__xludf.DUMMYFUNCTION("""COMPUTED_VALUE"""),"P-1-N-300820-2504") -> P-1-N-300820-2504 | E57: =IFERROR(__xludf.DUMMYFUNCTION("""COMPUTED_VALUE"""),"تمت طباعة الشهادة") -> تمت طباعة الشهادة | F57: =IFERROR(__xludf.DUMMYFUNCTION("""COMPUTED_VALUE"""),"Feline Happy Chicken 60g") -> Feline Happy Chicken 60g | G57: =IFERROR(__xludf.DUMMYFUNCTION("""COMPUTED_VALUE"""),"فيلين هابي بالدجاج 60 جم") -> فيلين هابي بالدجاج 60 جم | H57: =IFERROR(__xludf.DUMMYFUNCTION("""COMPUTED_VALUE"""),"MAFE20201209") -> MAFE20201209 | K57: =IFERROR(__xludf.DUMMYFUNCTION("""COMPUTED_VALUE"""),"مارك اند شابل ليمتد") -> مارك اند شابل ليمتد | L57: =IFERROR(__xludf.DUMMYFUNCTION("""COMPUTED_VALUE"""),"MC5627") -> MC5627
A58: =IFERROR(__xludf.DUMMYFUNCTION("""COMPUTED_VALUE"""),57.0) -> 57 | B58: =IFERROR(__xludf.DUMMYFUNCTION("""COMPUTED_VALUE"""),"MC5634") -> MC5634 | C58: =IFERROR(__xludf.DUMMYFUNCTION("""COMPUTED_VALUE"""),"P-1-N-300820-2506") -> P-1-N-300820-2506 | E58: =IFERROR(__xludf.DUMMYFUNCTION("""COMPUTED_VALUE"""),"تمت طباعة الشهادة") -> تمت طباعة الشهادة | F58: =IFERROR(__xludf.DUMMYFUNCTION("""COMPUTED_VALUE"""),"Feline Happy Duck 60g") -> Feline Happy Duck 60g | G58: =IFERROR(__xludf.DUMMYFUNCTION("""COMPUTED_VALUE"""),"فيلين هابي بالبط 60 جم") -> فيلين هابي بالبط 60 جم | H58: =IFERROR(__xludf.DUMMYFUNCTION("""COMPUTED_VALUE"""),"MAFE20201163") -> MAFE20201163 | K58: =IFERROR(__xludf.DUMMYFUNCTION("""COMPUTED_VALUE"""),"مارك اند شابل ليمتد") -> مارك اند شابل ليمتد | L58: =IFERROR(__xludf.DUMMYFUNCTION("""COMPUTED_VALUE"""),"MC5634") -> MC5634
A59: =IFERROR(__xludf.DUMMYFUNCTION("""COMPUTED_VALUE"""),58.0) -> 58 | B59: =IFERROR(__xludf.DUMMYFUNCTION("""COMPUTED_VALUE"""),"MC5641") -> MC5641 | C59: =IFERROR(__xludf.DUMMYFUNCTION("""COMPUTED_VALUE"""),"P-1-N-300820-2507") -> P-1-N-300820-2507 | E59: =IFERROR(__xludf.DUMMYFUNCTION("""COMPUTED_VALUE"""),"تمت طباعة الشهادة") -> تمت طباعة الشهادة | F59: =IFERROR(__xludf.DUMMYFUNCTION("""COMPUTED_VALUE"""),"Feline Happy Salmon 60g") -> Feline Happy Salmon 60g | G59: =IFERROR(__xludf.DUMMYFUNCTION("""COMPUTED_VALUE"""),"فيلين هابي بالسالمون 60 جم") -> فيلين هابي بالسالمون 60 جم | H59: =IFERROR(__xludf.DUMMYFUNCTION("""COMPUTED_VALUE"""),"MAFE20201162") -> MAFE20201162 | K59: =IFERROR(__xludf.DUMMYFUNCTION("""COMPUTED_VALUE"""),"مارك اند شابل ليمتد") -> مارك اند شابل ليمتد | L59: =IFERROR(__xludf.DUMMYFUNCTION("""COMPUTED_VALUE"""),"MC5641") -> MC5641
A60: =IFERROR(__xludf.DUMMYFUNCTION("""COMPUTED_VALUE"""),59.0) -> 59 | B60: =IFERROR(__xludf.DUMMYFUNCTION("""COMPUTED_VALUE"""),"422218") -> 422218 | C60: =IFERROR(__xludf.DUMMYFUNCTION("""COMPUTED_VALUE"""),"P-1-N-300820-2508") -> P-1-N-300820-2508 | E60: =IFERROR(__xludf.DUMMYFUNCTION("""COMPUTED_VALUE"""),"تمت طباعة الشهادة") -> تمت طباعة الشهادة | F60: =IFERROR(__xludf.DUMMYFUNCTION("""COMPUTED_VALUE"""),"ARA Parrot 2 KG") -> ARA Parrot 2 KG | G60: =IFERROR(__xludf.DUMMYFUNCTION("""COMPUTED_VALUE"""),"ببغاء أرا 2 كيلو") -> ببغاء أرا 2 كيلو | H60: =IFERROR(__xludf.DUMMYFUNCTION("""COMPUTED_VALUE"""),"MAFE20201076") -> MAFE20201076 | K60: =IFERROR(__xludf.DUMMYFUNCTION("""COMPUTED_VALUE"""),"فيرسل لاقا ان في") -> فيرسل لاقا ان في | L60: =IFERROR(__xludf.DUMMYFUNCTION("""COMPUTED_VALUE"""),"422218") -> 422218
A61: =IFERROR(__xludf.DUMMYFUNCTION("""COMPUTED_VALUE"""),60.0) -> 60 | B61: =IFERROR(__xludf.DUMMYFUNCTION("""COMPUTED_VALUE"""),"422219") -> 422219 | C61: =IFERROR(__xludf.DUMMYFUNCTION("""COMPUTED_VALUE"""),"P-1-N-300820-2509") -> P-1-N-300820-2509 | E61: =IFERROR(__xludf.DUMMYFUNCTION("""COMPUTED_VALUE"""),"تمت طباعة الشهادة") -> تمت طباعة الشهادة | F61: =IFERROR(__xludf.DUMMYFUNCTION("""COMPUTED_VALUE"""),"Prestige ARA Parrot 15 kg") -> Prestige ARA Parrot 15 kg | G61: =IFERROR(__xludf.DUMMYFUNCTION("""COMPUTED_VALUE"""),"برستيج أرا ببغاء 15 كيلو") -> برستيج أرا ببغاء 15 كيلو | H61: =IFERROR(__xludf.DUMMYFUNCTION("""COMPUTED_VALUE"""),"MAFE20201036") -> MAFE20201036 | K61: =IFERROR(__xludf.DUMMYFUNCTION("""COMPUTED_VALUE"""),"فيرسل لاقا ان في") -> فيرسل لاقا ان في | L61: =IFERROR(__xludf.DUMMYFUNCTION("""COMPUTED_VALUE"""),"422219") -> 422219
A62: =IFERROR(__xludf.DUMMYFUNCTION("""COMPUTED_VALUE"""),61.0) -> 61 | B62: =IFERROR(__xludf.DUMMYFUNCTION("""COMPUTED_VALUE"""),"421620") -> 421620 | C62: =IFERROR(__xludf.DUMMYFUNCTION("""COMPUTED_VALUE"""),"P-1-N-300820-2510") -> P-1-N-300820-2510 | E62: =IFERROR(__xludf.DUMMYFUNCTION("""COMPUTED_VALUE"""),"تمت طباعة الشهادة") -> تمت طباعة الشهادة | F62: =IFERROR(__xludf.DUMMYFUNCTION("""COMPUTED_VALUE"""),"Prestige Budgie 1 KG") -> Prestige Budgie 1 KG | G62: =IFERROR(__xludf.DUMMYFUNCTION("""COMPUTED_VALUE"""),"برستيج ببغاء صغير 1 كيلو") -> برستيج ببغاء صغير 1 كيلو | H62: =IFERROR(__xludf.DUMMYFUNCTION("""COMPUTED_VALUE"""),"MAFE20201047") -> MAFE20201047 | K62: =IFERROR(__xludf.DUMMYFUNCTION("""COMPUTED_VALUE"""),"فيرسل لاقا ان في") -> فيرسل لاقا ان في | L62: =IFERROR(__xludf.DUMMYFUNCTION("""COMPUTED_VALUE"""),"421620") -> 421620
A63: =IFERROR(__xludf.DUMMYFUNCTION("""COMPUTED_VALUE"""),62.0) -> 62 | B63: =IFERROR(__xludf.DUMMYFUNCTION("""COMPUTED_VALUE"""),"421621") -> 421621 | C63: =IFERROR(__xludf.DUMMYFUNCTION("""COMPUTED_VALUE"""),"P-1-N-300820-2512") -> P-1-N-300820-2512 | E63: =IFERROR(__xludf.DUMMYFUNCTION("""COMPUTED_VALUE"""),"تمت طباعة الشهادة") -> تمت طباعة الشهادة | F63: =IFERROR(__xludf.DUMMYFUNCTION("""COMPUTED_VALUE"""),"Prestige Budgie 4 KG") -> Prestige Budgie 4 KG | G63: =IFERROR(__xludf.DUMMYFUNCTION("""COMPUTED_VALUE"""),"برستيج ببغاء صغير 4 كيلو") -> برستيج ببغاء صغير 4 كيلو | H63: =IFERROR(__xludf.DUMMYFUNCTION("""COMPUTED_VALUE"""),"MAFE20201046") -> MAFE20201046 | K63: =IFERROR(__xludf.DUMMYFUNCTION("""COMPUTED_VALUE"""),"فيرسل لاقا ان في") -> فيرسل لاقا ان في | L63: =IFERROR(__xludf.DUMMYFUNCTION("""COMPUTED_VALUE"""),"421621") -> 421621
A64: =IFERROR(__xludf.DUMMYFUNCTION("""COMPUTED_VALUE"""),63.0) -> 63 | C64: =IFERROR(__xludf.DUMMYFUNCTION("""COMPUTED_VALUE"""),"P-1-N-310820-2517") -> P-1-N-310820-2517 | E64: =IFERROR(__xludf.DUMMYFUNCTION("""COMPUTED_VALUE"""),"تمت طباعة الشهادة") -> تمت طباعة الشهادة | F64: =IFERROR(__xludf.DUMMYFUNCTION("""COMPUTED_VALUE"""),"Healthy Centres Mature Cheese Flavour Treats 80g") -> Healthy Centres Mature Cheese Flavour Treats 80g | G64: =IFERROR(__xludf.DUMMYFUNCTION("""COMPUTED_VALUE"""),"هيلثي سنترز بنكهة الجبن الناضجة 80 جرام") -> هيلثي سنترز بنكهة الجبن الناضجة 80 جرام | H64: =IFERROR(__xludf.DUMMYFUNCTION("""COMPUTED_VALUE"""),"MAFE20201045") -> MAFE20201045 | K64: =IFERROR(__xludf.DUMMYFUNCTION("""COMPUTED_VALUE"""),"مارك اند شابل ليمتد") -> مارك اند شابل ليمتد
A65: =IFERROR(__xludf.DUMMYFUNCTION("""COMPUTED_VALUE"""),64.0) -> 64 | C65: =IFERROR(__xludf.DUMMYFUNCTION("""COMPUTED_VALUE"""),"P-1-N-310820-2518") -> P-1-N-310820-2518 | E65: =IFERROR(__xludf.DUMMYFUNCTION("""COMPUTED_VALUE"""),"REJECTED") -> REJECTED | F65: =IFERROR(__xludf.DUMMYFUNCTION("""COMPUTED_VALUE"""),"Healthy Centres Roast Chicken Flavour Treats 80g") -> Healthy Centres Roast Chicken Flavour Treats 80g | G65: =IFERROR(__xludf.DUMMYFUNCTION("""COMPUTED_VALUE"""),"هيلثي سنترز بنكهة الدجاج المشوي 80 جرام") -> هيلثي سنترز بنكهة الدجاج المشوي 80 جرام | K65: =IFERROR(__xludf.DUMMYFUNCTION("""COMPUTED_VALUE"""),"مارك اند شابل ليمتد") -> مارك اند شابل ليمتد
A66: =IFERROR(__xludf.DUMMYFUNCTION("""COMPUTED_VALUE"""),65.0) -> 65 | C66: =IFERROR(__xludf.DUMMYFUNCTION("""COMPUTED_VALUE"""),"P-1-N-310820-2519") -> P-1-N-310820-2519 | E66: =IFERROR(__xludf.DUMMYFUNCTION("""COMPUTED_VALUE"""),"تمت طباعة الشهادة") -> تمت طباعة الشهادة | F66: =IFERROR(__xludf.DUMMYFUNCTION("""COMPUTED_VALUE"""),"Healthy Centres with Real Chicken & Vegetables 113g") -> Healthy Centres with Real Chicken & Vegetables 113g | G66: =IFERROR(__xludf.DUMMYFUNCTION("""COMPUTED_VALUE"""),"هيلثي سنترز مع دجاج حقيقي وخضار 113 جم") -> هيلثي سنترز مع دجاج حقيقي وخضار 113 جم | H66: =IFERROR(__xludf.DUMMYFUNCTION("""COMPUTED_VALUE"""),"MAFE20201044") -> MAFE20201044 | K66: =IFERROR(__xludf.DUMMYFUNCTION("""COMPUTED_VALUE"""),"مارك اند شابل ليمتد") -> مارك اند شابل ليمتد
A67: =IFERROR(__xludf.DUMMYFUNCTION("""COMPUTED_VALUE"""),66.0) -> 66 | C67: =IFERROR(__xludf.DUMMYFUNCTION("""COMPUTED_VALUE"""),"P-1-N-310820-2520") -> P-1-N-310820-2520 | E67: =IFERROR(__xludf.DUMMYFUNCTION("""COMPUTED_VALUE"""),"تمت طباعة الشهادة") -> تمت طباعة الشهادة | F67: =IFERROR(__xludf.DUMMYFUNCTION("""COMPUTED_VALUE"""),"Healthy Centres with Real Turkey & Cranberry 113g") -> Healthy Centres with Real Turkey & Cranberry 113g | G67: =IFERROR(__xludf.DUMMYFUNCTION("""COMPUTED_VALUE"""),"هيلثي سنترز مع مع الديك الرومي الحقيقي والتوت البري 113 جم") -> هيلثي سنترز مع مع الديك الرومي الحقيقي والتوت البري 113 جم | H67: =IFERROR(__xludf.DUMMYFUNCTION("""COMPUTED_VALUE"""),"MAFE20201043") -> MAFE20201043 | K67: =IFERROR(__xludf.DUMMYFUNCTION("""COMPUTED_VALUE"""),"مارك اند شابل ليمتد") -> مارك اند شابل ليمتد
A68: =IFERROR(__xludf.DUMMYFUNCTION("""COMPUTED_VALUE"""),67.0) -> 67 | B68: =IFERROR(__xludf.DUMMYFUNCTION("""COMPUTED_VALUE"""),"421040") -> 421040 | C68: =IFERROR(__xludf.DUMMYFUNCTION("""COMPUTED_VALUE"""),"P-1-N-010920-2536") -> P-1-N-010920-2536 | E68: =IFERROR(__xludf.DUMMYFUNCTION("""COMPUTED_VALUE"""),"تمت طباعة الشهادة") -> تمت طباعة الشهادة | F68: =IFERROR(__xludf.DUMMYFUNCTION("""COMPUTED_VALUE"""),"Prestige Canary 1 KG") -> Prestige Canary 1 KG | G68: =IFERROR(__xludf.DUMMYFUNCTION("""COMPUTED_VALUE"""),"برستيج كناري 1 كيلو") -> برستيج كناري 1 كيلو | H68: =IFERROR(__xludf.DUMMYFUNCTION("""COMPUTED_VALUE"""),"MAFE20201094") -> MAFE20201094 | K68: =IFERROR(__xludf.DUMMYFUNCTION("""COMPUTED_VALUE"""),"فيرسل لاقا ان في") -> فيرسل لاقا ان في | L68: =IFERROR(__xludf.DUMMYFUNCTION("""COMPUTED_VALUE"""),"421040") -> 421040
A69: =IFERROR(__xludf.DUMMYFUNCTION("""COMPUTED_VALUE"""),68.0) -> 68 | B69: =IFERROR(__xludf.DUMMYFUNCTION("""COMPUTED_VALUE"""),"421795") -> 421795 | C69: =IFERROR(__xludf.DUMMYFUNCTION("""COMPUTED_VALUE"""),"P-1-N-010920-2537") -> P-1-N-010920-2537 | E69: =IFERROR(__xludf.DUMMYFUNCTION("""COMPUTED_VALUE"""),"تمت طباعة الشهادة") -> تمت طباعة الشهادة | F69: =IFERROR(__xludf.DUMMYFUNCTION("""COMPUTED_VALUE"""),"Prestige Parrot 1 KG") -> Prestige Parrot 1 KG | G69: =IFERROR(__xludf.DUMMYFUNCTION("""COMPUTED_VALUE"""),"برستيج ببغاء 1 كيلو") -> برستيج ببغاء 1 كيلو | H69: =IFERROR(__xludf.DUMMYFUNCTION("""COMPUTED_VALUE"""),"MAFE20201074") -> MAFE20201074 | K69: =IFERROR(__xludf.DUMMYFUNCTION("""COMPUTED_VALUE"""),"فيرسل لاقا ان في") -> فيرسل لاقا ان في | L69: =IFERROR(__xludf.DUMMYFUNCTION("""COMPUTED_VALUE"""),"421795") -> 421795
A70: =IFERROR(__xludf.DUMMYFUNCTION("""COMPUTED_VALUE"""),69.0) -> 69 | B70: =IFERROR(__xludf.DUMMYFUNCTION("""COMPUTED_VALUE"""),"421796") -> 421796 | C70: =IFERROR(__xludf.DUMMYFUNCTION("""COMPUTED_VALUE"""),"P-1-N-010920-2538") -> P-1-N-010920-2538 | E70: =IFERROR(__xludf.DUMMYFUNCTION("""COMPUTED_VALUE"""),"تمت طباعة الشهادة") -> تمت طباعة الشهادة | F70: =IFERROR(__xludf.DUMMYFUNCTION("""COMPUTED_VALUE"""),"Prestige Parrot 3 KG") -> Prestige Parrot 3 KG | G70: =IFERROR(__xludf.DUMMYFUNCTION("""COMPUTED_VALUE"""),"برستيج ببغاء 3 كيلو") -> برستيج ببغاء 3 كيلو | H70: =IFERROR(__xludf.DUMMYFUNCTION("""COMPUTED_VALUE"""),"MAFE20201073") -> MAFE20201073 | K70: =IFERROR(__xludf.DUMMYFUNCTION("""COMPUTED_VALUE"""),"فيرسل لاقا ان في") -> فيرسل لاقا ان في | L70: =IFERROR(__xludf.DUMMYFUNCTION("""COMPUTED_VALUE"""),"421796") -> 421796
A71: =IFERROR(__xludf.DUMMYFUNCTION("""COMPUTED_VALUE"""),70.0) -> 70 | B71: =IFERROR(__xludf.DUMMYFUNCTION("""COMPUTED_VALUE"""),"421880") -> 421880 | C71: =IFERROR(__xludf.DUMMYFUNCTION("""COMPUTED_VALUE"""),"P-1-N-010920-2539") -> P-1-N-010920-2539 | E71: =IFERROR(__xludf.DUMMYFUNCTION("""COMPUTED_VALUE"""),"تمت طباعة الشهادة") -> تمت طباعة الشهادة | F71: =IFERROR(__xludf.DUMMYFUNCTION("""COMPUTED_VALUE"""),"Prestige Big Parakeet 1 KG") -> Prestige Big Parakeet 1 KG | G71: =IFERROR(__xludf.DUMMYFUNCTION("""COMPUTED_VALUE"""),"برستيج ببغاء كبير (كروان) 1 كيلو") -> برستيج ببغاء كبير (كروان) 1 كيلو | H71: =IFERROR(__xludf.DUMMYFUNCTION("""COMPUTED_VALUE"""),"MAFE20201072") -> MAFE20201072 | K71: =IFERROR(__xludf.DUMMYFUNCTION("""COMPUTED_VALUE"""),"فيرسل لاقا ان في") -> فيرسل لاقا ان في | L71: =IFERROR(__xludf.DUMMYFUNCTION("""COMPUTED_VALUE"""),"421880") -> 421880
A72: =IFERROR(__xludf.DUMMYFUNCTION("""COMPUTED_VALUE"""),71.0) -> 71 | B72: =IFERROR(__xludf.DUMMYFUNCTION("""COMPUTED_VALUE"""),"421881") -> 421881 | C72: =IFERROR(__xludf.DUMMYFUNCTION("""COMPUTED_VALUE"""),"P-1-N-010920-2540") -> P-1-N-010920-2540 | E72: =IFERROR(__xludf.DUMMYFUNCTION("""COMPUTED_VALUE"""),"تمت طباعة الشهادة") -> تمت طباعة الشهادة | F72: =IFERROR(__xludf.DUMMYFUNCTION("""COMPUTED_VALUE"""),"Prestige Big Parakeet 4 KG") -> Prestige Big Parakeet 4 KG | G72: =IFERROR(__xludf.DUMMYFUNCTION("""COMPUTED_VALUE"""),"برستيج ببغاء كبير (كروان) 4 كيلو") -> برستيج ببغاء كبير (كروان) 4 كيلو | H72: =IFERROR(__xludf.DUMMYFUNCTION("""COMPUTED_VALUE"""),"MAFE20201071") -> MAFE20201071 | K72: =IFERROR(__xludf.DUMMYFUNCTION("""COMPUTED_VALUE"""),"فيرسل لاقا ان في") -> فيرسل لاقا ان في | L72: =IFERROR(__xludf.DUMMYFUNCTION("""COMPUTED_VALUE"""),"421881") -> 421881
A73: =IFERROR(__xludf.DUMMYFUNCTION("""COMPUTED_VALUE"""),72.0) -> 72 | B73: =IFERROR(__xludf.DUMMYFUNCTION("""COMPUTED_VALUE"""),"421521") -> 421521 | C73: =IFERROR(__xludf.DUMMYFUNCTION("""COMPUTED_VALUE"""),"P-1-N-010920-2541") -> P-1-N-010920-2541 | E73: =IFERROR(__xludf.DUMMYFUNCTION("""COMPUTED_VALUE"""),"تمت طباعة الشهادة") -> تمت طباعة الشهادة | F73: =IFERROR(__xludf.DUMMYFUNCTION("""COMPUTED_VALUE"""),"Prestige Tropical Finches 4 KG") -> Prestige Tropical Finches 4 KG | G73: =IFERROR(__xludf.DUMMYFUNCTION("""COMPUTED_VALUE"""),"برستيج عصافير استوائية 4 كيلو") -> برستيج عصافير استوائية 4 كيلو | H73: =IFERROR(__xludf.DUMMYFUNCTION("""COMPUTED_VALUE"""),"MAFE20201132") -> MAFE20201132 | K73: =IFERROR(__xludf.DUMMYFUNCTION("""COMPUTED_VALUE"""),"فيرسل لاقا ان في") -> فيرسل لاقا ان في | L73: =IFERROR(__xludf.DUMMYFUNCTION("""COMPUTED_VALUE"""),"421521") -> 421521
A74: =IFERROR(__xludf.DUMMYFUNCTION("""COMPUTED_VALUE"""),73.0) -> 73 | B74: =IFERROR(__xludf.DUMMYFUNCTION("""COMPUTED_VALUE"""),"421520") -> 421520 | C74: =IFERROR(__xludf.DUMMYFUNCTION("""COMPUTED_VALUE"""),"P-1-N-010920-2542") -> P-1-N-010920-2542 | E74: =IFERROR(__xludf.DUMMYFUNCTION("""COMPUTED_VALUE"""),"تمت طباعة الشهادة") -> تمت طباعة الشهادة | F74: =IFERROR(__xludf.DUMMYFUNCTION("""COMPUTED_VALUE"""),"Prestige Tropical Finches 1 KG") -> Prestige Tropical Finches 1 KG | G74: =IFERROR(__xludf.DUMMYFUNCTION("""COMPUTED_VALUE"""),"برستيج عصافير استوائية 1 كيلو") -> برستيج عصافير استوائية 1 كيلو | H74: =IFERROR(__xludf.DUMMYFUNCTION("""COMPUTED_VALUE"""),"MAFE20201131") -> MAFE20201131 | K74: =IFERROR(__xludf.DUMMYFUNCTION("""COMPUTED_VALUE"""),"فيرسل لاقا ان في") -> فيرسل لاقا ان في | L74: =IFERROR(__xludf.DUMMYFUNCTION("""COMPUTED_VALUE"""),"421520") -> 421520
A75: =IFERROR(__xludf.DUMMYFUNCTION("""COMPUTED_VALUE"""),74.0) -> 74 | B75: =IFERROR(__xludf.DUMMYFUNCTION("""COMPUTED_VALUE"""),"421041") -> 421041 | C75: =IFERROR(__xludf.DUMMYFUNCTION("""COMPUTED_VALUE"""),"P-1-N-010920-2544") -> P-1-N-010920-2544 | E75: =IFERROR(__xludf.DUMMYFUNCTION("""COMPUTED_VALUE"""),"تمت طباعة الشهادة") -> تمت طباعة الشهادة | F75: =IFERROR(__xludf.DUMMYFUNCTION("""COMPUTED_VALUE"""),"Prestige Canary 4 KG") -> Prestige Canary 4 KG | G75: =IFERROR(__xludf.DUMMYFUNCTION("""COMPUTED_VALUE"""),"برستيج كناري 4 كيلو") -> برستيج كناري 4 كيلو | H75: =IFERROR(__xludf.DUMMYFUNCTION("""COMPUTED_VALUE"""),"MAFE20201092") -> MAFE20201092 | K75: =IFERROR(__xludf.DUMMYFUNCTION("""COMPUTED_VALUE"""),"فيرسل لاقا ان في") -> فيرسل لاقا ان في | L75: =IFERROR(__xludf.DUMMYFUNCTION("""COMPUTED_VALUE"""),"421041") -> 421041
A76: =IFERROR(__xludf.DUMMYFUNCTION("""COMPUTED_VALUE"""),75.0) -> 75 | B76: =IFERROR(__xludf.DUMMYFUNCTION("""COMPUTED_VALUE"""),"421239") -> 421239 | C76: =IFERROR(__xludf.DUMMYFUNCTION("""COMPUTED_VALUE"""),"P-1-N-010920-2546") -> P-1-N-010920-2546 | E76: =IFERROR(__xludf.DUMMYFUNCTION("""COMPUTED_VALUE"""),"تمت طباعة الشهادة") -> تمت طباعة الشهادة | F76: =IFERROR(__xludf.DUMMYFUNCTION("""COMPUTED_VALUE"""),"Prestige European Finches 1 KG") -> Prestige European Finches 1 KG | G76: =IFERROR(__xludf.DUMMYFUNCTION("""COMPUTED_VALUE"""),"برستيج عصافير أوروبية 1 كيلو") -> برستيج عصافير أوروبية 1 كيلو | H76: =IFERROR(__xludf.DUMMYFUNCTION("""COMPUTED_VALUE"""),"MAFE20201070") -> MAFE20201070 | K76: =IFERROR(__xludf.DUMMYFUNCTION("""COMPUTED_VALUE"""),"فيرسل لاقا ان في") -> فيرسل لاقا ان في | L76: =IFERROR(__xludf.DUMMYFUNCTION("""COMPUTED_VALUE"""),"421239") -> 421239
A77: =IFERROR(__xludf.DUMMYFUNCTION("""COMPUTED_VALUE"""),76.0) -> 76 | B77: =IFERROR(__xludf.DUMMYFUNCTION("""COMPUTED_VALUE"""),"170541") -> 170541 | C77: =IFERROR(__xludf.DUMMYFUNCTION("""COMPUTED_VALUE"""),"P-1-N-020920-2561") -> P-1-N-020920-2561 | E77: =IFERROR(__xludf.DUMMYFUNCTION("""COMPUTED_VALUE"""),"تمت طباعة الشهادة") -> تمت طباعة الشهادة | F77: =IFERROR(__xludf.DUMMYFUNCTION("""COMPUTED_VALUE"""),"Profine Adult Chicken & Potatoes 15 KG") -> Profine Adult Chicken & Potatoes 15 KG | G77: =IFERROR(__xludf.DUMMYFUNCTION("""COMPUTED_VALUE"""),"بروفاين من الدجاج و البطاطس للكلاب البالغة 15 كيلو") -> بروفاين من الدجاج و البطاطس للكلاب البالغة 15 كيلو | H77: =IFERROR(__xludf.DUMMYFUNCTION("""COMPUTED_VALUE"""),"MAFE20201091") -> MAFE20201091 | K77: =IFERROR(__xludf.DUMMYFUNCTION("""COMPUTED_VALUE"""),"فافو براها اس ار او") -> فافو براها اس ار او | L77: =IFERROR(__xludf.DUMMYFUNCTION("""COMPUTED_VALUE"""),"170541") -> 170541
A78: =IFERROR(__xludf.DUMMYFUNCTION("""COMPUTED_VALUE"""),77.0) -> 77 | B78: =IFERROR(__xludf.DUMMYFUNCTION("""COMPUTED_VALUE"""),"170543") -> 170543 | C78: =IFERROR(__xludf.DUMMYFUNCTION("""COMPUTED_VALUE"""),"P-1-N-020920-2562") -> P-1-N-020920-2562 | E78: =IFERROR(__xludf.DUMMYFUNCTION("""COMPUTED_VALUE"""),"تمت طباعة الشهادة") -> تمت طباعة الشهادة | F78: =IFERROR(__xludf.DUMMYFUNCTION("""COMPUTED_VALUE"""),"Profine Energy Chicken & Potatoes 15 KG") -> Profine Energy Chicken & Potatoes 15 KG | G78: =IFERROR(__xludf.DUMMYFUNCTION("""COMPUTED_VALUE"""),"بروفاين الطاقة الدجاج و البطاطس 15 كيلو") -> بروفاين الطاقة الدجاج و البطاطس 15 كيلو | H78: =IFERROR(__xludf.DUMMYFUNCTION("""COMPUTED_VALUE"""),"MAFE20201090") -> MAFE20201090 | K78: =IFERROR(__xludf.DUMMYFUNCTION("""COMPUTED_VALUE"""),"فافو براها اس ار او") -> فافو براها اس ار او | L78: =IFERROR(__xludf.DUMMYFUNCTION("""COMPUTED_VALUE"""),"170543") -> 170543
A79: =IFERROR(__xludf.DUMMYFUNCTION("""COMPUTED_VALUE"""),78.0) -> 78 | B79: =IFERROR(__xludf.DUMMYFUNCTION("""COMPUTED_VALUE"""),"170549") -> 170549 | C79: =IFERROR(__xludf.DUMMYFUNCTION("""COMPUTED_VALUE"""),"P-1-N-020920-2563") -> P-1-N-020920-2563 | E79: =IFERROR(__xludf.DUMMYFUNCTION("""COMPUTED_VALUE"""),"تمت طباعة الشهادة") -> تمت طباعة الشهادة | F79: =IFERROR(__xludf.DUMMYFUNCTION("""COMPUTED_VALUE"""),"Profine Adult Lamb & Potatoes 15 KG") -> Profine Adult Lamb & Potatoes 15 KG | G79: =IFERROR(__xludf.DUMMYFUNCTION("""COMPUTED_VALUE"""),"بروفاين لحم الضأن و البطاطس للكلاب البالغة 15 كيلو") -> بروفاين لحم الضأن و البطاطس للكلاب البالغة 15 كيلو | H79: =IFERROR(__xludf.DUMMYFUNCTION("""COMPUTED_VALUE"""),"MAFE20201089") -> MAFE20201089 | K79: =IFERROR(__xludf.DUMMYFUNCTION("""COMPUTED_VALUE"""),"فافو براها اس ار او") -> فافو براها اس ار او | L79: =IFERROR(__xludf.DUMMYFUNCTION("""COMPUTED_VALUE"""),"170549") -> 170549
A80: =IFERROR(__xludf.DUMMYFUNCTION("""COMPUTED_VALUE"""),79.0) -> 79 | B80: =IFERROR(__xludf.DUMMYFUNCTION("""COMPUTED_VALUE"""),"170532") -> 170532 | C80: =IFERROR(__xludf.DUMMYFUNCTION("""COMPUTED_VALUE"""),"P-1-N-020920-2564") -> P-1-N-020920-2564 | E80: =IFERROR(__xludf.DUMMYFUNCTION("""COMPUTED_VALUE"""),"تمت طباعة الشهادة") -> تمت طباعة الشهادة | F80: =IFERROR(__xludf.DUMMYFUNCTION("""COMPUTED_VALUE"""),"Profine Puppy Chicken & Potatoes 15 KG") -> Profine Puppy Chicken & Potatoes 15 KG | G80: =IFERROR(__xludf.DUMMYFUNCTION("""COMPUTED_VALUE"""),"بروفاين الدجاج و البطاطس للكلاب الصغيرة 15 كيلو") -> بروفاين الدجاج و البطاطس للكلاب الصغيرة 15 كيلو | H80: =IFERROR(__xludf.DUMMYFUNCTION("""COMPUTED_VALUE"""),"MAFE20201095") -> MAFE20201095 | K80: =IFERROR(__xludf.DUMMYFUNCTION("""COMPUTED_VALUE"""),"فافو براها اس ار او") -> فافو براها اس ار او | L80: =IFERROR(__xludf.DUMMYFUNCTION("""COMPUTED_VALUE"""),"170532") -> 170532
A81: =IFERROR(__xludf.DUMMYFUNCTION("""COMPUTED_VALUE"""),80.0) -> 80 | B81: =IFERROR(__xludf.DUMMYFUNCTION("""COMPUTED_VALUE"""),"170547") -> 170547 | C81: =IFERROR(__xludf.DUMMYFUNCTION("""COMPUTED_VALUE"""),"P-1-N-020920-2565") -> P-1-N-020920-2565 | E81: =IFERROR(__xludf.DUMMYFUNCTION("""COMPUTED_VALUE"""),"تمت طباعة الشهادة") -> تمت طباعة الشهادة | F81: =IFERROR(__xludf.DUMMYFUNCTION("""COMPUTED_VALUE"""),"Profine Puppy Lamb & Potatoes 15 Kg") -> Profine Puppy Lamb & Potatoes 15 Kg | G81: =IFERROR(__xludf.DUMMYFUNCTION("""COMPUTED_VALUE"""),"بروفاين لحم الضأن و البطاطس للكلاب الصغيرة 15 كيلو") -> بروفاين لحم الضأن و البطاطس للكلاب الصغيرة 15 كيلو | H81: =IFERROR(__xludf.DUMMYFUNCTION("""COMPUTED_VALUE"""),"MAFE20201130") -> MAFE20201130 | K81: =IFERROR(__xludf.DUMMYFUNCTION("""COMPUTED_VALUE"""),"فافو براها اس ار او") -> فافو براها اس ار او | L81: =IFERROR(__xludf.DUMMYFUNCTION("""COMPUTED_VALUE"""),"170547") -> 170547
A82: =IFERROR(__xludf.DUMMYFUNCTION("""COMPUTED_VALUE"""),81.0) -> 81 | B82: =IFERROR(__xludf.DUMMYFUNCTION("""COMPUTED_VALUE"""),"170561") -> 170561 | C82: =IFERROR(__xludf.DUMMYFUNCTION("""COMPUTED_VALUE"""),"P-1-N-020920-2566") -> P-1-N-020920-2566 | E82: =IFERROR(__xludf.DUMMYFUNCTION("""COMPUTED_VALUE"""),"تمت طباعة الشهادة") -> تمت طباعة الشهادة | F82: =IFERROR(__xludf.DUMMYFUNCTION("""COMPUTED_VALUE"""),"Profine Kitten 10 KG") -> Profine Kitten 10 KG | G82: =IFERROR(__xludf.DUMMYFUNCTION("""COMPUTED_VALUE"""),"بروفاين للقطط الصغيرة 10 كيلو") -> بروفاين للقطط الصغيرة 10 كيلو | H82: =IFERROR(__xludf.DUMMYFUNCTION("""COMPUTED_VALUE"""),"MAFE20201100") -> MAFE20201100 | K82: =IFERROR(__xludf.DUMMYFUNCTION("""COMPUTED_VALUE"""),"فافو براها اس ار او") -> فافو براها اس ار او | L82: =IFERROR(__xludf.DUMMYFUNCTION("""COMPUTED_VALUE"""),"170561") -> 170561
A83: =IFERROR(__xludf.DUMMYFUNCTION("""COMPUTED_VALUE"""),82.0) -> 82 | B83: =IFERROR(__xludf.DUMMYFUNCTION("""COMPUTED_VALUE"""),"170560") -> 170560 | C83: =IFERROR(__xludf.DUMMYFUNCTION("""COMPUTED_VALUE"""),"P-1-N-020920-2567") -> P-1-N-020920-2567 | E83: =IFERROR(__xludf.DUMMYFUNCTION("""COMPUTED_VALUE"""),"تمت طباعة الشهادة") -> تمت طباعة الشهادة | F83: =IFERROR(__xludf.DUMMYFUNCTION("""COMPUTED_VALUE"""),"Profine kitten 2 KG") -> Profine kitten 2 KG | G83: =IFERROR(__xludf.DUMMYFUNCTION("""COMPUTED_VALUE"""),"بروفاين للقطط الصغيرة 2 كيلو") -> بروفاين للقطط الصغيرة 2 كيلو | H83: =IFERROR(__xludf.DUMMYFUNCTION("""COMPUTED_VALUE"""),"MAFE20201099") -> MAFE20201099 | K83: =IFERROR(__xludf.DUMMYFUNCTION("""COMPUTED_VALUE"""),"فافو براها اس ار او") -> فافو براها اس ار او | L83: =IFERROR(__xludf.DUMMYFUNCTION("""COMPUTED_VALUE"""),"170560") -> 170560
A84: =IFERROR(__xludf.DUMMYFUNCTION("""COMPUTED_VALUE"""),83.0) -> 83 | B84: =IFERROR(__xludf.DUMMYFUNCTION("""COMPUTED_VALUE"""),"170559") -> 170559 | C84: =IFERROR(__xludf.DUMMYFUNCTION("""COMPUTED_VALUE"""),"P-1-N-020920-2568") -> P-1-N-020920-2568 | E84: =IFERROR(__xludf.DUMMYFUNCTION("""COMPUTED_VALUE"""),"تمت طباعة الشهادة") -> تمت طباعة الشهادة | F84: =IFERROR(__xludf.DUMMYFUNCTION("""COMPUTED_VALUE"""),"Profine Kitten 300 g") -> Profine Kitten 300 g | G84: =IFERROR(__xludf.DUMMYFUNCTION("""COMPUTED_VALUE"""),"بروفاين للقطط الصغيرة 300 جرام") -> بروفاين للقطط الصغيرة 300 جرام | H84: =IFERROR(__xludf.DUMMYFUNCTION("""COMPUTED_VALUE"""),"MAFE20201098") -> MAFE20201098 | K84: =IFERROR(__xludf.DUMMYFUNCTION("""COMPUTED_VALUE"""),"فافو براها اس ار او") -> فافو براها اس ار او | L84: =IFERROR(__xludf.DUMMYFUNCTION("""COMPUTED_VALUE"""),"170559") -> 170559
A85: =IFERROR(__xludf.DUMMYFUNCTION("""COMPUTED_VALUE"""),84.0) -> 84 | B85: =IFERROR(__xludf.DUMMYFUNCTION("""COMPUTED_VALUE"""),"170563") -> 170563 | C85: =IFERROR(__xludf.DUMMYFUNCTION("""COMPUTED_VALUE"""),"P-1-N-020920-2570") -> P-1-N-020920-2570 | E85: =IFERROR(__xludf.DUMMYFUNCTION("""COMPUTED_VALUE"""),"تمت طباعة الشهادة") -> تمت طباعة الشهادة | F85: =IFERROR(__xludf.DUMMYFUNCTION("""COMPUTED_VALUE"""),"Profine Cat Sterilised 2 KG") -> Profine Cat Sterilised 2 KG | G85: =IFERROR(__xludf.DUMMYFUNCTION("""COMPUTED_VALUE"""),"بروفاين للقطط المعقمة 2 كيلو") -> بروفاين للقطط المعقمة 2 كيلو | H85: =IFERROR(__xludf.DUMMYFUNCTION("""COMPUTED_VALUE"""),"MAFE20201124") -> MAFE20201124 | K85: =IFERROR(__xludf.DUMMYFUNCTION("""COMPUTED_VALUE"""),"فافو براها اس ار او") -> فافو براها اس ار او | L85: =IFERROR(__xludf.DUMMYFUNCTION("""COMPUTED_VALUE"""),"170563") -> 170563
A86: =IFERROR(__xludf.DUMMYFUNCTION("""COMPUTED_VALUE"""),85.0) -> 85 | B86: =IFERROR(__xludf.DUMMYFUNCTION("""COMPUTED_VALUE"""),"170564") -> 170564 | C86: =IFERROR(__xludf.DUMMYFUNCTION("""COMPUTED_VALUE"""),"P-1-N-020920-2571") -> P-1-N-020920-2571 | E86: =IFERROR(__xludf.DUMMYFUNCTION("""COMPUTED_VALUE"""),"تمت طباعة الشهادة") -> تمت طباعة الشهادة | F86: =IFERROR(__xludf.DUMMYFUNCTION("""COMPUTED_VALUE"""),"Profine Cat Sterilised 10 KG") -> Profine Cat Sterilised 10 KG | G86: =IFERROR(__xludf.DUMMYFUNCTION("""COMPUTED_VALUE"""),"بروفاين للقطط المعقمة 10 كيلو") -> بروفاين للقطط المعقمة 10 كيلو | H86: =IFERROR(__xludf.DUMMYFUNCTION("""COMPUTED_VALUE"""),"MAFE20201097") -> MAFE20201097 | K86: =IFERROR(__xludf.DUMMYFUNCTION("""COMPUTED_VALUE"""),"فافو براها اس ار او") -> فافو براها اس ار او | L86: =IFERROR(__xludf.DUMMYFUNCTION("""COMPUTED_VALUE"""),"170564") -> 170564
A87: =IFERROR(__xludf.DUMMYFUNCTION("""COMPUTED_VALUE"""),86.0) -> 86 | B87: =IFERROR(__xludf.DUMMYFUNCTION("""COMPUTED_VALUE"""),"170562") -> 170562 | C87: =IFERROR(__xludf.DUMMYFUNCTION("""COMPUTED_VALUE"""),"P-1-N-020920-2572") -> P-1-N-020920-2572 | E87: =IFERROR(__xludf.DUMMYFUNCTION("""COMPUTED_VALUE"""),"تمت طباعة الشهادة") -> تمت طباعة الشهادة | F87: =IFERROR(__xludf.DUMMYFUNCTION("""COMPUTED_VALUE"""),"Profine Sterilised 300 g") -> Profine Sterilised 300 g | G87: =IFERROR(__xludf.DUMMYFUNCTION("""COMPUTED_VALUE"""),"بروفاين للقطط المعقمة 300 جرام") -> بروفاين للقطط المعقمة 300 جرام | H87: =IFERROR(__xludf.DUMMYFUNCTION("""COMPUTED_VALUE"""),"MAFE20201129") -> MAFE20201129 | K87: =IFERROR(__xludf.DUMMYFUNCTION("""COMPUTED_VALUE"""),"فافو براها اس ار او") -> فافو براها اس ار او | L87: =IFERROR(__xludf.DUMMYFUNCTION("""COMPUTED_VALUE"""),"170562") -> 170562
A88: =IFERROR(__xludf.DUMMYFUNCTION("""COMPUTED_VALUE"""),87.0) -> 87 | B88: =IFERROR(__xludf.DUMMYFUNCTION("""COMPUTED_VALUE"""),"170572") -> 170572 | C88: =IFERROR(__xludf.DUMMYFUNCTION("""COMPUTED_VALUE"""),"P-1-N-020920-2573") -> P-1-N-020920-2573 | E88: =IFERROR(__xludf.DUMMYFUNCTION("""COMPUTED_VALUE"""),"تمت طباعة الشهادة") -> تمت طباعة الشهادة | F88: =IFERROR(__xludf.DUMMYFUNCTION("""COMPUTED_VALUE"""),"Profine Cat Derma Adult Salmon 2 KG") -> Profine Cat Derma Adult Salmon 2 KG | G88: =IFERROR(__xludf.DUMMYFUNCTION("""COMPUTED_VALUE"""),"بروفاين دريما للقطط البالغة بالسلمون 2 كيلو") -> بروفاين دريما للقطط البالغة بالسلمون 2 كيلو | H88: =IFERROR(__xludf.DUMMYFUNCTION("""COMPUTED_VALUE"""),"MAFE20201128") -> MAFE20201128 | K88: =IFERROR(__xludf.DUMMYFUNCTION("""COMPUTED_VALUE"""),"فافو براها اس ار او") -> فافو براها اس ار او | L88: =IFERROR(__xludf.DUMMYFUNCTION("""COMPUTED_VALUE"""),"170572") -> 170572
A89: =IFERROR(__xludf.DUMMYFUNCTION("""COMPUTED_VALUE"""),88.0) -> 88 | B89: =IFERROR(__xludf.DUMMYFUNCTION("""COMPUTED_VALUE"""),"170572") -> 170572 | C89: =IFERROR(__xludf.DUMMYFUNCTION("""COMPUTED_VALUE"""),"P-1-N-020920-2574") -> P-1-N-020920-2574 | E89: =IFERROR(__xludf.DUMMYFUNCTION("""COMPUTED_VALUE"""),"تمت طباعة الشهادة") -> تمت طباعة الشهادة | F89: =IFERROR(__xludf.DUMMYFUNCTION("""COMPUTED_VALUE"""),"Profine Cat Derma Adult Salmon 2 KG") -> Profine Cat Derma Adult Salmon 2 KG | G89: =IFERROR(__xludf.DUMMYFUNCTION("""COMPUTED_VALUE"""),"بروفاين ديرما للقطط البالغة بالسلمون 2 كيلو") -> بروفاين ديرما للقطط البالغة بالسلمون 2 كيلو | H89: =IFERROR(__xludf.DUMMYFUNCTION("""COMPUTED_VALUE"""),"MAFE20201127") -> MAFE20201127 | K89: =IFERROR(__xludf.DUMMYFUNCTION("""COMPUTED_VALUE"""),"فافو براها اس ار او") -> فافو براها اس ار او | L89: =IFERROR(__xludf.DUMMYFUNCTION("""COMPUTED_VALUE"""),"170572") -> 170572
A90: =IFERROR(__xludf.DUMMYFUNCTION("""COMPUTED_VALUE"""),89.0) -> 89 | B90: =IFERROR(__xludf.DUMMYFUNCTION("""COMPUTED_VALUE"""),"170573") -> 170573 | C90: =IFERROR(__xludf.DUMMYFUNCTION("""COMPUTED_VALUE"""),"P-1-N-020920-2575") -> P-1-N-020920-2575 | E90: =IFERROR(__xludf.DUMMYFUNCTION("""COMPUTED_VALUE"""),"تمت طباعة الشهادة") -> تمت طباعة الشهادة | F90: =IFERROR(__xludf.DUMMYFUNCTION("""COMPUTED_VALUE"""),"Profine Cat Derma Adult Salmon 10 KG") -> Profine Cat Derma Adult Salmon 10 KG | G90: =IFERROR(__xludf.DUMMYFUNCTION("""COMPUTED_VALUE"""),"بروفاين ديرما للقطط البالغة بالسلمون 10 كيلو") -> بروفاين ديرما للقطط البالغة بالسلمون 10 كيلو | H90: =IFERROR(__xludf.DUMMYFUNCTION("""COMPUTED_VALUE"""),"MAFE20201126") -> MAFE20201126 | K90: =IFERROR(__xludf.DUMMYFUNCTION("""COMPUTED_VALUE"""),"فافو براها اس ار او") -> فافو براها اس ار او | L90: =IFERROR(__xludf.DUMMYFUNCTION("""COMPUTED_VALUE"""),"170573") -> 170573
A91: =IFERROR(__xludf.DUMMYFUNCTION("""COMPUTED_VALUE"""),90.0) -> 90 | B91: =IFERROR(__xludf.DUMMYFUNCTION("""COMPUTED_VALUE"""),"170571") -> 170571 | C91: =IFERROR(__xludf.DUMMYFUNCTION("""COMPUTED_VALUE"""),"P-1-N-020920-2576") -> P-1-N-020920-2576 | E91: =IFERROR(__xludf.DUMMYFUNCTION("""COMPUTED_VALUE"""),"تمت طباعة الشهادة") -> تمت طباعة الشهادة | F91: =IFERROR(__xludf.DUMMYFUNCTION("""COMPUTED_VALUE"""),"Profine Cat Derma Adult Salmon 300 g") -> Profine Cat Derma Adult Salmon 300 g | G91: =IFERROR(__xludf.DUMMYFUNCTION("""COMPUTED_VALUE"""),"بروفاين ديرما للقطط البالغة بالسلمون 300 جرام") -> بروفاين ديرما للقطط البالغة بالسلمون 300 جرام | H91: =IFERROR(__xludf.DUMMYFUNCTION("""COMPUTED_VALUE"""),"MAFE20201088") -> MAFE20201088 | K91: =IFERROR(__xludf.DUMMYFUNCTION("""COMPUTED_VALUE"""),"فافو براها اس ار او") -> فافو براها اس ار او | L91: =IFERROR(__xludf.DUMMYFUNCTION("""COMPUTED_VALUE"""),"170571") -> 170571
A92: =IFERROR(__xludf.DUMMYFUNCTION("""COMPUTED_VALUE"""),91.0) -> 91 | B92: =IFERROR(__xludf.DUMMYFUNCTION("""COMPUTED_VALUE"""),"170566") -> 170566 | C92: =IFERROR(__xludf.DUMMYFUNCTION("""COMPUTED_VALUE"""),"P-1-N-020920-2578") -> P-1-N-020920-2578 | E92: =IFERROR(__xludf.DUMMYFUNCTION("""COMPUTED_VALUE"""),"تمت طباعة الشهادة") -> تمت طباعة الشهادة | F92: =IFERROR(__xludf.DUMMYFUNCTION("""COMPUTED_VALUE"""),"Profine Cat Original Adult Chincken 2 Kg") -> Profine Cat Original Adult Chincken 2 Kg | G92: =IFERROR(__xludf.DUMMYFUNCTION("""COMPUTED_VALUE"""),"بروفاين أوريجنال للقطط البالغة بالدجاج 2 كيلو") -> بروفاين أوريجنال للقطط البالغة بالدجاج 2 كيلو | H92: =IFERROR(__xludf.DUMMYFUNCTION("""COMPUTED_VALUE"""),"MAFE20201087") -> MAFE20201087 | K92: =IFERROR(__xludf.DUMMYFUNCTION("""COMPUTED_VALUE"""),"فافو براها اس ار او") -> فافو براها اس ار او | L92: =IFERROR(__xludf.DUMMYFUNCTION("""COMPUTED_VALUE"""),"170566") -> 170566
A93: =IFERROR(__xludf.DUMMYFUNCTION("""COMPUTED_VALUE"""),92.0) -> 92 | B93: =IFERROR(__xludf.DUMMYFUNCTION("""COMPUTED_VALUE"""),"170567") -> 170567 | C93: =IFERROR(__xludf.DUMMYFUNCTION("""COMPUTED_VALUE"""),"P-1-N-020920-2579") -> P-1-N-020920-2579 | E93: =IFERROR(__xludf.DUMMYFUNCTION("""COMPUTED_VALUE"""),"تمت طباعة الشهادة") -> تمت طباعة الشهادة | F93: =IFERROR(__xludf.DUMMYFUNCTION("""COMPUTED_VALUE"""),"Profine Cat Original Adult Chicken 10 KG") -> Profine Cat Original Adult Chicken 10 KG | G93: =IFERROR(__xludf.DUMMYFUNCTION("""COMPUTED_VALUE"""),"بروفاين أوريجنال للقطط البالغة بالدجاج 10 كيلو") -> بروفاين أوريجنال للقطط البالغة بالدجاج 10 كيلو | H93: =IFERROR(__xludf.DUMMYFUNCTION("""COMPUTED_VALUE"""),"MAFE20201086") -> MAFE20201086 | K93: =IFERROR(__xludf.DUMMYFUNCTION("""COMPUTED_VALUE"""),"فافو براها اس ار او") -> فافو براها اس ار او | L93: =IFERROR(__xludf.DUMMYFUNCTION("""COMPUTED_VALUE"""),"170567") -> 170567
A94: =IFERROR(__xludf.DUMMYFUNCTION("""COMPUTED_VALUE"""),93.0) -> 93 | B94: =IFERROR(__xludf.DUMMYFUNCTION("""COMPUTED_VALUE"""),"170565") -> 170565 | C94: =IFERROR(__xludf.DUMMYFUNCTION("""COMPUTED_VALUE"""),"P-1-N-020920-2580") -> P-1-N-020920-2580 | E94: =IFERROR(__xludf.DUMMYFUNCTION("""COMPUTED_VALUE"""),"تمت طباعة الشهادة") -> تمت طباعة الشهادة | F94: =IFERROR(__xludf.DUMMYFUNCTION("""COMPUTED_VALUE"""),"Profine Cat Original Adult Chicken 300 g") -> Profine Cat Original Adult Chicken 300 g | G94: =IFERROR(__xludf.DUMMYFUNCTION("""COMPUTED_VALUE"""),"بروفاين أوريجنال للقطط البالغة بالدجاج 300 جرام") -> بروفاين أوريجنال للقطط البالغة بالدجاج 300 جرام | H94: =IFERROR(__xludf.DUMMYFUNCTION("""COMPUTED_VALUE"""),"MAFE20201085") -> MAFE20201085 | K94: =IFERROR(__xludf.DUMMYFUNCTION("""COMPUTED_VALUE"""),"فافو براها اس ار او") -> فافو براها اس ار او | L94: =IFERROR(__xludf.DUMMYFUNCTION("""COMPUTED_VALUE"""),"170565") -> 170565
